Workbook

Sheet pay data
A1: net pnl | B1: 880000 | C1: =B1*0.7 -> 616000 | G1: net liq | H1: 1843600
A2: salary | B2: 115000 | G2: energy | H2: -110860
A3: current bonus | B3: 34200 | G3: expense | H3: -171902
H4: =SUM(H1:H3) -> 1560838
A5: Distribution | B5: Total Pay | C5: Addt'l Pay | D5: % | G5: ytd | H5: 193200
A6: 250000 | B6: 115000 | C6: =B6-$B$2 -> 0 | D6: =B6/A6 -> 0.46 | E6: =A6*0.7 -> 175000 | F6: =B6/E6 -> 0.65714286 | G6: last yr adj | H6: -15295
A7: 500000 | B7: 135000 | C7: =B7-$B$2 -> 20000 | D7: =B7/A7 -> 0.27 | E7: =A7*0.7 -> 350000 | F7: =B7/E7 -> 0.38571429 | G7: fut pay | H7: 0
A8: 750000 | B8: 155000 | C8: =B8-$B$2 -> 40000 | D8: =B8/A8 -> 0.20666667 | E8: =A8*0.7 -> 525000 | F8: =B8/E8 -> 0.2952381 | H8: =SUM(H5:H7) -> 177905
A9: 1000000 | B9: 167000 | C9: =B9-$B$2 -> 52000 | D9: =B9/A9 -> 0.167 | E9: =A9*0.7 -> 700000 | F9: =B9/E9 -> 0.23857143
A10: 1250000 | B10: 187000 | C10: =B10-$B$2 -> 72000 | D10: =B10/A10 -> 0.1496 | E10: =A10*0.7 -> 875000 | F10: =B10/E10 -> 0.21371429 | H10: =H8+H4 -> 1738743
A11: 1500000 | B11: 208000 | C11: =B11-$B$2 -> 93000 | D11: =B11/A11 -> 0.13866667 | E11: =A11*0.7 -> 1050000 | F11: =B11/E11 -> 0.19809524 | H11: =H10/A13 -> 0.8693715
A12: 1750000 | B12: 228000 | C12: =B12-$B$2 -> 113000 | D12: =B12/A12 -> 0.13028571 | E12: =A12*0.7 -> 1225000 | F12: =B12/E12 -> 0.18612245 | H12: =H11*B13 -> 219081.62
A13: 2000000 | B13: 252000 | C13: =B13-$B$2 -> 137000 | D13: =B13/A13 -> 0.126 | E13: =A13*0.7 -> 1400000 | F13: =B13/E13 -> 0.18
A14: 2250000 | B14: 272000 | C14: =B14-$B$2 -> 157000 | D14: =B14/A14 -> 0.12088889 | E14: =A14*0.7 -> 1575000 | F14: =B14/E14 -> 0.17269841 | H14: =H12-H8 -> 41176.618
A15: 2500000 | B15: 292000 | C15: =B15-$B$2 -> 177000 | D15: =B15/A15 -> 0.1168 | E15: =A15*0.7 -> 1750000 | F15: =B15/E15 -> 0.16685714
A16: 2750000 | B16: 316000 | C16: =B16-$B$2 -> 201000 | D16: =B16/A16 -> 0.11490909 | E16: =A16*0.7 -> 1925000 | F16: =B16/E16 -> 0.16415584
A17: 3000000 | B17: 340000 | C17: =B17-$B$2 -> 225000 | D17: =B17/A17 -> 0.11333333 | E17: =A17*0.7 -> 2100000 | F17: =B17/E17 -> 0.16190476
A18: 3250000 | B18: 360000 | C18: =B18-$B$2 -> 245000 | D18: =B18/A18 -> 0.11076923 | E18: =A18*0.7 -> 2275000 | F18: =B18/E18 -> 0.15824176
A19: 3500000 | B19: 380000 | C19: =B19-$B$2 -> 265000 | D19: =B19/A19 -> 0.10857143 | E19: =A19*0.7 -> 2450000 | F19: =B19/E19 -> 0.15510204 | H19: =1522279+23000 -> 1545279
A20: 3750000 | B20: 400000 | C20: =B20-$B$2 -> 285000 | D20: =B20/A20 -> 0.10666667 | E20: =A20*0.7 -> 2625000 | F20: =B20/E20 -> 0.15238095
A21: 4000000 | B21: 420000 | C21: =B21-$B$2 -> 305000 | D21: =B21/A21 -> 0.105 | E21: =A21*0.7 -> 2800000 | F21: =B21/E21 -> 0.15 | H21: =H19+H5 -> 1738479
A22: 4250000 | B22: 440000 | C22: =B22-$B$2 -> 325000 | D22: =B22/A22 -> 0.10352941 | E22: =A22*0.7 -> 2975000 | F22: =B22/E22 -> 0.14789916
A23: 4500000 | B23: 460000 | C23: =B23-$B$2 -> 345000 | D23: =B23/A23 -> 0.10222222 | E23: =A23*0.7 -> 3150000 | F23: =B23/E23 -> 0.14603175
A24: 4750000 | B24: 480000 | C24: =B24-$B$2 -> 365000 | D24: =B24/A24 -> 0.10105263 | E24: =A24*0.7 -> 3325000 | F24: =B24/E24 -> 0.1443609
A25: 5000000 | B25: 500000 | C25: =B25-$B$2 -> 385000 | D25: =B25/A25 -> 0.1 | E25: =A25*0.7 -> 3500000 | F25: =B25/E25 -> 0.14285714
A26: 5250000 | B26: 520000 | C26: =B26-$B$2 -> 405000 | D26: =B26/A26 -> 0.099047619 | E26: =A26*0.7 -> 3675000 | F26: =B26/E26 -> 0.1414966
A27: 5500000 | B27: 540000 | C27: =B27-$B$2 -> 425000 | D27: =B27/A27 -> 0.098181818 | E27: =A27*0.7 -> 3850000 | F27: =B27/E27 -> 0.14025974
A28: 5750000 | B28: 560000 | C28: =B28-$B$2 -> 445000 | D28: =B28/A28 -> 0.097391304 | E28: =A28*0.7 -> 4025000 | F28: =B28/E28 -> 0.13913043
A29: 6000000 | B29: 580000 | C29: =B29-$B$2 -> 465000 | D29: =B29/A29 -> 0.096666667 | E29: =A29*0.7 -> 4200000 | F29: =B29/E29 -> 0.13809524
A30: 6250000 | B30: 600000 | C30: =B30-$B$2 -> 485000 | D30: =B30/A30 -> 0.096 | E30: =A30*0.7 -> 4375000 | F30: =B30/E30 -> 0.13714286
A31: 6500000 | B31: 620000 | C31: =B31-$B$2 -> 505000 | D31: =B31/A31 -> 0.095384615 | E31: =A31*0.7 -> 4550000 | F31: =B31/E31 -> 0.13626374
A32: 6750000 | B32: 640000 | C32: =B32-$B$2 -> 525000 | D32: =B32/A32 -> 0.094814815 | E32: =A32*0.7 -> 4725000 | F32: =B32/E32 -> 0.13544974
A33: 7000000 | B33: 660000 | C33: =B33-$B$2 -> 545000 | D33: =B33/A33 -> 0.094285714 | E33: =A33*0.7 -> 4900000 | F33: =B33/E33 -> 0.13469388
... A45: 10000000 | B45: 900000 | C45: =B45-$B$2 -> 785000 | D45: =B45/A45 -> 0.09 | E45: =A45*0.7 -> 7000000 | F45: =B45/E45 -> 0.12857143

Sheet PnL Data
A1: % days positive | B1: =COUNTIF('Daily PnL Log'!$J$3:$J$1972,">0")/COUNT('Daily PnL Log'!$J$3:$J$1972) -> 0.54732824
A2: % days negative | B2: =COUNTIF('Daily PnL Log'!$J$3:$J$1972,"<0")/COUNT('Daily PnL Log'!$J$3:$J$1972) -> 0.45267176
A4: avg up day | B4: =AVERAGEIF('Daily PnL Log'!$J$3:$J$1972,">0") -> 37481.962
A5: avg down day | B5: =AVERAGEIF('Daily PnL Log'!$J$3:$J$1972,"<0") -> -29647.7
A7: EV | B7: =(B4*B1)+(B5*B2) -> 7094.26
A8: annualized EV | B8: =B7*251 -> 1780659.3
A11: Column1 | B11: soybeans | C11: meal | D11: oil | E11: corn | F11: wheat | G11: kc
A12: % days positive | B12: =COUNTIF('Daily PnL Log'!$C$3:$C$1972,">0")/COUNT('Daily PnL Log'!$C$3:$C$1972) -> 0.50687023 | C12: =COUNTIF('Daily PnL Log'!$D$3:$D$1972,">0")/COUNT('Daily PnL Log'!$D$3:$D$1972) -> 0.49694656 | D12: =COUNTIF('Daily PnL Log'!$E$3:$E$1972,">0")/COUNT('Daily PnL Log'!$E$3:$E$1972) -> 0.37022901 | E12: =COUNTIF('Daily PnL Log'!$F$3:$F$1972,">0")/COUNT('Daily PnL Log'!$F$3:$F$1972) -> 0.50458015 | F12: =COUNTIF('Daily PnL Log'!$G$3:$G$1972,">0")/COUNT('Daily PnL Log'!$G$3:$G$1972) -> 0.51221374 | G12: =COUNTIF('Daily PnL Log'!$H$3:$H$1972,">0")/COUNTIFS('Daily PnL Log'!$H$3:$H$1972,"<>0",'Daily PnL Log'!$H$3:$H$1972,"<>") -> 0.46449704
A13: % days negative | B13: =COUNTIF('Daily PnL Log'!$C$3:$C$1972,"<0")/COUNT('Daily PnL Log'!$C$3:$C$1972) -> 0.49312977 | C13: =COUNTIF('Daily PnL Log'!$D$3:$D$1972,"<0")/COUNT('Daily PnL Log'!$D$3:$D$1972) -> 0.50305344 | D13: =COUNTIF('Daily PnL Log'!$E$3:$E$1972,"<0")/COUNT('Daily PnL Log'!$E$3:$E$1972) -> 0.3519084 | E13: =COUNTIF('Daily PnL Log'!$F$3:$F$1972,"<0")/COUNT('Daily PnL Log'!$F$3:$F$1972) -> 0.49541985 | F13: =COUNTIF('Daily PnL Log'!$G$3:$G$1972,"<0")/COUNT('Daily PnL Log'!$G$3:$G$1972) -> 0.48778626 | G13: =COUNTIF('Daily PnL Log'!$H$3:$H$1972,"<0")/COUNTIFS('Daily PnL Log'!$H$3:$H$1972,"<>0",'Daily PnL Log'!$H$3:$H$1972,"<>") -> 0.53550296
A15: avg up day | B15: =AVERAGEIF('Daily PnL Log'!$C$3:$C$1972,">0") -> 24015.196 | C15: =AVERAGEIF('Daily PnL Log'!$D$3:$D$1972,">0") -> 15836.107 | D15: =AVERAGEIF('Daily PnL Log'!$E$3:$E$1972,">0") -> 5530.9394 | E15: =AVERAGEIF('Daily PnL Log'!$F$3:$F$1972,">0") -> 14299.358 | F15: =AVERAGEIF('Daily PnL Log'!$G$3:$G$1972,">0") -> 14680.236 | G15: =AVERAGEIF('Daily PnL Log'!$H$3:$H$1972,">0") -> 4618.4217
A16: avg down day | B16: =AVERAGEIF('Daily PnL Log'!$C$3:$C$1972,"<0") -> -15903.896 | C16: =AVERAGEIF('Daily PnL Log'!$D$3:$D$1972,"<0") -> -12865.121 | D16: =AVERAGEIF('Daily PnL Log'!$E$3:$E$1972,"<0") -> -6986.604 | E16: =AVERAGEIF('Daily PnL Log'!$F$3:$F$1972,"<0") -> -13323.445 | F16: =AVERAGEIF('Daily PnL Log'!$G$3:$G$1972,"<0") -> -13104.973 | G16: =AVERAGEIF('Daily PnL Log'!$H$3:$H$1972,"<0") -> -4038.4796
A18: EV | B18: =(B15*B12)+(B16*B13) -> 4329.9032 | C18: =(C15*C12)+(C16*C13) -> 1397.8556 | D18: =(D15*D12)+(D16*D13) -> -410.93043 | E18: =(E15*E12)+(E16*E13) -> 614.47305 | F18: =(F15*F12)+(F16*F13) -> 1126.9928 | G18: =(G15*G12)+(G16*G13) -> -17.374556
A19: annualized EV | B19: =B18*251 -> 1086805.7 | C19: =C18*251 -> 350861.77 | D19: =D18*251 -> -103143.54 | E19: =E18*251 -> 154232.74 | F19: =F18*251 -> 282875.2 | G19: =G18*251 -> -4361.0136
A23: OC Notional | B23: 7500000
A24: Net Liq | B24: .
A25: Cash | B25: 500000
A26: Energies TE | B26: 0
A27: Expense | B27: -140000
B28: =SUM(B23:B27) -> 7860000
A30: expiry | B30: 45828
A31: int | B31: 0.0395
A32: dte | B32: =B30-TODAY() -> -244
A33: daily rate | B33: =(B31/365)*B32 -> -0.026405479
A35: int | B35: =B33*B28 -> -207547.07
A36: daily int | B36: =B35/B32 -> 850.60274
A38: itm prem | B38: 58.165
A39: parity | B39: =B38*B33 -> -1.5358747

Sheet Daily PnL Log
B1: TOTALS | C1: =SUM(Table5[Beans]) -> 5672173.2 | D1: =SUM(Table5[Meal]) -> 1831190.9 | E1: =SUM(Table5[Oil]) -> -538318.86 | F1: =SUM(Table5[Corn]) -> 804959.7 | G1: =SUM(Table5[Wheat]) -> 1476360.6 | H1: =SUM(Table5[KC Wheat]) -> -11745.2 | I1: =SUM(Table5[Energies]) -> 58860.25 | J1: =SUM(Table5[Total PnL]) -> 9293480.6 | K1: =SUM(Table5[Commissions]) -> -161438.06 | L1: =SUM(Table5[Clr/brk fees]) -> -988783.83 | M1: =SUM(Table5[Total Fees]) -> -1150221.9 | N1: =SUM(Table5[Net PnL]) -> 8143258.7 | W1: =AVERAGE(Table5[Margin]) -> 677503.86 | X1: =SUM(Table5[RoM]) -> 11.832013 | Y1: =SUM(Table5[Expenses]) -> -1290401.8 | Z1: =SUM(Table5[Int]) -> 442465.41 | AA1: =SUM(Table5[Distributions]) -> -5977310.9 | AB1: =SUM(Table5[Bonuses]) -> -200825.87
A2: Month | B2: Date | C2: Beans | D2: Meal | E2: Oil | F2: Corn | G2: Wheat | H2: KC Wheat | I2: Energies | J2: Total PnL | K2: Commissions | L2: Clr/brk fees | M2: Total Fees | N2: Net PnL | O2: Cum Beans | P2: Cum Meal | Q2: Cum Oil | R2: Cum Corn | S2: Cum Wheat | T2: Cum KC | U2: Cum Brent | V2: Cum PnL | W2: Margin | X2: RoM | Y2: Expenses | Z2: Int | AA2: Distributions | AB2: Bonuses | AC2: Net Liq
A3: =TEXT(B3,"mmm") -> Dec | B3: 44166 | C3: 26392 | D3: -6809 | E3: 16996 | F3: 51822 | G3: -8504 | H3: -453 | I3: 0 | J3: =IF(SUM(C3:I3)=0,"",SUM(C3:I3)) -> 79444 | K3: -343 | L3: -789 | M3: =IF(SUM(K3:L3)=0,"",SUM(K3:L3)) -> -1132 | N3: =IFERROR(J3+M3,"") -> 78312 | O3: =Table5[[#This Row],[Beans]] -> 26392 | P3: =Table5[[#This Row],[Meal]] -> -6809 | Q3: =Table5[[#This Row],[Oil]] -> 16996 | R3: =Table5[[#This Row],[Corn]] -> 51822 | S3: =Table5[[#This Row],[Wheat]] -> -8504 | T3: =Table5[[#This Row],[KC Wheat]] -> -453 | U3: =Table5[[#This Row],[Energies]] -> 0 | V3: =N3 -> 78312 | W3: 511504 | X3: =IFERROR(N3/W3,"") -> 0.15310144 | Y3: -4534.44 | AC3: 514915
A4: =TEXT(B4,"mmm") -> Dec | B4: 44167 | C4: -34672 | D4: -2480 | E4: 3917 | F4: -46548 | G4: 18015 | H4: 4023 | I4: 0 | J4: =IF(SUM(C4:I4)=0,"",SUM(C4:I4)) -> -57745 | K4: -201.2 | L4: -461.86 | M4: =IF(SUM(K4:L4)=0,"",SUM(K4:L4)) -> -663.06 | N4: =IFERROR(J4+M4,"") -> -58408.06 | O4: =IF(Table5[[#This Row],[Beans]]="","",O3+Table5[[#This Row],[Beans]]) -> -8280 | P4: =IF(Table5[[#This Row],[Meal]]="","",P3+Table5[[#This Row],[Meal]]) -> -9289 | Q4: =IF(Table5[[#This Row],[Oil]]="","",Q3+Table5[[#This Row],[Oil]]) -> 20913 | R4: =IF(Table5[[#This Row],[Corn]]="","",R3+Table5[[#This Row],[Corn]]) -> 5274 | S4: =IF(Table5[[#This Row],[Wheat]]="","",S3+Table5[[#This Row],[Wheat]]) -> 9511 | T4: =IF(Table5[[#This Row],[KC Wheat]]="","",T3+Table5[[#This Row],[KC Wheat]]) -> 3570 | U4: =IF(Table5[[#This Row],[Energies]]="","",U3+Table5[[#This Row],[Energies]]) -> 0 | V4: =IF(N4<>"",IFERROR(V3+N4,""),"") -> 19903.94 | W4: 535156 | X4: =IFERROR(N4/W4,"") -> -0.10914212 | AC4: 485194.5
A5: =TEXT(B5,"mmm") -> Dec | B5: 44168 | C5: -4247 | D5: 13770 | E5: -301 | F5: -21998 | G5: 600.2 | H5: -752 | I5: 0 | J5: =IF(SUM(C5:I5)=0,"",SUM(C5:I5)) -> -12927.8 | K5: -110.1 | L5: -253.23 | M5: =IF(SUM(K5:L5)=0,"",SUM(K5:L5)) -> -363.33 | N5: =IFERROR(J5+M5,"") -> -13291.13 | O5: =IF(Table5[[#This Row],[Beans]]="","",O4+Table5[[#This Row],[Beans]]) -> -12527 | P5: =IF(Table5[[#This Row],[Meal]]="","",P4+Table5[[#This Row],[Meal]]) -> 4481 | Q5: =IF(Table5[[#This Row],[Oil]]="","",Q4+Table5[[#This Row],[Oil]]) -> 20612 | R5: =IF(Table5[[#This Row],[Corn]]="","",R4+Table5[[#This Row],[Corn]]) -> -16724 | S5: =IF(Table5[[#This Row],[Wheat]]="","",S4+Table5[[#This Row],[Wheat]]) -> 10111.2 | T5: =IF(Table5[[#This Row],[KC Wheat]]="","",T4+Table5[[#This Row],[KC Wheat]]) -> 2818 | U5: =IF(Table5[[#This Row],[Energies]]="","",U4+Table5[[#This Row],[Energies]]) -> 0 | V5: =IF(N5<>"",IFERROR(V4+N5,""),"") -> 6612.81 | W5: 537434 | X5: =IFERROR(N5/W5,"") -> -0.02473072 | AC5: 450137.72
A6: =TEXT(B6,"mmm") -> Dec | B6: 44169 | C6: -2523 | D6: -2071 | E6: -9040 | F6: 85116 | G6: -8326 | H6: -1175 | I6: 0 | J6: =IF(SUM(C6:I6)=0,"",SUM(C6:I6)) -> 61981 | K6: -229 | L6: -512.67 | M6: =IF(SUM(K6:L6)=0,"",SUM(K6:L6)) -> -741.67 | N6: =IFERROR(J6+M6,"") -> 61239.33 | O6: =IF(Table5[[#This Row],[Beans]]="","",O5+Table5[[#This Row],[Beans]]) -> -15050 | P6: =IF(Table5[[#This Row],[Meal]]="","",P5+Table5[[#This Row],[Meal]]) -> 2410 | Q6: =IF(Table5[[#This Row],[Oil]]="","",Q5+Table5[[#This Row],[Oil]]) -> 11572 | R6: =IF(Table5[[#This Row],[Corn]]="","",R5+Table5[[#This Row],[Corn]]) -> 68392 | S6: =IF(Table5[[#This Row],[Wheat]]="","",S5+Table5[[#This Row],[Wheat]]) -> 1785.2 | T6: =IF(Table5[[#This Row],[KC Wheat]]="","",T5+Table5[[#This Row],[KC Wheat]]) -> 1643 | U6: =IF(Table5[[#This Row],[Energies]]="","",U5+Table5[[#This Row],[Energies]]) -> 0 | V6: =IF(N6<>"",IFERROR(V5+N6,""),"") -> 67852.14 | W6: 502836 | X6: =IFERROR(N6/W6,"") -> 0.12178788 | AC6: 507061.65
A7: =TEXT(B7,"mmm") -> Dec | B7: 44172 | C7: -4397 | D7: -22464 | E7: -4352 | F7: -20784 | G7: 9686 | H7: -266 | I7: 0 | J7: =IF(SUM(C7:I7)=0,"",SUM(C7:I7)) -> -42577 | K7: -173.9 | L7: -399.97 | M7: =IF(SUM(K7:L7)=0,"",SUM(K7:L7)) -> -573.87 | N7: =IFERROR(J7+M7,"") -> -43150.87 | O7: =IF(Table5[[#This Row],[Beans]]="","",O6+Table5[[#This Row],[Beans]]) -> -19447 | P7: =IF(Table5[[#This Row],[Meal]]="","",P6+Table5[[#This Row],[Meal]]) -> -20054 | Q7: =IF(Table5[[#This Row],[Oil]]="","",Q6+Table5[[#This Row],[Oil]]) -> 7220 | R7: =IF(Table5[[#This Row],[Corn]]="","",R6+Table5[[#This Row],[Corn]]) -> 47608 | S7: =IF(Table5[[#This Row],[Wheat]]="","",S6+Table5[[#This Row],[Wheat]]) -> 11471.2 | T7: =IF(Table5[[#This Row],[KC Wheat]]="","",T6+Table5[[#This Row],[KC Wheat]]) -> 1377 | U7: =IF(Table5[[#This Row],[Energies]]="","",U6+Table5[[#This Row],[Energies]]) -> 0 | V7: =IF(N7<>"",IFERROR(V6+N7,""),"") -> 24701.27 | W7: 527603 | X7: =IFERROR(N7/W7,"") -> -0.081786627 | AC7: 496410.78
A8: =TEXT(B8,"mmm") -> Dec | B8: 44173 | C8: 24437 | D8: -12518 | E8: 3376 | F8: 12578 | G8: -5257 | H8: 143.6 | I8: 0 | J8: =IF(SUM(C8:I8)=0,"",SUM(C8:I8)) -> 22759.6 | K8: -221 | L8: -504 | M8: =IF(SUM(K8:L8)=0,"",SUM(K8:L8)) -> -725 | N8: =IFERROR(J8+M8,"") -> 22034.6 | O8: =IF(Table5[[#This Row],[Beans]]="","",O7+Table5[[#This Row],[Beans]]) -> 4990 | P8: =IF(Table5[[#This Row],[Meal]]="","",P7+Table5[[#This Row],[Meal]]) -> -32572 | Q8: =IF(Table5[[#This Row],[Oil]]="","",Q7+Table5[[#This Row],[Oil]]) -> 10596 | R8: =IF(Table5[[#This Row],[Corn]]="","",R7+Table5[[#This Row],[Corn]]) -> 60186 | S8: =IF(Table5[[#This Row],[Wheat]]="","",S7+Table5[[#This Row],[Wheat]]) -> 6214.2 | T8: =IF(Table5[[#This Row],[KC Wheat]]="","",T7+Table5[[#This Row],[KC Wheat]]) -> 1520.6 | U8: =IF(Table5[[#This Row],[Energies]]="","",U7+Table5[[#This Row],[Energies]]) -> 0 | V8: =IF(N8<>"",IFERROR(V7+N8,""),"") -> 46735.87 | W8: 537111 | X8: =IFERROR(N8/W8,"") -> 0.041024295 | AC8: 511167.51
A9: =TEXT(B9,"mmm") -> Dec | B9: 44174 | C9: -13534.5 | D9: 13236.5 | E9: 5410.5 | F9: -265 | G9: -3936.1 | H9: 3708 | I9: 0 | J9: =IF(SUM(C9:I9)=0,"",SUM(C9:I9)) -> 4619.4 | K9: -225 | L9: -518 | M9: =IF(SUM(K9:L9)=0,"",SUM(K9:L9)) -> -743 | N9: =IFERROR(J9+M9,"") -> 3876.4 | O9: =IF(Table5[[#This Row],[Beans]]="","",O8+Table5[[#This Row],[Beans]]) -> -8544.5 | P9: =IF(Table5[[#This Row],[Meal]]="","",P8+Table5[[#This Row],[Meal]]) -> -19335.5 | Q9: =IF(Table5[[#This Row],[Oil]]="","",Q8+Table5[[#This Row],[Oil]]) -> 16006.5 | R9: =IF(Table5[[#This Row],[Corn]]="","",R8+Table5[[#This Row],[Corn]]) -> 59921 | S9: =IF(Table5[[#This Row],[Wheat]]="","",S8+Table5[[#This Row],[Wheat]]) -> 2278.1 | T9: =IF(Table5[[#This Row],[KC Wheat]]="","",T8+Table5[[#This Row],[KC Wheat]]) -> 5228.6 | U9: =IF(Table5[[#This Row],[Energies]]="","",U8+Table5[[#This Row],[Energies]]) -> 0 | V9: =IF(N9<>"",IFERROR(V8+N9,""),"") -> 50612.27 | W9: 570452 | X9: =IFERROR(N9/W9,"") -> 0.0067953132 | Y9: -494.32 | AC9: 477770.02
A10: =TEXT(B10,"mmm") -> Dec | B10: 44175 | C10: 16649 | D10: -1085.7 | E10: 4059.7 | F10: 43227.7 | G10: 32150.9 | H10: 2123 | I10: 0 | J10: =IF(SUM(C10:I10)=0,"",SUM(C10:I10)) -> 97124.6 | K10: -365.8 | L10: -841 | M10: =IF(SUM(K10:L10)=0,"",SUM(K10:L10)) -> -1206.8 | N10: =IFERROR(J10+M10,"") -> 95917.8 | O10: =IF(Table5[[#This Row],[Beans]]="","",O9+Table5[[#This Row],[Beans]]) -> 8104.5 | P10: =IF(Table5[[#This Row],[Meal]]="","",P9+Table5[[#This Row],[Meal]]) -> -20421.2 | Q10: =IF(Table5[[#This Row],[Oil]]="","",Q9+Table5[[#This Row],[Oil]]) -> 20066.2 | R10: =IF(Table5[[#This Row],[Corn]]="","",R9+Table5[[#This Row],[Corn]]) -> 103148.7 | S10: =IF(Table5[[#This Row],[Wheat]]="","",S9+Table5[[#This Row],[Wheat]]) -> 34429 | T10: =IF(Table5[[#This Row],[KC Wheat]]="","",T9+Table5[[#This Row],[KC Wheat]]) -> 7351.6 | U10: =IF(Table5[[#This Row],[Energies]]="","",U9+Table5[[#This Row],[Energies]]) -> 0 | V10: =IF(N10<>"",IFERROR(V9+N10,""),"") -> 146530.07 | W10: 655764 | X10: =IFERROR(N10/W10,"") -> 0.14626878 | AC10: 593470.63
A11: =TEXT(B11,"mmm") -> Dec | B11: 44176 | C11: -39875 | D11: 17694.1 | E11: -4784.3 | F11: 3647.6 | G11: -18220.9 | H11: 1175 | I11: 0 | J11: =IF(SUM(C11:I11)=0,"",SUM(C11:I11)) -> -40363.5 | K11: -195.4 | L11: -449.03 | M11: =IF(SUM(K11:L11)=0,"",SUM(K11:L11)) -> -644.43 | N11: =IFERROR(J11+M11,"") -> -41007.93 | O11: =IF(Table5[[#This Row],[Beans]]="","",O10+Table5[[#This Row],[Beans]]) -> -31770.5 | P11: =IF(Table5[[#This Row],[Meal]]="","",P10+Table5[[#This Row],[Meal]]) -> -2727.1 | Q11: =IF(Table5[[#This Row],[Oil]]="","",Q10+Table5[[#This Row],[Oil]]) -> 15281.9 | R11: =IF(Table5[[#This Row],[Corn]]="","",R10+Table5[[#This Row],[Corn]]) -> 106796.3 | S11: =IF(Table5[[#This Row],[Wheat]]="","",S10+Table5[[#This Row],[Wheat]]) -> 16208.1 | T11: =IF(Table5[[#This Row],[KC Wheat]]="","",T10+Table5[[#This Row],[KC Wheat]]) -> 8526.6 | U11: =IF(Table5[[#This Row],[Energies]]="","",U10+Table5[[#This Row],[Energies]]) -> 0 | V11: =IF(N11<>"",IFERROR(V10+N11,""),"") -> 105522.14 | W11: 607150 | X11: =IFERROR(N11/W11,"") -> -0.067541678 | AC11: 560283.45
A12: =TEXT(B12,"mmm") -> Dec | B12: 44179 | C12: -40323 | D12: 13345 | E12: 2258 | F12: 20498 | G12: -22991 | H12: 2330 | I12: 0 | J12: =IF(SUM(C12:I12)=0,"",SUM(C12:I12)) -> -24883 | K12: -282.7 | L12: -650.21 | M12: =IF(SUM(K12:L12)=0,"",SUM(K12:L12)) -> -932.91 | N12: =IFERROR(J12+M12,"") -> -25815.91 | O12: =IF(Table5[[#This Row],[Beans]]="","",O11+Table5[[#This Row],[Beans]]) -> -72093.5 | P12: =IF(Table5[[#This Row],[Meal]]="","",P11+Table5[[#This Row],[Meal]]) -> 10617.9 | Q12: =IF(Table5[[#This Row],[Oil]]="","",Q11+Table5[[#This Row],[Oil]]) -> 17539.9 | R12: =IF(Table5[[#This Row],[Corn]]="","",R11+Table5[[#This Row],[Corn]]) -> 127294.3 | S12: =IF(Table5[[#This Row],[Wheat]]="","",S11+Table5[[#This Row],[Wheat]]) -> -6782.9 | T12: =IF(Table5[[#This Row],[KC Wheat]]="","",T11+Table5[[#This Row],[KC Wheat]]) -> 10856.6 | U12: =IF(Table5[[#This Row],[Energies]]="","",U11+Table5[[#This Row],[Energies]]) -> 0 | V12: =IF(N12<>"",IFERROR(V11+N12,""),"") -> 79706.23 | W12: 834837 | X12: =IFERROR(N12/W12,"") -> -0.030923294 | AC12: 530848
A13: =TEXT(B13,"mmm") -> Dec | B13: 44180 | C13: 23205 | D13: -2204 | E13: -8303 | F13: -3983 | G13: 11694 | H13: -1560 | I13: 0 | J13: =IF(SUM(C13:I13)=0,"",SUM(C13:I13)) -> 18849 | K13: -260 | L13: -598 | M13: =IF(SUM(K13:L13)=0,"",SUM(K13:L13)) -> -858 | N13: =IFERROR(J13+M13,"") -> 17991 | O13: =IF(Table5[[#This Row],[Beans]]="","",O12+Table5[[#This Row],[Beans]]) -> -48888.5 | P13: =IF(Table5[[#This Row],[Meal]]="","",P12+Table5[[#This Row],[Meal]]) -> 8413.9 | Q13: =IF(Table5[[#This Row],[Oil]]="","",Q12+Table5[[#This Row],[Oil]]) -> 9236.9 | R13: =IF(Table5[[#This Row],[Corn]]="","",R12+Table5[[#This Row],[Corn]]) -> 123311.3 | S13: =IF(Table5[[#This Row],[Wheat]]="","",S12+Table5[[#This Row],[Wheat]]) -> 4911.1 | T13: =IF(Table5[[#This Row],[KC Wheat]]="","",T12+Table5[[#This Row],[KC Wheat]]) -> 9296.6 | U13: =IF(Table5[[#This Row],[Energies]]="","",U12+Table5[[#This Row],[Energies]]) -> 0 | V13: =IF(N13<>"",IFERROR(V12+N13,""),"") -> 97697.23 | W13: 752056 | X13: =IFERROR(N13/W13,"") -> 0.023922421 | AC13: 564475.79
A14: =TEXT(B14,"mmm") -> Dec | B14: 44181 | C14: 52890 | D14: 56581 | E14: 14164 | F14: 14013 | G14: -5924 | H14: -352 | I14: 0 | J14: =IF(SUM(C14:I14)=0,"",SUM(C14:I14)) -> 131372 | K14: -584.3 | L14: -1343.89 | M14: =IF(SUM(K14:L14)=0,"",SUM(K14:L14)) -> -1928.19 | N14: =IFERROR(J14+M14,"") -> 129443.81 | O14: =IF(Table5[[#This Row],[Beans]]="","",O13+Table5[[#This Row],[Beans]]) -> 4001.5 | P14: =IF(Table5[[#This Row],[Meal]]="","",P13+Table5[[#This Row],[Meal]]) -> 64994.9 | Q14: =IF(Table5[[#This Row],[Oil]]="","",Q13+Table5[[#This Row],[Oil]]) -> 23400.9 | R14: =IF(Table5[[#This Row],[Corn]]="","",R13+Table5[[#This Row],[Corn]]) -> 137324.3 | S14: =IF(Table5[[#This Row],[Wheat]]="","",S13+Table5[[#This Row],[Wheat]]) -> -1012.9 | T14: =IF(Table5[[#This Row],[KC Wheat]]="","",T13+Table5[[#This Row],[KC Wheat]]) -> 8944.6 | U14: =IF(Table5[[#This Row],[Energies]]="","",U13+Table5[[#This Row],[Energies]]) -> 0 | V14: =IF(N14<>"",IFERROR(V13+N14,""),"") -> 227141.04 | W14: 577307 | X14: =IFERROR(N14/W14,"") -> 0.22422006 | Y14: -3901.88 | AC14: 698531.35
A15: =TEXT(B15,"mmm") -> Dec | B15: 44182 | C15: -24271 | D15: 39986 | E15: -5529 | F15: -19519 | G15: 6861 | H15: 1397 | I15: 0 | J15: =IF(SUM(C15:I15)=0,"",SUM(C15:I15)) -> -1075 | K15: -380.2 | L15: -873.92 | M15: =IF(SUM(K15:L15)=0,"",SUM(K15:L15)) -> -1254.12 | N15: =IFERROR(J15+M15,"") -> -2329.12 | O15: =IF(Table5[[#This Row],[Beans]]="","",O14+Table5[[#This Row],[Beans]]) -> -20269.5 | P15: =IF(Table5[[#This Row],[Meal]]="","",P14+Table5[[#This Row],[Meal]]) -> 104980.9 | Q15: =IF(Table5[[#This Row],[Oil]]="","",Q14+Table5[[#This Row],[Oil]]) -> 17871.9 | R15: =IF(Table5[[#This Row],[Corn]]="","",R14+Table5[[#This Row],[Corn]]) -> 117805.3 | S15: =IF(Table5[[#This Row],[Wheat]]="","",S14+Table5[[#This Row],[Wheat]]) -> 5848.1 | T15: =IF(Table5[[#This Row],[KC Wheat]]="","",T14+Table5[[#This Row],[KC Wheat]]) -> 10341.6 | U15: =IF(Table5[[#This Row],[Energies]]="","",U14+Table5[[#This Row],[Energies]]) -> 0 | V15: =IF(N15<>"",IFERROR(V14+N15,""),"") -> 224811.92 | W15: 537527 | X15: =IFERROR(N15/W15,"") -> -0.0043330289 | AC15: 657004.98
A16: =TEXT(B16,"mmm") -> Dec | B16: 44183 | C16: -21471 | D16: 30533 | E16: 7856 | F16: -32080 | G16: 7351 | H16: -1350 | I16: 0 | J16: =IF(SUM(C16:I16)=0,"",SUM(C16:I16)) -> -9161 | K16: -326.9 | L16: -751.412 | M16: =IF(SUM(K16:L16)=0,"",SUM(K16:L16)) -> -1078.312 | N16: =IFERROR(J16+M16,"") -> -10239.312 | O16: =IF(Table5[[#This Row],[Beans]]="","",O15+Table5[[#This Row],[Beans]]) -> -41740.5 | P16: =IF(Table5[[#This Row],[Meal]]="","",P15+Table5[[#This Row],[Meal]]) -> 135513.9 | Q16: =IF(Table5[[#This Row],[Oil]]="","",Q15+Table5[[#This Row],[Oil]]) -> 25727.9 | R16: =IF(Table5[[#This Row],[Corn]]="","",R15+Table5[[#This Row],[Corn]]) -> 85725.3 | S16: =IF(Table5[[#This Row],[Wheat]]="","",S15+Table5[[#This Row],[Wheat]]) -> 13199.1 | T16: =IF(Table5[[#This Row],[KC Wheat]]="","",T15+Table5[[#This Row],[KC Wheat]]) -> 8991.6 | U16: =IF(Table5[[#This Row],[Energies]]="","",U15+Table5[[#This Row],[Energies]]) -> 0 | V16: =IF(N16<>"",IFERROR(V15+N16,""),"") -> 214572.61 | W16: 518736 | X16: =IFERROR(N16/W16,"") -> -0.019738965 | AC16: 653197.41
A17: =TEXT(B17,"mmm") -> Dec | B17: 44186 | C17: -21412 | D17: 13892 | E17: -2974 | F17: -26606 | G17: 14291 | H17: -3024 | I17: 0 | J17: =IF(SUM(C17:I17)=0,"",SUM(C17:I17)) -> -25833 | K17: -299.3 | L17: -688.3 | M17: =IF(SUM(K17:L17)=0,"",SUM(K17:L17)) -> -987.6 | N17: =IFERROR(J17+M17,"") -> -26820.6 | O17: =IF(Table5[[#This Row],[Beans]]="","",O16+Table5[[#This Row],[Beans]]) -> -63152.5 | P17: =IF(Table5[[#This Row],[Meal]]="","",P16+Table5[[#This Row],[Meal]]) -> 149405.9 | Q17: =IF(Table5[[#This Row],[Oil]]="","",Q16+Table5[[#This Row],[Oil]]) -> 22753.9 | R17: =IF(Table5[[#This Row],[Corn]]="","",R16+Table5[[#This Row],[Corn]]) -> 59119.3 | S17: =IF(Table5[[#This Row],[Wheat]]="","",S16+Table5[[#This Row],[Wheat]]) -> 27490.1 | T17: =IF(Table5[[#This Row],[KC Wheat]]="","",T16+Table5[[#This Row],[KC Wheat]]) -> 5967.6 | U17: =IF(Table5[[#This Row],[Energies]]="","",U16+Table5[[#This Row],[Energies]]) -> 0 | V17: =IF(N17<>"",IFERROR(V16+N17,""),"") -> 187752.01 | W17: 469834 | X17: =IFERROR(N17/W17,"") -> -0.057085268 | AC17: 675021.31
A18: =TEXT(B18,"mmm") -> Dec | B18: 44187 | C18: 17925 | D18: 14454 | E18: 1426 | F18: -29368 | G18: 7148 | H18: 597 | I18: 0 | J18: =IF(SUM(C18:I18)=0,"",SUM(C18:I18)) -> 12182 | K18: -221.1 | L18: -508.53 | M18: =IF(SUM(K18:L18)=0,"",SUM(K18:L18)) -> -729.63 | N18: =IFERROR(J18+M18,"") -> 11452.37 | O18: =IF(Table5[[#This Row],[Beans]]="","",O17+Table5[[#This Row],[Beans]]) -> -45227.5 | P18: =IF(Table5[[#This Row],[Meal]]="","",P17+Table5[[#This Row],[Meal]]) -> 163859.9 | Q18: =IF(Table5[[#This Row],[Oil]]="","",Q17+Table5[[#This Row],[Oil]]) -> 24179.9 | R18: =IF(Table5[[#This Row],[Corn]]="","",R17+Table5[[#This Row],[Corn]]) -> 29751.3 | S18: =IF(Table5[[#This Row],[Wheat]]="","",S17+Table5[[#This Row],[Wheat]]) -> 34638.1 | T18: =IF(Table5[[#This Row],[KC Wheat]]="","",T17+Table5[[#This Row],[KC Wheat]]) -> 6564.6 | U18: =IF(Table5[[#This Row],[Energies]]="","",U17+Table5[[#This Row],[Energies]]) -> 0 | V18: =IF(N18<>"",IFERROR(V17+N18,""),"") -> 199204.38 | W18: 455131 | X18: =IFERROR(N18/W18,"") -> 0.025162799 | AC18: 674363.18
A19: =TEXT(B19,"mmm") -> Dec | B19: 44188 | C19: -7026 | D19: 3956 | E19: -6614 | F19: -54369 | G19: 4143 | H19: -2762 | I19: 0 | J19: =IF(SUM(C19:I19)=0,"",SUM(C19:I19)) -> -62672 | K19: -197.7 | L19: -454.71 | M19: =IF(SUM(K19:L19)=0,"",SUM(K19:L19)) -> -652.41 | N19: =IFERROR(J19+M19,"") -> -63324.41 | O19: =IF(Table5[[#This Row],[Beans]]="","",O18+Table5[[#This Row],[Beans]]) -> -52253.5 | P19: =IF(Table5[[#This Row],[Meal]]="","",P18+Table5[[#This Row],[Meal]]) -> 167815.9 | Q19: =IF(Table5[[#This Row],[Oil]]="","",Q18+Table5[[#This Row],[Oil]]) -> 17565.9 | R19: =IF(Table5[[#This Row],[Corn]]="","",R18+Table5[[#This Row],[Corn]]) -> -24617.7 | S19: =IF(Table5[[#This Row],[Wheat]]="","",S18+Table5[[#This Row],[Wheat]]) -> 38781.1 | T19: =IF(Table5[[#This Row],[KC Wheat]]="","",T18+Table5[[#This Row],[KC Wheat]]) -> 3802.6 | U19: =IF(Table5[[#This Row],[Energies]]="","",U18+Table5[[#This Row],[Energies]]) -> 0 | V19: =IF(N19<>"",IFERROR(V18+N19,""),"") -> 135879.97 | W19: 546574 | X19: =IFERROR(N19/W19,"") -> -0.11585697 | Y19: -2292 | AC19: 587264.77
A20: =TEXT(B20,"mmm") -> Dec | B20: 44189 | C20: -18575 | D20: 5413 | E20: -5209 | F20: 33404 | G20: 41.7 | H20: 232 | I20: 0 | J20: =IF(SUM(C20:I20)=0,"",SUM(C20:I20)) -> 15306.7 | K20: -1602.5 | L20: -2317.57 | M20: =IF(SUM(K20:L20)=0,"",SUM(K20:L20)) -> -3920.07 | N20: =IFERROR(J20+M20,"") -> 11386.63 | O20: =IF(Table5[[#This Row],[Beans]]="","",O19+Table5[[#This Row],[Beans]]) -> -70828.5 | P20: =IF(Table5[[#This Row],[Meal]]="","",P19+Table5[[#This Row],[Meal]]) -> 173228.9 | Q20: =IF(Table5[[#This Row],[Oil]]="","",Q19+Table5[[#This Row],[Oil]]) -> 12356.9 | R20: =IF(Table5[[#This Row],[Corn]]="","",R19+Table5[[#This Row],[Corn]]) -> 8786.3 | S20: =IF(Table5[[#This Row],[Wheat]]="","",S19+Table5[[#This Row],[Wheat]]) -> 38822.8 | T20: =IF(Table5[[#This Row],[KC Wheat]]="","",T19+Table5[[#This Row],[KC Wheat]]) -> 4034.6 | U20: =IF(Table5[[#This Row],[Energies]]="","",U19+Table5[[#This Row],[Energies]]) -> 0 | V20: =IF(N20<>"",IFERROR(V19+N20,""),"") -> 147266.6 | W20: 620318 | X20: =IFERROR(N20/W20,"") -> 0.018356117 | AC20: 636614.95
A21: =TEXT(B21,"mmm") -> Dec | B21: 44193 | C21: 1870 | D21: 4872 | E21: 2252 | F21: 27167 | G21: -5893 | H21: -448 | I21: 0 | J21: =IF(SUM(C21:I21)=0,"",SUM(C21:I21)) -> 29820 | K21: -207.8 | L21: -477.91 | M21: =IF(SUM(K21:L21)=0,"",SUM(K21:L21)) -> -685.71 | N21: =IFERROR(J21+M21,"") -> 29134.29 | O21: =IF(Table5[[#This Row],[Beans]]="","",O20+Table5[[#This Row],[Beans]]) -> -68958.5 | P21: =IF(Table5[[#This Row],[Meal]]="","",P20+Table5[[#This Row],[Meal]]) -> 178100.9 | Q21: =IF(Table5[[#This Row],[Oil]]="","",Q20+Table5[[#This Row],[Oil]]) -> 14608.9 | R21: =IF(Table5[[#This Row],[Corn]]="","",R20+Table5[[#This Row],[Corn]]) -> 35953.3 | S21: =IF(Table5[[#This Row],[Wheat]]="","",S20+Table5[[#This Row],[Wheat]]) -> 32929.8 | T21: =IF(Table5[[#This Row],[KC Wheat]]="","",T20+Table5[[#This Row],[KC Wheat]]) -> 3586.6 | U21: =IF(Table5[[#This Row],[Energies]]="","",U20+Table5[[#This Row],[Energies]]) -> 0 | V21: =IF(N21<>"",IFERROR(V20+N21,""),"") -> 176400.89 | W21: 638866 | X21: =IFERROR(N21/W21,"") -> 0.045603131 | AC21: 630630.74
A22: =TEXT(B22,"mmm") -> Dec | B22: 44194 | C22: -44586 | D22: 845 | E22: -5619 | F22: -104510 | G22: 4305 | H22: 1177 | I22: 0 | J22: =IF(SUM(C22:I22)=0,"",SUM(C22:I22)) -> -148388 | K22: -168.6 | L22: -387.06 | M22: =IF(SUM(K22:L22)=0,"",SUM(K22:L22)) -> -555.66 | N22: =IFERROR(J22+M22,"") -> -148943.66 | O22: =IF(Table5[[#This Row],[Beans]]="","",O21+Table5[[#This Row],[Beans]]) -> -113544.5 | P22: =IF(Table5[[#This Row],[Meal]]="","",P21+Table5[[#This Row],[Meal]]) -> 178945.9 | Q22: =IF(Table5[[#This Row],[Oil]]="","",Q21+Table5[[#This Row],[Oil]]) -> 8989.9 | R22: =IF(Table5[[#This Row],[Corn]]="","",R21+Table5[[#This Row],[Corn]]) -> -68556.7 | S22: =IF(Table5[[#This Row],[Wheat]]="","",S21+Table5[[#This Row],[Wheat]]) -> 37234.8 | T22: =IF(Table5[[#This Row],[KC Wheat]]="","",T21+Table5[[#This Row],[KC Wheat]]) -> 4763.6 | U22: =IF(Table5[[#This Row],[Energies]]="","",U21+Table5[[#This Row],[Energies]]) -> 0 | V22: =IF(N22<>"",IFERROR(V21+N22,""),"") -> 27457.228 | W22: 640145 | X22: =IFERROR(N22/W22,"") -> -0.23267175 | Y22: -3901.88 | AA22: -71274.25 | AC22: 498047.58
A23: =TEXT(B23,"mmm") -> Dec | B23: 44195 | C23: 1301 | D23: -25604 | E23: 15610 | F23: -14677 | G23: 22984 | H23: -639 | I23: 0 | J23: =IF(SUM(C23:I23)=0,"",SUM(C23:I23)) -> -1025 | K23: -211.4 | L23: -486.22 | M23: =IF(SUM(K23:L23)=0,"",SUM(K23:L23)) -> -697.62 | N23: =IFERROR(J23+M23,"") -> -1722.62 | O23: =IF(Table5[[#This Row],[Beans]]="","",O22+Table5[[#This Row],[Beans]]) -> -112243.5 | P23: =IF(Table5[[#This Row],[Meal]]="","",P22+Table5[[#This Row],[Meal]]) -> 153341.9 | Q23: =IF(Table5[[#This Row],[Oil]]="","",Q22+Table5[[#This Row],[Oil]]) -> 24599.9 | R23: =IF(Table5[[#This Row],[Corn]]="","",R22+Table5[[#This Row],[Corn]]) -> -83233.7 | S23: =IF(Table5[[#This Row],[Wheat]]="","",S22+Table5[[#This Row],[Wheat]]) -> 60218.8 | T23: =IF(Table5[[#This Row],[KC Wheat]]="","",T22+Table5[[#This Row],[KC Wheat]]) -> 4124.6 | U23: =IF(Table5[[#This Row],[Energies]]="","",U22+Table5[[#This Row],[Energies]]) -> 0 | V23: =IF(N23<>"",IFERROR(V22+N23,""),"") -> 25734.608 | W23: 619947 | X23: =IFERROR(N23/W23,"") -> -0.0027786569 | AC23: 517116.96
A24: =TEXT(B24,"mmm") -> Dec | B24: 44196 | C24: -14236 | D24: 18469 | E24: 16035 | F24: -86553 | G24: 23210 | H24: 6296 | I24: 0 | J24: =IF(SUM(C24:I24)=0,"",SUM(C24:I24)) -> -36779 | K24: -411.9 | L24: -947.37 | M24: =IF(SUM(K24:L24)=0,"",SUM(K24:L24)) -> -1359.27 | N24: =IFERROR(J24+M24,"") -> -38138.27 | O24: =IF(Table5[[#This Row],[Beans]]="","",O23+Table5[[#This Row],[Beans]]) -> -126479.5 | P24: =IF(Table5[[#This Row],[Meal]]="","",P23+Table5[[#This Row],[Meal]]) -> 171810.9 | Q24: =IF(Table5[[#This Row],[Oil]]="","",Q23+Table5[[#This Row],[Oil]]) -> 40634.9 | R24: =IF(Table5[[#This Row],[Corn]]="","",R23+Table5[[#This Row],[Corn]]) -> -169786.7 | S24: =IF(Table5[[#This Row],[Wheat]]="","",S23+Table5[[#This Row],[Wheat]]) -> 83428.8 | T24: =IF(Table5[[#This Row],[KC Wheat]]="","",T23+Table5[[#This Row],[KC Wheat]]) -> 10420.6 | U24: =IF(Table5[[#This Row],[Energies]]="","",U23+Table5[[#This Row],[Energies]]) -> 0 | V24: =IF(N24<>"",IFERROR(V23+N24,""),"") -> -12403.662 | W24: 571633 | X24: =IFERROR(N24/W24,"") -> -0.066718104 | AC24: 429540.44
A25: =TEXT(B25,"mmm") -> Jan | B25: 44200 | C25: 40106.2 | D25: -4651 | E25: -10541.7 | F25: 3772.2 | G25: 21673.7 | H25: -8256.9 | I25: 0 | J25: =IF(SUM(C25:I25)=0,"",SUM(C25:I25)) -> 42102.5 | K25: -220.4 | L25: -506.92 | M25: =IF(SUM(K25:L25)=0,"",SUM(K25:L25)) -> -727.32 | N25: =IFERROR(J25+M25,"") -> 41375.18 | O25: =IF(Table5[[#This Row],[Beans]]="","",O24+Table5[[#This Row],[Beans]]) -> -86373.3 | P25: =IF(Table5[[#This Row],[Meal]]="","",P24+Table5[[#This Row],[Meal]]) -> 167159.9 | Q25: =IF(Table5[[#This Row],[Oil]]="","",Q24+Table5[[#This Row],[Oil]]) -> 30093.2 | R25: =IF(Table5[[#This Row],[Corn]]="","",R24+Table5[[#This Row],[Corn]]) -> -166014.5 | S25: =IF(Table5[[#This Row],[Wheat]]="","",S24+Table5[[#This Row],[Wheat]]) -> 105102.5 | T25: =IF(Table5[[#This Row],[KC Wheat]]="","",T24+Table5[[#This Row],[KC Wheat]]) -> 2163.7 | U25: =IF(Table5[[#This Row],[Energies]]="","",U24+Table5[[#This Row],[Energies]]) -> 0 | V25: =IF(N25<>"",IFERROR(V24+N25,""),"") -> 28971.518 | W25: 574028 | X25: =IFERROR(N25/W25,"") -> 0.072078679 | Y25: -530.95 | AA25: -429540.44 | AC25: 86079.43
A26: =TEXT(B26,"mmm") -> Jan | B26: 44201 | C26: -3994.5 | D26: -1153.7 | E26: -23510.7 | F26: -13806.8 | G26: 45942.7 | H26: 1625.2 | I26: 0 | J26: =IF(SUM(C26:I26)=0,"",SUM(C26:I26)) -> 5102.2 | K26: -335.6 | L26: -771.88 | M26: =IF(SUM(K26:L26)=0,"",SUM(K26:L26)) -> -1107.48 | N26: =IFERROR(J26+M26,"") -> 3994.72 | O26: =IF(Table5[[#This Row],[Beans]]="","",O25+Table5[[#This Row],[Beans]]) -> -90367.8 | P26: =IF(Table5[[#This Row],[Meal]]="","",P25+Table5[[#This Row],[Meal]]) -> 166006.2 | Q26: =IF(Table5[[#This Row],[Oil]]="","",Q25+Table5[[#This Row],[Oil]]) -> 6582.5 | R26: =IF(Table5[[#This Row],[Corn]]="","",R25+Table5[[#This Row],[Corn]]) -> -179821.3 | S26: =IF(Table5[[#This Row],[Wheat]]="","",S25+Table5[[#This Row],[Wheat]]) -> 151045.2 | T26: =IF(Table5[[#This Row],[KC Wheat]]="","",T25+Table5[[#This Row],[KC Wheat]]) -> 3788.9 | U26: =IF(Table5[[#This Row],[Energies]]="","",U25+Table5[[#This Row],[Energies]]) -> 0 | V26: =IF(N26<>"",IFERROR(V25+N26,""),"") -> 32966.238 | W26: 505650 | X26: =IFERROR(N26/W26,"") -> 0.0079001681 | AC26: 62202.7
A27: =TEXT(B27,"mmm") -> Jan | B27: 44202 | C27: 6693.5 | D27: -5655.6 | E27: 22539.2 | F27: 22857.4 | G27: -1768.8 | H27: 7479.6 | I27: 0 | J27: =IF(SUM(C27:I27)=0,"",SUM(C27:I27)) -> 52145.3 | K27: -324.1 | L27: -745.43 | M27: =IF(SUM(K27:L27)=0,"",SUM(K27:L27)) -> -1069.53 | N27: =IFERROR(J27+M27,"") -> 51075.77 | O27: =IF(Table5[[#This Row],[Beans]]="","",O26+Table5[[#This Row],[Beans]]) -> -83674.3 | P27: =IF(Table5[[#This Row],[Meal]]="","",P26+Table5[[#This Row],[Meal]]) -> 160350.6 | Q27: =IF(Table5[[#This Row],[Oil]]="","",Q26+Table5[[#This Row],[Oil]]) -> 29121.7 | R27: =IF(Table5[[#This Row],[Corn]]="","",R26+Table5[[#This Row],[Corn]]) -> -156963.9 | S27: =IF(Table5[[#This Row],[Wheat]]="","",S26+Table5[[#This Row],[Wheat]]) -> 149276.4 | T27: =IF(Table5[[#This Row],[KC Wheat]]="","",T26+Table5[[#This Row],[KC Wheat]]) -> 11268.5 | U27: =IF(Table5[[#This Row],[Energies]]="","",U26+Table5[[#This Row],[Energies]]) -> 0 | V27: =IF(N27<>"",IFERROR(V26+N27,""),"") -> 84042.008 | W27: 633885 | X27: =IFERROR(N27/W27,"") -> 0.080575767 | AC27: 115572.92
A28: =TEXT(B28,"mmm") -> Jan | B28: 44203 | C28: 5089.3 | D28: -6030.9 | E28: -7999.4 | F28: -6418.3 | G28: -1716.8 | H28: 8477.3 | I28: 0 | J28: =IF(SUM(C28:I28)=0,"",SUM(C28:I28)) -> -8598.8 | K28: -336.2 | L28: -773.26 | M28: =IF(SUM(K28:L28)=0,"",SUM(K28:L28)) -> -1109.46 | N28: =IFERROR(J28+M28,"") -> -9708.26 | O28: =IF(Table5[[#This Row],[Beans]]="","",O27+Table5[[#This Row],[Beans]]) -> -78585 | P28: =IF(Table5[[#This Row],[Meal]]="","",P27+Table5[[#This Row],[Meal]]) -> 154319.7 | Q28: =IF(Table5[[#This Row],[Oil]]="","",Q27+Table5[[#This Row],[Oil]]) -> 21122.3 | R28: =IF(Table5[[#This Row],[Corn]]="","",R27+Table5[[#This Row],[Corn]]) -> -163382.2 | S28: =IF(Table5[[#This Row],[Wheat]]="","",S27+Table5[[#This Row],[Wheat]]) -> 147559.6 | T28: =IF(Table5[[#This Row],[KC Wheat]]="","",T27+Table5[[#This Row],[KC Wheat]]) -> 19745.8 | U28: =IF(Table5[[#This Row],[Energies]]="","",U27+Table5[[#This Row],[Energies]]) -> 0 | V28: =IF(N28<>"",IFERROR(V27+N28,""),"") -> 74333.748 | W28: 702318 | X28: =IFERROR(N28/W28,"") -> -0.013823168 | AC28: 146918.21
A29: =TEXT(B29,"mmm") -> Jan | B29: 44204 | C29: 11189.4 | D29: -451.2 | E29: 9589.1 | F29: 2755.3 | G29: -8017.4 | H29: -1840.8 | I29: 0 | J29: =IF(SUM(C29:I29)=0,"",SUM(C29:I29)) -> 13224.4 | K29: -331.2 | L29: -761.76 | M29: =IF(SUM(K29:L29)=0,"",SUM(K29:L29)) -> -1092.96 | N29: =IFERROR(J29+M29,"") -> 12131.44 | O29: =IF(Table5[[#This Row],[Beans]]="","",O28+Table5[[#This Row],[Beans]]) -> -67395.6 | P29: =IF(Table5[[#This Row],[Meal]]="","",P28+Table5[[#This Row],[Meal]]) -> 153868.5 | Q29: =IF(Table5[[#This Row],[Oil]]="","",Q28+Table5[[#This Row],[Oil]]) -> 30711.4 | R29: =IF(Table5[[#This Row],[Corn]]="","",R28+Table5[[#This Row],[Corn]]) -> -160626.9 | S29: =IF(Table5[[#This Row],[Wheat]]="","",S28+Table5[[#This Row],[Wheat]]) -> 139542.2 | T29: =IF(Table5[[#This Row],[KC Wheat]]="","",T28+Table5[[#This Row],[KC Wheat]]) -> 17905 | U29: =IF(Table5[[#This Row],[Energies]]="","",U28+Table5[[#This Row],[Energies]]) -> 0 | V29: =IF(N29<>"",IFERROR(V28+N29,""),"") -> 86465.188 | W29: 555070 | X29: =IFERROR(N29/W29,"") -> 0.021855694 | AC29: 109764
A30: =TEXT(B30,"mmm") -> Jan | B30: 44207 | C30: 13145.7 | D30: 13628.5 | E30: -8993 | F30: 30199.3 | G30: -16084.2 | H30: -32458 | I30: 0 | J30: =IF(SUM(C30:I30)=0,"",SUM(C30:I30)) -> -561.7 | K30: -443.9 | L30: -1020.97 | M30: =IF(SUM(K30:L30)=0,"",SUM(K30:L30)) -> -1464.87 | N30: =IFERROR(J30+M30,"") -> -2026.57 | O30: =IF(Table5[[#This Row],[Beans]]="","",O29+Table5[[#This Row],[Beans]]) -> -54249.9 | P30: =IF(Table5[[#This Row],[Meal]]="","",P29+Table5[[#This Row],[Meal]]) -> 167497 | Q30: =IF(Table5[[#This Row],[Oil]]="","",Q29+Table5[[#This Row],[Oil]]) -> 21718.4 | R30: =IF(Table5[[#This Row],[Corn]]="","",R29+Table5[[#This Row],[Corn]]) -> -130427.6 | S30: =IF(Table5[[#This Row],[Wheat]]="","",S29+Table5[[#This Row],[Wheat]]) -> 123458 | T30: =IF(Table5[[#This Row],[KC Wheat]]="","",T29+Table5[[#This Row],[KC Wheat]]) -> -14553 | U30: =IF(Table5[[#This Row],[Energies]]="","",U29+Table5[[#This Row],[Energies]]) -> 0 | V30: =IF(N30<>"",IFERROR(V29+N30,""),"") -> 84438.618 | W30: 579176 | X30: =IFERROR(N30/W30,"") -> -0.0034990573 | Y30: -1388.53 | AC30: 121639.38
A31: =TEXT(B31,"mmm") -> Jan | B31: 44208 | C31: -14581.6 | D31: 9798.6 | E31: 1109.5 | F31: 11221.4 | G31: 65911.7 | H31: -9798.5 | I31: 0 | J31: =IF(SUM(C31:I31)=0,"",SUM(C31:I31)) -> 63661.1 | K31: -392.7 | L31: -903.21 | M31: =IF(SUM(K31:L31)=0,"",SUM(K31:L31)) -> -1295.91 | N31: =IFERROR(J31+M31,"") -> 62365.19 | O31: =IF(Table5[[#This Row],[Beans]]="","",O30+Table5[[#This Row],[Beans]]) -> -68831.5 | P31: =IF(Table5[[#This Row],[Meal]]="","",P30+Table5[[#This Row],[Meal]]) -> 177295.6 | Q31: =IF(Table5[[#This Row],[Oil]]="","",Q30+Table5[[#This Row],[Oil]]) -> 22827.9 | R31: =IF(Table5[[#This Row],[Corn]]="","",R30+Table5[[#This Row],[Corn]]) -> -119206.2 | S31: =IF(Table5[[#This Row],[Wheat]]="","",S30+Table5[[#This Row],[Wheat]]) -> 189369.7 | T31: =IF(Table5[[#This Row],[KC Wheat]]="","",T30+Table5[[#This Row],[KC Wheat]]) -> -24351.5 | U31: =IF(Table5[[#This Row],[Energies]]="","",U30+Table5[[#This Row],[Energies]]) -> 0 | V31: =IF(N31<>"",IFERROR(V30+N31,""),"") -> 146803.81 | W31: 593466 | X31: =IFERROR(N31/W31,"") -> 0.10508637 | Y31: -125 | AC31: -54154.03
A32: =TEXT(B32,"mmm") -> Jan | B32: 44209 | C32: 55269.3 | D32: -16230 | E32: -652.3 | F32: 10492.2 | G32: 24637 | H32: -1563.5 | I32: 0 | J32: =IF(SUM(C32:I32)=0,"",SUM(C32:I32)) -> 71952.7 | K32: -830.5 | L32: -1910.12 | M32: =IF(SUM(K32:L32)=0,"",SUM(K32:L32)) -> -2740.62 | N32: =IFERROR(J32+M32,"") -> 69212.08 | O32: =IF(Table5[[#This Row],[Beans]]="","",O31+Table5[[#This Row],[Beans]]) -> -13562.2 | P32: =IF(Table5[[#This Row],[Meal]]="","",P31+Table5[[#This Row],[Meal]]) -> 161065.6 | Q32: =IF(Table5[[#This Row],[Oil]]="","",Q31+Table5[[#This Row],[Oil]]) -> 22175.6 | R32: =IF(Table5[[#This Row],[Corn]]="","",R31+Table5[[#This Row],[Corn]]) -> -108714 | S32: =IF(Table5[[#This Row],[Wheat]]="","",S31+Table5[[#This Row],[Wheat]]) -> 214006.7 | T32: =IF(Table5[[#This Row],[KC Wheat]]="","",T31+Table5[[#This Row],[KC Wheat]]) -> -25915 | U32: =IF(Table5[[#This Row],[Energies]]="","",U31+Table5[[#This Row],[Energies]]) -> 0 | V32: =IF(N32<>"",IFERROR(V31+N32,""),"") -> 216015.89 | W32: 418646 | X32: =IFERROR(N32/W32,"") -> 0.16532364 | AC32: 257737.1
A33: =TEXT(B33,"mmm") -> Jan | B33: 44210 | C33: -9365.9 | D33: 5512.2 | E33: 5121.6 | F33: 20474.8 | G33: -9101.9 | H33: -5077.9 | I33: 0 | J33: =IF(SUM(C33:I33)=0,"",SUM(C33:I33)) -> 7562.9 | K33: -418.3 | L33: -961.25 | M33: =IF(SUM(K33:L33)=0,"",SUM(K33:L33)) -> -1379.55 | N33: =IFERROR(J33+M33,"") -> 6183.35 | O33: =IF(Table5[[#This Row],[Beans]]="","",O32+Table5[[#This Row],[Beans]]) -> -22928.1 | P33: =IF(Table5[[#This Row],[Meal]]="","",P32+Table5[[#This Row],[Meal]]) -> 166577.8 | Q33: =IF(Table5[[#This Row],[Oil]]="","",Q32+Table5[[#This Row],[Oil]]) -> 27297.2 | R33: =IF(Table5[[#This Row],[Corn]]="","",R32+Table5[[#This Row],[Corn]]) -> -88239.2 | S33: =IF(Table5[[#This Row],[Wheat]]="","",S32+Table5[[#This Row],[Wheat]]) -> 204904.8 | T33: =IF(Table5[[#This Row],[KC Wheat]]="","",T32+Table5[[#This Row],[KC Wheat]]) -> -30992.9 | U33: =IF(Table5[[#This Row],[Energies]]="","",U32+Table5[[#This Row],[Energies]]) -> 0 | V33: =IF(N33<>"",IFERROR(V32+N33,""),"") -> 222199.24 | W33: 405870 | X33: =IFERROR(N33/W33,"") -> 0.015234804 | AC33: 219076.3
A34: =TEXT(B34,"mmm") -> Jan | B34: 44211 | C34: 25955 | D34: -18377 | E34: 2888 | F34: -4839.5 | G34: -13182.5 | H34: 7131.5 | I34: 0 | J34: =IF(SUM(C34:I34)=0,"",SUM(C34:I34)) -> -424.5 | K34: -174.4 | L34: -400.67 | M34: =IF(SUM(K34:L34)=0,"",SUM(K34:L34)) -> -575.07 | N34: =IFERROR(J34+M34,"") -> -999.57 | O34: =IF(Table5[[#This Row],[Beans]]="","",O33+Table5[[#This Row],[Beans]]) -> 3026.9 | P34: =IF(Table5[[#This Row],[Meal]]="","",P33+Table5[[#This Row],[Meal]]) -> 148200.8 | Q34: =IF(Table5[[#This Row],[Oil]]="","",Q33+Table5[[#This Row],[Oil]]) -> 30185.2 | R34: =IF(Table5[[#This Row],[Corn]]="","",R33+Table5[[#This Row],[Corn]]) -> -93078.7 | S34: =IF(Table5[[#This Row],[Wheat]]="","",S33+Table5[[#This Row],[Wheat]]) -> 191722.3 | T34: =IF(Table5[[#This Row],[KC Wheat]]="","",T33+Table5[[#This Row],[KC Wheat]]) -> -23861.4 | U34: =IF(Table5[[#This Row],[Energies]]="","",U33+Table5[[#This Row],[Energies]]) -> 0 | V34: =IF(N34<>"",IFERROR(V33+N34,""),"") -> 221199.67 | W34: 424968 | X34: =IFERROR(N34/W34,"") -> -0.0023521065 | AC34: 262855.48
A35: =TEXT(B35,"mmm") -> Jan | B35: 44215 | C35: 19006.6 | D35: -26003.3 | E35: 5702.8 | F35: 11697.2 | G35: 3653.5 | H35: -8.9 | I35: 0 | J35: =IF(SUM(C35:I35)=0,"",SUM(C35:I35)) -> 14047.9 | K35: -347 | L35: -797.05 | M35: =IF(SUM(K35:L35)=0,"",SUM(K35:L35)) -> -1144.05 | N35: =IFERROR(J35+M35,"") -> 12903.85 | O35: =IF(Table5[[#This Row],[Beans]]="","",O34+Table5[[#This Row],[Beans]]) -> 22033.5 | P35: =IF(Table5[[#This Row],[Meal]]="","",P34+Table5[[#This Row],[Meal]]) -> 122197.5 | Q35: =IF(Table5[[#This Row],[Oil]]="","",Q34+Table5[[#This Row],[Oil]]) -> 35888 | R35: =IF(Table5[[#This Row],[Corn]]="","",R34+Table5[[#This Row],[Corn]]) -> -81381.5 | S35: =IF(Table5[[#This Row],[Wheat]]="","",S34+Table5[[#This Row],[Wheat]]) -> 195375.8 | T35: =IF(Table5[[#This Row],[KC Wheat]]="","",T34+Table5[[#This Row],[KC Wheat]]) -> -23870.3 | U35: =IF(Table5[[#This Row],[Energies]]="","",U34+Table5[[#This Row],[Energies]]) -> 0 | V35: =IF(N35<>"",IFERROR(V34+N35,""),"") -> 234103.52 | W35: 419208 | X35: =IFERROR(N35/W35,"") -> 0.030781497 | Y35: -4134.38 | AC35: 275659.68
A36: =TEXT(B36,"mmm") -> Jan | B36: 44216 | C36: -2612.5 | D36: 9961.5 | E36: 7842.6 | F36: -5937.8 | G36: 24721.8 | H36: 3396.5 | I36: 0 | J36: =IF(SUM(C36:I36)=0,"",SUM(C36:I36)) -> 37372.1 | K36: -307.9 | L36: -706.61 | M36: =IF(SUM(K36:L36)=0,"",SUM(K36:L36)) -> -1014.51 | N36: =IFERROR(J36+M36,"") -> 36357.59 | O36: =IF(Table5[[#This Row],[Beans]]="","",O35+Table5[[#This Row],[Beans]]) -> 19421 | P36: =IF(Table5[[#This Row],[Meal]]="","",P35+Table5[[#This Row],[Meal]]) -> 132159 | Q36: =IF(Table5[[#This Row],[Oil]]="","",Q35+Table5[[#This Row],[Oil]]) -> 43730.6 | R36: =IF(Table5[[#This Row],[Corn]]="","",R35+Table5[[#This Row],[Corn]]) -> -87319.3 | S36: =IF(Table5[[#This Row],[Wheat]]="","",S35+Table5[[#This Row],[Wheat]]) -> 220097.6 | T36: =IF(Table5[[#This Row],[KC Wheat]]="","",T35+Table5[[#This Row],[KC Wheat]]) -> -20473.8 | U36: =IF(Table5[[#This Row],[Energies]]="","",U35+Table5[[#This Row],[Energies]]) -> 0 | V36: =IF(N36<>"",IFERROR(V35+N36,""),"") -> 270461.11 | W36: 564346 | X36: =IFERROR(N36/W36,"") -> 0.064424289 | AC36: 319597.67
A37: =TEXT(B37,"mmm") -> Jan | B37: 44217 | C37: 9209.9 | D37: 2946.1 | E37: -12528.9 | F37: 23075 | G37: -27052.5 | H37: -5363.4 | I37: 0 | J37: =IF(SUM(C37:I37)=0,"",SUM(C37:I37)) -> -9713.8 | K37: -446.7 | L37: -1027.38 | M37: =IF(SUM(K37:L37)=0,"",SUM(K37:L37)) -> -1474.08 | N37: =IFERROR(J37+M37,"") -> -11187.88 | O37: =IF(Table5[[#This Row],[Beans]]="","",O36+Table5[[#This Row],[Beans]]) -> 28630.9 | P37: =IF(Table5[[#This Row],[Meal]]="","",P36+Table5[[#This Row],[Meal]]) -> 135105.1 | Q37: =IF(Table5[[#This Row],[Oil]]="","",Q36+Table5[[#This Row],[Oil]]) -> 31201.7 | R37: =IF(Table5[[#This Row],[Corn]]="","",R36+Table5[[#This Row],[Corn]]) -> -64244.3 | S37: =IF(Table5[[#This Row],[Wheat]]="","",S36+Table5[[#This Row],[Wheat]]) -> 193045.1 | T37: =IF(Table5[[#This Row],[KC Wheat]]="","",T36+Table5[[#This Row],[KC Wheat]]) -> -25837.2 | U37: =IF(Table5[[#This Row],[Energies]]="","",U36+Table5[[#This Row],[Energies]]) -> 0 | V37: =IF(N37<>"",IFERROR(V36+N37,""),"") -> 259273.23 | W37: 533459 | X37: =IFERROR(N37/W37,"") -> -0.020972333 | AC37: 330574.84
A38: =TEXT(B38,"mmm") -> Jan | B38: 44218 | C38: 23672.6 | D38: 87083.9 | E38: 9583.9 | F38: -23953.8 | G38: -18059.5 | H38: 358.9 | I38: 0 | J38: =IF(SUM(C38:I38)=0,"",SUM(C38:I38)) -> 78686 | K38: -1556.1 | L38: -2650.04 | M38: =IF(SUM(K38:L38)=0,"",SUM(K38:L38)) -> -4206.14 | N38: =IFERROR(J38+M38,"") -> 74479.86 | O38: =IF(Table5[[#This Row],[Beans]]="","",O37+Table5[[#This Row],[Beans]]) -> 52303.5 | P38: =IF(Table5[[#This Row],[Meal]]="","",P37+Table5[[#This Row],[Meal]]) -> 222189 | Q38: =IF(Table5[[#This Row],[Oil]]="","",Q37+Table5[[#This Row],[Oil]]) -> 40785.6 | R38: =IF(Table5[[#This Row],[Corn]]="","",R37+Table5[[#This Row],[Corn]]) -> -88198.1 | S38: =IF(Table5[[#This Row],[Wheat]]="","",S37+Table5[[#This Row],[Wheat]]) -> 174985.6 | T38: =IF(Table5[[#This Row],[KC Wheat]]="","",T37+Table5[[#This Row],[KC Wheat]]) -> -25478.3 | U38: =IF(Table5[[#This Row],[Energies]]="","",U37+Table5[[#This Row],[Energies]]) -> 0 | V38: =IF(N38<>"",IFERROR(V37+N38,""),"") -> 333753.09 | W38: 753463 | X38: =IFERROR(N38/W38,"") -> 0.098850056 | AC38: 391700.8
A39: =TEXT(B39,"mmm") -> Jan | B39: 44221 | C39: 3143.7 | D39: -1075.1 | E39: 2192.1 | F39: 38506.1 | G39: 4253.6 | H39: 2544.5 | I39: 0 | J39: =IF(SUM(C39:I39)=0,"",SUM(C39:I39)) -> 49564.9 | K39: -306 | L39: -703.8 | M39: =IF(SUM(K39:L39)=0,"",SUM(K39:L39)) -> -1009.8 | N39: =IFERROR(J39+M39,"") -> 48555.1 | O39: =IF(Table5[[#This Row],[Beans]]="","",O38+Table5[[#This Row],[Beans]]) -> 55447.2 | P39: =IF(Table5[[#This Row],[Meal]]="","",P38+Table5[[#This Row],[Meal]]) -> 221113.9 | Q39: =IF(Table5[[#This Row],[Oil]]="","",Q38+Table5[[#This Row],[Oil]]) -> 42977.7 | R39: =IF(Table5[[#This Row],[Corn]]="","",R38+Table5[[#This Row],[Corn]]) -> -49692 | S39: =IF(Table5[[#This Row],[Wheat]]="","",S38+Table5[[#This Row],[Wheat]]) -> 179239.2 | T39: =IF(Table5[[#This Row],[KC Wheat]]="","",T38+Table5[[#This Row],[KC Wheat]]) -> -22933.8 | U39: =IF(Table5[[#This Row],[Energies]]="","",U38+Table5[[#This Row],[Energies]]) -> 0 | V39: =IF(N39<>"",IFERROR(V38+N39,""),"") -> 382308.19 | W39: 658417 | X39: =IFERROR(N39/W39,"") -> 0.07374521 | Y39: -4497.85 | AC39: 462584.4
A40: =TEXT(B40,"mmm") -> Jan | B40: 44222 | C40: 26149.8 | D40: 16916.9 | E40: 21427.9 | F40: -10068.2 | G40: 12693.8 | H40: 9694.4 | I40: 0 | J40: =IF(SUM(C40:I40)=0,"",SUM(C40:I40)) -> 76814.6 | K40: -593 | L40: -1363.75 | M40: =IF(SUM(K40:L40)=0,"",SUM(K40:L40)) -> -1956.75 | N40: =IFERROR(J40+M40,"") -> 74857.85 | O40: =IF(Table5[[#This Row],[Beans]]="","",O39+Table5[[#This Row],[Beans]]) -> 81597 | P40: =IF(Table5[[#This Row],[Meal]]="","",P39+Table5[[#This Row],[Meal]]) -> 238030.8 | Q40: =IF(Table5[[#This Row],[Oil]]="","",Q39+Table5[[#This Row],[Oil]]) -> 64405.6 | R40: =IF(Table5[[#This Row],[Corn]]="","",R39+Table5[[#This Row],[Corn]]) -> -59760.2 | S40: =IF(Table5[[#This Row],[Wheat]]="","",S39+Table5[[#This Row],[Wheat]]) -> 191933 | T40: =IF(Table5[[#This Row],[KC Wheat]]="","",T39+Table5[[#This Row],[KC Wheat]]) -> -13239.4 | U40: =IF(Table5[[#This Row],[Energies]]="","",U39+Table5[[#This Row],[Energies]]) -> 0 | V40: =IF(N40<>"",IFERROR(V39+N40,""),"") -> 457166.04 | W40: 496721.9 | X40: =IFERROR(N40/W40,"") -> 0.15070374 | AC40: 496721.9
A41: =TEXT(B41,"mmm") -> Jan | B41: 44223 | C41: -15098.6 | D41: 36143.6 | E41: -16833.3 | F41: -18503.2 | G41: -4819.7 | H41: -1896.4 | I41: 0 | J41: =IF(SUM(C41:I41)=0,"",SUM(C41:I41)) -> -21007.6 | K41: -322.8 | L41: -742.23 | M41: =IF(SUM(K41:L41)=0,"",SUM(K41:L41)) -> -1065.03 | N41: =IFERROR(J41+M41,"") -> -22072.63 | O41: =IF(Table5[[#This Row],[Beans]]="","",O40+Table5[[#This Row],[Beans]]) -> 66498.4 | P41: =IF(Table5[[#This Row],[Meal]]="","",P40+Table5[[#This Row],[Meal]]) -> 274174.4 | Q41: =IF(Table5[[#This Row],[Oil]]="","",Q40+Table5[[#This Row],[Oil]]) -> 47572.3 | R41: =IF(Table5[[#This Row],[Corn]]="","",R40+Table5[[#This Row],[Corn]]) -> -78263.4 | S41: =IF(Table5[[#This Row],[Wheat]]="","",S40+Table5[[#This Row],[Wheat]]) -> 187113.3 | T41: =IF(Table5[[#This Row],[KC Wheat]]="","",T40+Table5[[#This Row],[KC Wheat]]) -> -15135.8 | U41: =IF(Table5[[#This Row],[Energies]]="","",U40+Table5[[#This Row],[Energies]]) -> 0 | V41: =IF(N41<>"",IFERROR(V40+N41,""),"") -> 435093.41 | W41: 706725 | X41: =IFERROR(N41/W41,"") -> -0.031232276 | Y41: -369 | AC41: 470634.12
A42: =TEXT(B42,"mmm") -> Jan | B42: 44224 | C42: -18896.2 | D42: 12597.5 | E42: -27012.8 | F42: -58493.9 | G42: 17708.3 | H42: 7203.2 | I42: 0 | J42: =IF(SUM(C42:I42)=0,"",SUM(C42:I42)) -> -66893.9 | K42: -285.9 | L42: -657.09 | M42: =IF(SUM(K42:L42)=0,"",SUM(K42:L42)) -> -942.99 | N42: =IFERROR(J42+M42,"") -> -67836.89 | O42: =IF(Table5[[#This Row],[Beans]]="","",O41+Table5[[#This Row],[Beans]]) -> 47602.2 | P42: =IF(Table5[[#This Row],[Meal]]="","",P41+Table5[[#This Row],[Meal]]) -> 286771.9 | Q42: =IF(Table5[[#This Row],[Oil]]="","",Q41+Table5[[#This Row],[Oil]]) -> 20559.5 | R42: =IF(Table5[[#This Row],[Corn]]="","",R41+Table5[[#This Row],[Corn]]) -> -136757.3 | S42: =IF(Table5[[#This Row],[Wheat]]="","",S41+Table5[[#This Row],[Wheat]]) -> 204821.6 | T42: =IF(Table5[[#This Row],[KC Wheat]]="","",T41+Table5[[#This Row],[KC Wheat]]) -> -7932.6 | U42: =IF(Table5[[#This Row],[Energies]]="","",U41+Table5[[#This Row],[Energies]]) -> 0 | V42: =IF(N42<>"",IFERROR(V41+N42,""),"") -> 367256.52 | W42: 681280 | X42: =IFERROR(N42/W42,"") -> -0.099572701 | AC42: 386207.63
A43: =TEXT(B43,"mmm") -> Jan | B43: 44225 | C43: 3807.9 | D43: 27878.7 | E43: -4233.4 | F43: -9238.2 | G43: -545.1 | H43: -8050.1 | I43: 0 | J43: =IF(SUM(C43:I43)=0,"",SUM(C43:I43)) -> 9619.8 | K43: -278.9 | L43: -641.26 | M43: =IF(SUM(K43:L43)=0,"",SUM(K43:L43)) -> -920.16 | N43: =IFERROR(J43+M43,"") -> 8699.64 | O43: =IF(Table5[[#This Row],[Beans]]="","",O42+Table5[[#This Row],[Beans]]) -> 51410.1 | P43: =IF(Table5[[#This Row],[Meal]]="","",P42+Table5[[#This Row],[Meal]]) -> 314650.6 | Q43: =IF(Table5[[#This Row],[Oil]]="","",Q42+Table5[[#This Row],[Oil]]) -> 16326.1 | R43: =IF(Table5[[#This Row],[Corn]]="","",R42+Table5[[#This Row],[Corn]]) -> -145995.5 | S43: =IF(Table5[[#This Row],[Wheat]]="","",S42+Table5[[#This Row],[Wheat]]) -> 204276.5 | T43: =IF(Table5[[#This Row],[KC Wheat]]="","",T42+Table5[[#This Row],[KC Wheat]]) -> -15982.7 | U43: =IF(Table5[[#This Row],[Energies]]="","",U42+Table5[[#This Row],[Energies]]) -> 0 | V43: =IF(N43<>"",IFERROR(V42+N43,""),"") -> 375956.16 | W43: 620346 | X43: =IFERROR(N43/W43,"") -> 0.014023851 | Y43: -7553 | AC43: 462814.47
A44: =TEXT(B44,"mmm") -> Feb | B44: 44228 | C44: 58282.7 | D44: -53339.3 | E44: 4572.6 | F44: 11868.9 | G44: -1006.4 | H44: 4346.7 | I44: 0 | J44: =IF(SUM(C44:I44)=0,"",SUM(C44:I44)) -> 24725.2 | K44: -160.15 | L44: -736.17 | M44: =IF(SUM(K44:L44)=0,"",SUM(K44:L44)) -> -896.32 | N44: =IFERROR(J44+M44,"") -> 23828.88 | O44: =IF(Table5[[#This Row],[Beans]]="","",O43+Table5[[#This Row],[Beans]]) -> 109692.8 | P44: =IF(Table5[[#This Row],[Meal]]="","",P43+Table5[[#This Row],[Meal]]) -> 261311.3 | Q44: =IF(Table5[[#This Row],[Oil]]="","",Q43+Table5[[#This Row],[Oil]]) -> 20898.7 | R44: =IF(Table5[[#This Row],[Corn]]="","",R43+Table5[[#This Row],[Corn]]) -> -134126.6 | S44: =IF(Table5[[#This Row],[Wheat]]="","",S43+Table5[[#This Row],[Wheat]]) -> 203270.1 | T44: =IF(Table5[[#This Row],[KC Wheat]]="","",T43+Table5[[#This Row],[KC Wheat]]) -> -11636 | U44: =IF(Table5[[#This Row],[Energies]]="","",U43+Table5[[#This Row],[Energies]]) -> 0 | V44: =IF(N44<>"",IFERROR(V43+N44,""),"") -> 399785.04 | W44: 522671 | X44: =IFERROR(N44/W44,"") -> 0.045590591 | Y44: -513.45 | AC44: 456946.9
A45: =TEXT(B45,"mmm") -> Feb | B45: 44229 | C45: 34124 | D45: -11984.2 | E45: 8074.4 | F45: 49477.2 | G45: -8117.4 | H45: 1747.2 | I45: 0 | J45: =IF(SUM(C45:I45)=0,"",SUM(C45:I45)) -> 73321.2 | K45: -135.15 | L45: -621.51 | M45: =IF(SUM(K45:L45)=0,"",SUM(K45:L45)) -> -756.66 | N45: =IFERROR(J45+M45,"") -> 72564.54 | O45: =IF(Table5[[#This Row],[Beans]]="","",O44+Table5[[#This Row],[Beans]]) -> 143816.8 | P45: =IF(Table5[[#This Row],[Meal]]="","",P44+Table5[[#This Row],[Meal]]) -> 249327.1 | Q45: =IF(Table5[[#This Row],[Oil]]="","",Q44+Table5[[#This Row],[Oil]]) -> 28973.1 | R45: =IF(Table5[[#This Row],[Corn]]="","",R44+Table5[[#This Row],[Corn]]) -> -84649.4 | S45: =IF(Table5[[#This Row],[Wheat]]="","",S44+Table5[[#This Row],[Wheat]]) -> 195152.7 | T45: =IF(Table5[[#This Row],[KC Wheat]]="","",T44+Table5[[#This Row],[KC Wheat]]) -> -9888.8 | U45: =IF(Table5[[#This Row],[Energies]]="","",U44+Table5[[#This Row],[Energies]]) -> 0 | V45: =IF(N45<>"",IFERROR(V44+N45,""),"") -> 472349.58 | W45: 576936 | X45: =IFERROR(N45/W45,"") -> 0.12577572 | AC45: 514063.24
A46: =TEXT(B46,"mmm") -> Feb | B46: 44230 | C46: 46706.4 | D46: -1685.9 | E46: 17456.3 | F46: 49311.7 | G46: 713.5 | H46: -4606.6 | I46: 0 | J46: =IF(SUM(C46:I46)=0,"",SUM(C46:I46)) -> 107895.4 | K46: -249.65 | L46: -1148.39 | M46: =IF(SUM(K46:L46)=0,"",SUM(K46:L46)) -> -1398.04 | N46: =IFERROR(J46+M46,"") -> 106497.36 | O46: =IF(Table5[[#This Row],[Beans]]="","",O45+Table5[[#This Row],[Beans]]) -> 190523.2 | P46: =IF(Table5[[#This Row],[Meal]]="","",P45+Table5[[#This Row],[Meal]]) -> 247641.2 | Q46: =IF(Table5[[#This Row],[Oil]]="","",Q45+Table5[[#This Row],[Oil]]) -> 46429.4 | R46: =IF(Table5[[#This Row],[Corn]]="","",R45+Table5[[#This Row],[Corn]]) -> -35337.7 | S46: =IF(Table5[[#This Row],[Wheat]]="","",S45+Table5[[#This Row],[Wheat]]) -> 195866.2 | T46: =IF(Table5[[#This Row],[KC Wheat]]="","",T45+Table5[[#This Row],[KC Wheat]]) -> -14495.4 | U46: =IF(Table5[[#This Row],[Energies]]="","",U45+Table5[[#This Row],[Energies]]) -> 0 | V46: =IF(N46<>"",IFERROR(V45+N46,""),"") -> 578846.94 | W46: 542400 | X46: =IFERROR(N46/W46,"") -> 0.19634469 | AC46: 594900.05
A47: =TEXT(B47,"mmm") -> Feb | B47: 44231 | C47: 10811.8 | D47: -8945.5 | E47: 5022.4 | F47: 5298.6 | G47: -7480.6 | H47: -1414.9 | I47: 0 | J47: =IF(SUM(C47:I47)=0,"",SUM(C47:I47)) -> 3291.8 | K47: -101.05 | L47: -464.71 | M47: =IF(SUM(K47:L47)=0,"",SUM(K47:L47)) -> -565.76 | N47: =IFERROR(J47+M47,"") -> 2726.04 | O47: =IF(Table5[[#This Row],[Beans]]="","",O46+Table5[[#This Row],[Beans]]) -> 201335 | P47: =IF(Table5[[#This Row],[Meal]]="","",P46+Table5[[#This Row],[Meal]]) -> 238695.7 | Q47: =IF(Table5[[#This Row],[Oil]]="","",Q46+Table5[[#This Row],[Oil]]) -> 51451.8 | R47: =IF(Table5[[#This Row],[Corn]]="","",R46+Table5[[#This Row],[Corn]]) -> -30039.1 | S47: =IF(Table5[[#This Row],[Wheat]]="","",S46+Table5[[#This Row],[Wheat]]) -> 188385.6 | T47: =IF(Table5[[#This Row],[KC Wheat]]="","",T46+Table5[[#This Row],[KC Wheat]]) -> -15910.3 | U47: =IF(Table5[[#This Row],[Energies]]="","",U46+Table5[[#This Row],[Energies]]) -> 0 | V47: =IF(N47<>"",IFERROR(V46+N47,""),"") -> 581572.98 | W47: 619731 | X47: =IFERROR(N47/W47,"") -> 0.0043987472 | Y47: -1371.03 | AA47: -444201 | AC47: 139617.29
A48: =TEXT(B48,"mmm") -> Feb | B48: 44232 | C48: 17362.1 | D48: 2621.9 | E48: 8349.2 | F48: 8278.7 | G48: 251.8 | H48: -5468.3 | I48: 0 | J48: =IF(SUM(C48:I48)=0,"",SUM(C48:I48)) -> 31395.4 | K48: -138.35 | L48: -635.66 | M48: =IF(SUM(K48:L48)=0,"",SUM(K48:L48)) -> -774.01 | N48: =IFERROR(J48+M48,"") -> 30621.39 | O48: =IF(Table5[[#This Row],[Beans]]="","",O47+Table5[[#This Row],[Beans]]) -> 218697.1 | P48: =IF(Table5[[#This Row],[Meal]]="","",P47+Table5[[#This Row],[Meal]]) -> 241317.6 | Q48: =IF(Table5[[#This Row],[Oil]]="","",Q47+Table5[[#This Row],[Oil]]) -> 59801 | R48: =IF(Table5[[#This Row],[Corn]]="","",R47+Table5[[#This Row],[Corn]]) -> -21760.4 | S48: =IF(Table5[[#This Row],[Wheat]]="","",S47+Table5[[#This Row],[Wheat]]) -> 188637.4 | T48: =IF(Table5[[#This Row],[KC Wheat]]="","",T47+Table5[[#This Row],[KC Wheat]]) -> -21378.6 | U48: =IF(Table5[[#This Row],[Energies]]="","",U47+Table5[[#This Row],[Energies]]) -> 0 | V48: =IF(N48<>"",IFERROR(V47+N48,""),"") -> 612194.37 | W48: 630166 | X48: =IFERROR(N48/W48,"") -> 0.048592577 | Y48: -5000 | AC48: 201604.53
A49: =TEXT(B49,"mmm") -> Feb | B49: 44235 | C49: -3690.2 | D49: -8104.7 | E49: -2969.6 | F49: -50252.1 | G49: 1872.5 | H49: -2799.5 | I49: 0 | J49: =IF(SUM(C49:I49)=0,"",SUM(C49:I49)) -> -65943.6 | K49: -210.15 | L49: -966.51 | M49: =IF(SUM(K49:L49)=0,"",SUM(K49:L49)) -> -1176.66 | N49: =IFERROR(J49+M49,"") -> -67120.26 | O49: =IF(Table5[[#This Row],[Beans]]="","",O48+Table5[[#This Row],[Beans]]) -> 215006.9 | P49: =IF(Table5[[#This Row],[Meal]]="","",P48+Table5[[#This Row],[Meal]]) -> 233212.9 | Q49: =IF(Table5[[#This Row],[Oil]]="","",Q48+Table5[[#This Row],[Oil]]) -> 56831.4 | R49: =IF(Table5[[#This Row],[Corn]]="","",R48+Table5[[#This Row],[Corn]]) -> -72012.5 | S49: =IF(Table5[[#This Row],[Wheat]]="","",S48+Table5[[#This Row],[Wheat]]) -> 190509.9 | T49: =IF(Table5[[#This Row],[KC Wheat]]="","",T48+Table5[[#This Row],[KC Wheat]]) -> -24178.1 | U49: =IF(Table5[[#This Row],[Energies]]="","",U48+Table5[[#This Row],[Energies]]) -> 0 | V49: =IF(N49<>"",IFERROR(V48+N49,""),"") -> 545074.11 | W49: 658899 | X49: =IFERROR(N49/W49,"") -> -0.1018673 | Y49: -125 | AC49: 119762.37
A50: =TEXT(B50,"mmm") -> Feb | B50: 44236 | C50: -9710.8 | D50: 3476.8 | E50: -15131.2 | F50: -23396.7 | G50: -29376.4 | H50: 17633.4 | I50: 0 | J50: =IF(SUM(C50:I50)=0,"",SUM(C50:I50)) -> -56504.9 | K50: -112.35 | L50: -516.57 | M50: =IF(SUM(K50:L50)=0,"",SUM(K50:L50)) -> -628.92 | N50: =IFERROR(J50+M50,"") -> -57133.82 | O50: =IF(Table5[[#This Row],[Beans]]="","",O49+Table5[[#This Row],[Beans]]) -> 205296.1 | P50: =IF(Table5[[#This Row],[Meal]]="","",P49+Table5[[#This Row],[Meal]]) -> 236689.7 | Q50: =IF(Table5[[#This Row],[Oil]]="","",Q49+Table5[[#This Row],[Oil]]) -> 41700.2 | R50: =IF(Table5[[#This Row],[Corn]]="","",R49+Table5[[#This Row],[Corn]]) -> -95409.2 | S50: =IF(Table5[[#This Row],[Wheat]]="","",S49+Table5[[#This Row],[Wheat]]) -> 161133.5 | T50: =IF(Table5[[#This Row],[KC Wheat]]="","",T49+Table5[[#This Row],[KC Wheat]]) -> -6544.7 | U50: =IF(Table5[[#This Row],[Energies]]="","",U49+Table5[[#This Row],[Energies]]) -> 0 | V50: =IF(N50<>"",IFERROR(V49+N50,""),"") -> 487940.29 | W50: 650675 | X50: =IFERROR(N50/W50,"") -> -0.087807 | AC50: 55210.2
A51: =TEXT(B51,"mmm") -> Feb | B51: 44237 | C51: 7515 | D51: 52155.4 | E51: 19400.5 | F51: 2680.9 | G51: -3481.6 | H51: -6106.5 | I51: 0 | J51: =IF(SUM(C51:I51)=0,"",SUM(C51:I51)) -> 72163.7 | K51: -166.35 | L51: -763.62 | M51: =IF(SUM(K51:L51)=0,"",SUM(K51:L51)) -> -929.97 | N51: =IFERROR(J51+M51,"") -> 71233.73 | O51: =IF(Table5[[#This Row],[Beans]]="","",O50+Table5[[#This Row],[Beans]]) -> 212811.1 | P51: =IF(Table5[[#This Row],[Meal]]="","",P50+Table5[[#This Row],[Meal]]) -> 288845.1 | Q51: =IF(Table5[[#This Row],[Oil]]="","",Q50+Table5[[#This Row],[Oil]]) -> 61100.7 | R51: =IF(Table5[[#This Row],[Corn]]="","",R50+Table5[[#This Row],[Corn]]) -> -92728.3 | S51: =IF(Table5[[#This Row],[Wheat]]="","",S50+Table5[[#This Row],[Wheat]]) -> 157651.9 | T51: =IF(Table5[[#This Row],[KC Wheat]]="","",T50+Table5[[#This Row],[KC Wheat]]) -> -12651.2 | U51: =IF(Table5[[#This Row],[Energies]]="","",U50+Table5[[#This Row],[Energies]]) -> 0 | V51: =IF(N51<>"",IFERROR(V50+N51,""),"") -> 559174.02 | W51: 600339 | X51: =IFERROR(N51/W51,"") -> 0.11865584 | Y51: 4125.58 | AC51: 142876.81
A52: =TEXT(B52,"mmm") -> Feb | B52: 44238 | C52: 14274.5 | D52: -5745.4 | E52: 14385.5 | F52: -6610.6 | G52: -2168.5 | H52: 23.6 | I52: 0 | J52: =IF(SUM(C52:I52)=0,"",SUM(C52:I52)) -> 14159.1 | K52: -250.05 | L52: -1142.76 | M52: =IF(SUM(K52:L52)=0,"",SUM(K52:L52)) -> -1392.81 | N52: =IFERROR(J52+M52,"") -> 12766.29 | O52: =IF(Table5[[#This Row],[Beans]]="","",O51+Table5[[#This Row],[Beans]]) -> 227085.6 | P52: =IF(Table5[[#This Row],[Meal]]="","",P51+Table5[[#This Row],[Meal]]) -> 283099.7 | Q52: =IF(Table5[[#This Row],[Oil]]="","",Q51+Table5[[#This Row],[Oil]]) -> 75486.2 | R52: =IF(Table5[[#This Row],[Corn]]="","",R51+Table5[[#This Row],[Corn]]) -> -99338.9 | S52: =IF(Table5[[#This Row],[Wheat]]="","",S51+Table5[[#This Row],[Wheat]]) -> 155483.4 | T52: =IF(Table5[[#This Row],[KC Wheat]]="","",T51+Table5[[#This Row],[KC Wheat]]) -> -12627.6 | U52: =IF(Table5[[#This Row],[Energies]]="","",U51+Table5[[#This Row],[Energies]]) -> 0 | V52: =IF(N52<>"",IFERROR(V51+N52,""),"") -> 571940.31 | W52: 721566 | X52: =IFERROR(N52/W52,"") -> 0.017692477 | AC52: 153823.75
A53: =TEXT(B53,"mmm") -> Feb | B53: 44239 | C53: -11725.8 | D53: -11706.8 | E53: 8810.7 | F53: 5594 | G53: 2570.3 | H53: -7141.7 | I53: 0 | J53: =IF(SUM(C53:I53)=0,"",SUM(C53:I53)) -> -13599.3 | K53: -46.6 | L53: -211.84 | M53: =IF(SUM(K53:L53)=0,"",SUM(K53:L53)) -> -258.44 | N53: =IFERROR(J53+M53,"") -> -13857.74 | O53: =IF(Table5[[#This Row],[Beans]]="","",O52+Table5[[#This Row],[Beans]]) -> 215359.8 | P53: =IF(Table5[[#This Row],[Meal]]="","",P52+Table5[[#This Row],[Meal]]) -> 271392.9 | Q53: =IF(Table5[[#This Row],[Oil]]="","",Q52+Table5[[#This Row],[Oil]]) -> 84296.9 | R53: =IF(Table5[[#This Row],[Corn]]="","",R52+Table5[[#This Row],[Corn]]) -> -93744.9 | S53: =IF(Table5[[#This Row],[Wheat]]="","",S52+Table5[[#This Row],[Wheat]]) -> 158053.7 | T53: =IF(Table5[[#This Row],[KC Wheat]]="","",T52+Table5[[#This Row],[KC Wheat]]) -> -19769.3 | U53: =IF(Table5[[#This Row],[Energies]]="","",U52+Table5[[#This Row],[Energies]]) -> 0 | V53: =IF(N53<>"",IFERROR(V52+N53,""),"") -> 558082.57 | W53: 873267 | X53: =IFERROR(N53/W53,"") -> -0.015868847 | AC53: 128562.06
A54: =TEXT(B54,"mmm") -> Feb | B54: 44243 | C54: -11102.8 | D54: -871.6 | E54: 10337.9 | F54: 28608.6 | G54: 11305.9 | H54: 8815.9 | I54: 0 | J54: =IF(SUM(C54:I54)=0,"",SUM(C54:I54)) -> 47093.9 | K54: -147.3 | L54: -676.92 | M54: =IF(SUM(K54:L54)=0,"",SUM(K54:L54)) -> -824.22 | N54: =IFERROR(J54+M54,"") -> 46269.68 | O54: =IF(Table5[[#This Row],[Beans]]="","",O53+Table5[[#This Row],[Beans]]) -> 204257 | P54: =IF(Table5[[#This Row],[Meal]]="","",P53+Table5[[#This Row],[Meal]]) -> 270521.3 | Q54: =IF(Table5[[#This Row],[Oil]]="","",Q53+Table5[[#This Row],[Oil]]) -> 94634.8 | R54: =IF(Table5[[#This Row],[Corn]]="","",R53+Table5[[#This Row],[Corn]]) -> -65136.3 | S54: =IF(Table5[[#This Row],[Wheat]]="","",S53+Table5[[#This Row],[Wheat]]) -> 169359.6 | T54: =IF(Table5[[#This Row],[KC Wheat]]="","",T53+Table5[[#This Row],[KC Wheat]]) -> -10953.4 | U54: =IF(Table5[[#This Row],[Energies]]="","",U53+Table5[[#This Row],[Energies]]) -> 0 | V54: =IF(N54<>"",IFERROR(V53+N54,""),"") -> 604352.25 | W54: 852989 | X54: =IFERROR(N54/W54,"") -> 0.05424417 | AC54: 171293.84
A55: =TEXT(B55,"mmm") -> Feb | B55: 44244 | C55: 6667.7 | D55: 14253.8 | E55: 9542.9 | F55: -8028 | G55: -10485 | H55: -4034.7 | I55: 0 | J55: =IF(SUM(C55:I55)=0,"",SUM(C55:I55)) -> 7916.7 | K55: -159.25 | L55: -731.05 | M55: =IF(SUM(K55:L55)=0,"",SUM(K55:L55)) -> -890.3 | N55: =IFERROR(J55+M55,"") -> 7026.4 | O55: =IF(Table5[[#This Row],[Beans]]="","",O54+Table5[[#This Row],[Beans]]) -> 210924.7 | P55: =IF(Table5[[#This Row],[Meal]]="","",P54+Table5[[#This Row],[Meal]]) -> 284775.1 | Q55: =IF(Table5[[#This Row],[Oil]]="","",Q54+Table5[[#This Row],[Oil]]) -> 104177.7 | R55: =IF(Table5[[#This Row],[Corn]]="","",R54+Table5[[#This Row],[Corn]]) -> -73164.3 | S55: =IF(Table5[[#This Row],[Wheat]]="","",S54+Table5[[#This Row],[Wheat]]) -> 158874.6 | T55: =IF(Table5[[#This Row],[KC Wheat]]="","",T54+Table5[[#This Row],[KC Wheat]]) -> -14988.1 | U55: =IF(Table5[[#This Row],[Energies]]="","",U54+Table5[[#This Row],[Energies]]) -> 0 | V55: =IF(N55<>"",IFERROR(V54+N55,""),"") -> 611378.65 | W55: 821560 | X55: =IFERROR(N55/W55,"") -> 0.0085525099 | AC55: 200797.29
A56: =TEXT(B56,"mmm") -> Feb | B56: 44245 | C56: -20122.3 | D56: 2070.1 | E56: 243.6 | F56: -9425.9 | G56: -268 | H56: 4723.4 | I56: 0 | J56: =IF(SUM(C56:I56)=0,"",SUM(C56:I56)) -> -22779.1 | K56: -246.35 | L56: -1133.06 | M56: =IF(SUM(K56:L56)=0,"",SUM(K56:L56)) -> -1379.41 | N56: =IFERROR(J56+M56,"") -> -24158.51 | O56: =IF(Table5[[#This Row],[Beans]]="","",O55+Table5[[#This Row],[Beans]]) -> 190802.4 | P56: =IF(Table5[[#This Row],[Meal]]="","",P55+Table5[[#This Row],[Meal]]) -> 286845.2 | Q56: =IF(Table5[[#This Row],[Oil]]="","",Q55+Table5[[#This Row],[Oil]]) -> 104421.3 | R56: =IF(Table5[[#This Row],[Corn]]="","",R55+Table5[[#This Row],[Corn]]) -> -82590.2 | S56: =IF(Table5[[#This Row],[Wheat]]="","",S55+Table5[[#This Row],[Wheat]]) -> 158606.6 | T56: =IF(Table5[[#This Row],[KC Wheat]]="","",T55+Table5[[#This Row],[KC Wheat]]) -> -10264.7 | U56: =IF(Table5[[#This Row],[Energies]]="","",U55+Table5[[#This Row],[Energies]]) -> 0 | V56: =IF(N56<>"",IFERROR(V55+N56,""),"") -> 587220.14 | W56: 752975 | X56: =IFERROR(N56/W56,"") -> -0.03208408 | AC56: 160647.63
A57: =TEXT(B57,"mmm") -> Feb | B57: 44246 | C57: 39466.6 | D57: -21139.3 | E57: -7004.6 | F57: 28821.2 | G57: -25503.9 | H57: 9187.7 | I57: 0 | J57: =IF(SUM(C57:I57)=0,"",SUM(C57:I57)) -> 23827.7 | K57: -1305.95 | L57: -3887.69 | M57: =IF(SUM(K57:L57)=0,"",SUM(K57:L57)) -> -5193.64 | N57: =IFERROR(J57+M57,"") -> 18634.06 | O57: =IF(Table5[[#This Row],[Beans]]="","",O56+Table5[[#This Row],[Beans]]) -> 230269 | P57: =IF(Table5[[#This Row],[Meal]]="","",P56+Table5[[#This Row],[Meal]]) -> 265705.9 | Q57: =IF(Table5[[#This Row],[Oil]]="","",Q56+Table5[[#This Row],[Oil]]) -> 97416.7 | R57: =IF(Table5[[#This Row],[Corn]]="","",R56+Table5[[#This Row],[Corn]]) -> -53769 | S57: =IF(Table5[[#This Row],[Wheat]]="","",S56+Table5[[#This Row],[Wheat]]) -> 133102.7 | T57: =IF(Table5[[#This Row],[KC Wheat]]="","",T56+Table5[[#This Row],[KC Wheat]]) -> -1077 | U57: =IF(Table5[[#This Row],[Energies]]="","",U56+Table5[[#This Row],[Energies]]) -> 0 | V57: =IF(N57<>"",IFERROR(V56+N57,""),"") -> 605854.2 | W57: 521745 | X57: =IFERROR(N57/W57,"") -> 0.03571488 | AC57: 179802.74
A58: =TEXT(B58,"mmm") -> Feb | B58: 44249 | C58: 55 | D58: -1595.7 | E58: 1645.7 | F58: 16633.6 | G58: -2177.3 | H58: 8264.5 | I58: 0 | J58: =IF(SUM(C58:I58)=0,"",SUM(C58:I58)) -> 22825.8 | K58: -81.65 | L58: -375.59 | M58: =IF(SUM(K58:L58)=0,"",SUM(K58:L58)) -> -457.24 | N58: =IFERROR(J58+M58,"") -> 22368.56 | O58: =IF(Table5[[#This Row],[Beans]]="","",O57+Table5[[#This Row],[Beans]]) -> 230324 | P58: =IF(Table5[[#This Row],[Meal]]="","",P57+Table5[[#This Row],[Meal]]) -> 264110.2 | Q58: =IF(Table5[[#This Row],[Oil]]="","",Q57+Table5[[#This Row],[Oil]]) -> 99062.4 | R58: =IF(Table5[[#This Row],[Corn]]="","",R57+Table5[[#This Row],[Corn]]) -> -37135.4 | S58: =IF(Table5[[#This Row],[Wheat]]="","",S57+Table5[[#This Row],[Wheat]]) -> 130925.4 | T58: =IF(Table5[[#This Row],[KC Wheat]]="","",T57+Table5[[#This Row],[KC Wheat]]) -> 7187.5 | U58: =IF(Table5[[#This Row],[Energies]]="","",U57+Table5[[#This Row],[Energies]]) -> 0 | V58: =IF(N58<>"",IFERROR(V57+N58,""),"") -> 628222.76 | W58: 522057 | X58: =IFERROR(N58/W58,"") -> 0.042846969 | Y58: -4516.62 | AC58: 202314.5
A59: =TEXT(B59,"mmm") -> Feb | B59: 44250 | C59: -5828.8 | D59: -7625.8 | E59: -17720.6 | F59: 20024.6 | G59: -4327.3 | H59: -4188.3 | I59: 0 | J59: =IF(SUM(C59:I59)=0,"",SUM(C59:I59)) -> -19666.2 | K59: -107.05 | L59: -492.43 | M59: =IF(SUM(K59:L59)=0,"",SUM(K59:L59)) -> -599.48 | N59: =IFERROR(J59+M59,"") -> -20265.68 | O59: =IF(Table5[[#This Row],[Beans]]="","",O58+Table5[[#This Row],[Beans]]) -> 224495.2 | P59: =IF(Table5[[#This Row],[Meal]]="","",P58+Table5[[#This Row],[Meal]]) -> 256484.4 | Q59: =IF(Table5[[#This Row],[Oil]]="","",Q58+Table5[[#This Row],[Oil]]) -> 81341.8 | R59: =IF(Table5[[#This Row],[Corn]]="","",R58+Table5[[#This Row],[Corn]]) -> -17110.8 | S59: =IF(Table5[[#This Row],[Wheat]]="","",S58+Table5[[#This Row],[Wheat]]) -> 126598.1 | T59: =IF(Table5[[#This Row],[KC Wheat]]="","",T58+Table5[[#This Row],[KC Wheat]]) -> 2999.2 | U59: =IF(Table5[[#This Row],[Energies]]="","",U58+Table5[[#This Row],[Energies]]) -> 0 | V59: =IF(N59<>"",IFERROR(V58+N59,""),"") -> 607957.08 | W59: 482181 | X59: =IFERROR(N59/W59,"") -> -0.042029197 | AC59: 185147.27
A60: =TEXT(B60,"mmm") -> Feb | B60: 44251 | C60: -33683.7 | D60: 13649.9 | E60: -3258.5 | F60: -36806.9 | G60: -2037.4 | H60: 687.4 | I60: 0 | J60: =IF(SUM(C60:I60)=0,"",SUM(C60:I60)) -> -61449.2 | K60: -13.55 | L60: -62.33 | M60: =IF(SUM(K60:L60)=0,"",SUM(K60:L60)) -> -75.88 | N60: =IFERROR(J60+M60,"") -> -61525.08 | O60: =IF(Table5[[#This Row],[Beans]]="","",O59+Table5[[#This Row],[Beans]]) -> 190811.5 | P60: =IF(Table5[[#This Row],[Meal]]="","",P59+Table5[[#This Row],[Meal]]) -> 270134.3 | Q60: =IF(Table5[[#This Row],[Oil]]="","",Q59+Table5[[#This Row],[Oil]]) -> 78083.3 | R60: =IF(Table5[[#This Row],[Corn]]="","",R59+Table5[[#This Row],[Corn]]) -> -53917.7 | S60: =IF(Table5[[#This Row],[Wheat]]="","",S59+Table5[[#This Row],[Wheat]]) -> 124560.7 | T60: =IF(Table5[[#This Row],[KC Wheat]]="","",T59+Table5[[#This Row],[KC Wheat]]) -> 3686.6 | U60: =IF(Table5[[#This Row],[Energies]]="","",U59+Table5[[#This Row],[Energies]]) -> 0 | V60: =IF(N60<>"",IFERROR(V59+N60,""),"") -> 546432 | W60: 467716 | X60: =IFERROR(N60/W60,"") -> -0.13154367 | AC60: 115482.14
A61: =TEXT(B61,"mmm") -> Feb | B61: 44252 | C61: 60268.5 | D61: -8075.6 | E61: 10267.2 | F61: 22290.3 | G61: -8430.9 | H61: 1920.4 | I61: 0 | J61: =IF(SUM(C61:I61)=0,"",SUM(C61:I61)) -> 78239.9 | K61: -102.55 | L61: -471.73 | M61: =IF(SUM(K61:L61)=0,"",SUM(K61:L61)) -> -574.28 | N61: =IFERROR(J61+M61,"") -> 77665.62 | O61: =IF(Table5[[#This Row],[Beans]]="","",O60+Table5[[#This Row],[Beans]]) -> 251080 | P61: =IF(Table5[[#This Row],[Meal]]="","",P60+Table5[[#This Row],[Meal]]) -> 262058.7 | Q61: =IF(Table5[[#This Row],[Oil]]="","",Q60+Table5[[#This Row],[Oil]]) -> 88350.5 | R61: =IF(Table5[[#This Row],[Corn]]="","",R60+Table5[[#This Row],[Corn]]) -> -31627.4 | S61: =IF(Table5[[#This Row],[Wheat]]="","",S60+Table5[[#This Row],[Wheat]]) -> 116129.8 | T61: =IF(Table5[[#This Row],[KC Wheat]]="","",T60+Table5[[#This Row],[KC Wheat]]) -> 5607 | U61: =IF(Table5[[#This Row],[Energies]]="","",U60+Table5[[#This Row],[Energies]]) -> 0 | V61: =IF(N61<>"",IFERROR(V60+N61,""),"") -> 624097.62 | W61: 453107 | X61: =IFERROR(N61/W61,"") -> 0.1714068 | AC61: 215498.86
A62: =TEXT(B62,"mmm") -> Feb | B62: 44253 | C62: -9047.1 | D62: 5719.2 | E62: 4943.2 | F62: 16271.5 | G62: 10210.3 | H62: 7790.7 | I62: 0 | J62: =IF(SUM(C62:I62)=0,"",SUM(C62:I62)) -> 35887.8 | K62: -117.35 | L62: -539.81 | M62: =IF(SUM(K62:L62)=0,"",SUM(K62:L62)) -> -657.16 | N62: =IFERROR(J62+M62,"") -> 35230.64 | O62: =IF(Table5[[#This Row],[Beans]]="","",O61+Table5[[#This Row],[Beans]]) -> 242032.9 | P62: =IF(Table5[[#This Row],[Meal]]="","",P61+Table5[[#This Row],[Meal]]) -> 267777.9 | Q62: =IF(Table5[[#This Row],[Oil]]="","",Q61+Table5[[#This Row],[Oil]]) -> 93293.7 | R62: =IF(Table5[[#This Row],[Corn]]="","",R61+Table5[[#This Row],[Corn]]) -> -15355.9 | S62: =IF(Table5[[#This Row],[Wheat]]="","",S61+Table5[[#This Row],[Wheat]]) -> 126340.1 | T62: =IF(Table5[[#This Row],[KC Wheat]]="","",T61+Table5[[#This Row],[KC Wheat]]) -> 13397.7 | U62: =IF(Table5[[#This Row],[Energies]]="","",U61+Table5[[#This Row],[Energies]]) -> 0 | V62: =IF(N62<>"",IFERROR(V61+N62,""),"") -> 659328.26 | W62: 506584 | X62: =IFERROR(N62/W62,"") -> 0.069545505 | Y62: -4485.42 | AC62: 231715.7
A63: =TEXT(B63,"mmm") -> Mar | B63: 44256 | C63: 56897.8 | D63: -18684.1 | E63: 6045 | F63: 18852.2 | G63: -11806.9 | H63: -7513.7 | I63: 0 | J63: =IF(SUM(C63:I63)=0,"",SUM(C63:I63)) -> 43790.3 | K63: -60.3 | L63: -277.38 | M63: =IF(SUM(K63:L63)=0,"",SUM(K63:L63)) -> -337.68 | N63: =IFERROR(J63+M63,"") -> 43452.62 | O63: =IF(Table5[[#This Row],[Beans]]="","",O62+Table5[[#This Row],[Beans]]) -> 298930.7 | P63: =IF(Table5[[#This Row],[Meal]]="","",P62+Table5[[#This Row],[Meal]]) -> 249093.8 | Q63: =IF(Table5[[#This Row],[Oil]]="","",Q62+Table5[[#This Row],[Oil]]) -> 99338.7 | R63: =IF(Table5[[#This Row],[Corn]]="","",R62+Table5[[#This Row],[Corn]]) -> 3496.3 | S63: =IF(Table5[[#This Row],[Wheat]]="","",S62+Table5[[#This Row],[Wheat]]) -> 114533.2 | T63: =IF(Table5[[#This Row],[KC Wheat]]="","",T62+Table5[[#This Row],[KC Wheat]]) -> 5884 | U63: =IF(Table5[[#This Row],[Energies]]="","",U62+Table5[[#This Row],[Energies]]) -> 0 | V63: =IF(N63<>"",IFERROR(V62+N63,""),"") -> 702780.88 | W63: 451968 | X63: =IFERROR(N63/W63,"") -> 0.096140921 | Y63: -476.96 | AC63: 239156.5
A64: =TEXT(B64,"mmm") -> Mar | B64: 44257 | C64: -10051.4 | D64: 589.6 | E64: -4300.4 | F64: -12318.3 | G64: 5901.3 | H64: -265.1 | I64: 0 | J64: =IF(SUM(C64:I64)=0,"",SUM(C64:I64)) -> -20444.3 | K64: -83.4 | L64: -383.64 | M64: =IF(SUM(K64:L64)=0,"",SUM(K64:L64)) -> -467.04 | N64: =IFERROR(J64+M64,"") -> -20911.34 | O64: =IF(Table5[[#This Row],[Beans]]="","",O63+Table5[[#This Row],[Beans]]) -> 288879.3 | P64: =IF(Table5[[#This Row],[Meal]]="","",P63+Table5[[#This Row],[Meal]]) -> 249683.4 | Q64: =IF(Table5[[#This Row],[Oil]]="","",Q63+Table5[[#This Row],[Oil]]) -> 95038.3 | R64: =IF(Table5[[#This Row],[Corn]]="","",R63+Table5[[#This Row],[Corn]]) -> -8822 | S64: =IF(Table5[[#This Row],[Wheat]]="","",S63+Table5[[#This Row],[Wheat]]) -> 120434.5 | T64: =IF(Table5[[#This Row],[KC Wheat]]="","",T63+Table5[[#This Row],[KC Wheat]]) -> 5618.9 | U64: =IF(Table5[[#This Row],[Energies]]="","",U63+Table5[[#This Row],[Energies]]) -> 0 | V64: =IF(N64<>"",IFERROR(V63+N64,""),"") -> 681869.54 | W64: 480114 | X64: =IFERROR(N64/W64,"") -> -0.043554947 | AA64: -150000 | AC64: 98144.46
A65: =TEXT(B65,"mmm") -> Mar | B65: 44258 | C65: -24901.2 | D65: -6048.4 | E65: -10700.9 | F65: 25933.9 | G65: 16328.3 | H65: -1359.8 | I65: 0 | J65: =IF(SUM(C65:I65)=0,"",SUM(C65:I65)) -> -748.1 | K65: -94.2 | L65: -433.32 | M65: =IF(SUM(K65:L65)=0,"",SUM(K65:L65)) -> -527.52 | N65: =IFERROR(J65+M65,"") -> -1275.62 | O65: =IF(Table5[[#This Row],[Beans]]="","",O64+Table5[[#This Row],[Beans]]) -> 263978.1 | P65: =IF(Table5[[#This Row],[Meal]]="","",P64+Table5[[#This Row],[Meal]]) -> 243635 | Q65: =IF(Table5[[#This Row],[Oil]]="","",Q64+Table5[[#This Row],[Oil]]) -> 84337.4 | R65: =IF(Table5[[#This Row],[Corn]]="","",R64+Table5[[#This Row],[Corn]]) -> 17111.9 | S65: =IF(Table5[[#This Row],[Wheat]]="","",S64+Table5[[#This Row],[Wheat]]) -> 136762.8 | T65: =IF(Table5[[#This Row],[KC Wheat]]="","",T64+Table5[[#This Row],[KC Wheat]]) -> 4259.1 | U65: =IF(Table5[[#This Row],[Energies]]="","",U64+Table5[[#This Row],[Energies]]) -> 0 | V65: =IF(N65<>"",IFERROR(V64+N65,""),"") -> 680593.92 | W65: 544787 | X65: =IFERROR(N65/W65,"") -> -0.0023415023 | Y65: -15899 | AC65: 75272.19
A66: =TEXT(B66,"mmm") -> Mar | B66: 44259 | C66: 34504.1 | D66: -21197.5 | E66: -4923.4 | F66: 6510.4 | G66: 1944.7 | H66: 1738.6 | I66: 0 | J66: =IF(SUM(C66:I66)=0,"",SUM(C66:I66)) -> 18576.9 | K66: -88.15 | L66: -405.49 | M66: =IF(SUM(K66:L66)=0,"",SUM(K66:L66)) -> -493.64 | N66: =IFERROR(J66+M66,"") -> 18083.26 | O66: =IF(Table5[[#This Row],[Beans]]="","",O65+Table5[[#This Row],[Beans]]) -> 298482.2 | P66: =IF(Table5[[#This Row],[Meal]]="","",P65+Table5[[#This Row],[Meal]]) -> 222437.5 | Q66: =IF(Table5[[#This Row],[Oil]]="","",Q65+Table5[[#This Row],[Oil]]) -> 79414 | R66: =IF(Table5[[#This Row],[Corn]]="","",R65+Table5[[#This Row],[Corn]]) -> 23622.3 | S66: =IF(Table5[[#This Row],[Wheat]]="","",S65+Table5[[#This Row],[Wheat]]) -> 138707.5 | T66: =IF(Table5[[#This Row],[KC Wheat]]="","",T65+Table5[[#This Row],[KC Wheat]]) -> 5997.7 | U66: =IF(Table5[[#This Row],[Energies]]="","",U65+Table5[[#This Row],[Energies]]) -> 0 | V66: =IF(N66<>"",IFERROR(V65+N66,""),"") -> 698677.18 | W66: 506741 | X66: =IFERROR(N66/W66,"") -> 0.035685409 | AC66: 111936.05
A67: =TEXT(B67,"mmm") -> Mar | B67: 44260 | C67: -45925.1 | D67: 91.6 | E67: -4150.8 | F67: -35933.2 | G67: 1292.8 | H67: -14213.6 | I67: 0 | J67: =IF(SUM(C67:I67)=0,"",SUM(C67:I67)) -> -98838.3 | K67: -98.3 | L67: -451.25 | M67: =IF(SUM(K67:L67)=0,"",SUM(K67:L67)) -> -549.55 | N67: =IFERROR(J67+M67,"") -> -99387.85 | O67: =IF(Table5[[#This Row],[Beans]]="","",O66+Table5[[#This Row],[Beans]]) -> 252557.1 | P67: =IF(Table5[[#This Row],[Meal]]="","",P66+Table5[[#This Row],[Meal]]) -> 222529.1 | Q67: =IF(Table5[[#This Row],[Oil]]="","",Q66+Table5[[#This Row],[Oil]]) -> 75263.2 | R67: =IF(Table5[[#This Row],[Corn]]="","",R66+Table5[[#This Row],[Corn]]) -> -12310.9 | S67: =IF(Table5[[#This Row],[Wheat]]="","",S66+Table5[[#This Row],[Wheat]]) -> 140000.3 | T67: =IF(Table5[[#This Row],[KC Wheat]]="","",T66+Table5[[#This Row],[KC Wheat]]) -> -8215.9 | U67: =IF(Table5[[#This Row],[Energies]]="","",U66+Table5[[#This Row],[Energies]]) -> 0 | V67: =IF(N67<>"",IFERROR(V66+N67,""),"") -> 599289.33 | W67: 570044 | X67: =IFERROR(N67/W67,"") -> -0.17435119 | Y67: -1334.54 | AC67: 13953.5
A68: =TEXT(B68,"mmm") -> Mar | B68: 44263 | C68: -4444.8 | D68: -15268.1 | E68: 14331.2 | F68: -44666.5 | G68: -10392.9 | H68: -849 | I68: 0 | J68: =IF(SUM(C68:I68)=0,"",SUM(C68:I68)) -> -61290.1 | K68: -34.65 | L68: -159.39 | M68: =IF(SUM(K68:L68)=0,"",SUM(K68:L68)) -> -194.04 | N68: =IFERROR(J68+M68,"") -> -61484.14 | O68: =IF(Table5[[#This Row],[Beans]]="","",O67+Table5[[#This Row],[Beans]]) -> 248112.3 | P68: =IF(Table5[[#This Row],[Meal]]="","",P67+Table5[[#This Row],[Meal]]) -> 207261 | Q68: =IF(Table5[[#This Row],[Oil]]="","",Q67+Table5[[#This Row],[Oil]]) -> 89594.4 | R68: =IF(Table5[[#This Row],[Corn]]="","",R67+Table5[[#This Row],[Corn]]) -> -56977.4 | S68: =IF(Table5[[#This Row],[Wheat]]="","",S67+Table5[[#This Row],[Wheat]]) -> 129607.4 | T68: =IF(Table5[[#This Row],[KC Wheat]]="","",T67+Table5[[#This Row],[KC Wheat]]) -> -9064.9 | U68: =IF(Table5[[#This Row],[Energies]]="","",U67+Table5[[#This Row],[Energies]]) -> 0 | V68: =IF(N68<>"",IFERROR(V67+N68,""),"") -> 537805.19 | W68: 540098 | X68: =IFERROR(N68/W68,"") -> -0.11383886 | AC68: -49006.04
A69: =TEXT(B69,"mmm") -> Mar | B69: 44264 | C69: -3532.4 | D69: -12811.7 | E69: -21134.7 | F69: 19225.5 | G69: 12580.5 | H69: -204.6 | I69: 0 | J69: =IF(SUM(C69:I69)=0,"",SUM(C69:I69)) -> -5877.4 | K69: -106.7 | L69: -490.82 | M69: =IF(SUM(K69:L69)=0,"",SUM(K69:L69)) -> -597.52 | N69: =IFERROR(J69+M69,"") -> -6474.92 | O69: =IF(Table5[[#This Row],[Beans]]="","",O68+Table5[[#This Row],[Beans]]) -> 244579.9 | P69: =IF(Table5[[#This Row],[Meal]]="","",P68+Table5[[#This Row],[Meal]]) -> 194449.3 | Q69: =IF(Table5[[#This Row],[Oil]]="","",Q68+Table5[[#This Row],[Oil]]) -> 68459.7 | R69: =IF(Table5[[#This Row],[Corn]]="","",R68+Table5[[#This Row],[Corn]]) -> -37751.9 | S69: =IF(Table5[[#This Row],[Wheat]]="","",S68+Table5[[#This Row],[Wheat]]) -> 142187.9 | T69: =IF(Table5[[#This Row],[KC Wheat]]="","",T68+Table5[[#This Row],[KC Wheat]]) -> -9269.5 | U69: =IF(Table5[[#This Row],[Energies]]="","",U68+Table5[[#This Row],[Energies]]) -> 0 | V69: =IF(N69<>"",IFERROR(V68+N69,""),"") -> 531330.27 | W69: 574875 | X69: =IFERROR(N69/W69,"") -> -0.011263179 | Y69: -494 | AC69: -92599.56
A70: =TEXT(B70,"mmm") -> Mar | B70: 44265 | C70: 59591.4 | D70: -37263.7 | E70: 10022.9 | F70: 29160.4 | G70: 39591.1 | H70: 3649.2 | I70: 0 | J70: =IF(SUM(C70:I70)=0,"",SUM(C70:I70)) -> 104751.3 | K70: -135.05 | L70: -621.23 | M70: =IF(SUM(K70:L70)=0,"",SUM(K70:L70)) -> -756.28 | N70: =IFERROR(J70+M70,"") -> 103995.02 | O70: =IF(Table5[[#This Row],[Beans]]="","",O69+Table5[[#This Row],[Beans]]) -> 304171.3 | P70: =IF(Table5[[#This Row],[Meal]]="","",P69+Table5[[#This Row],[Meal]]) -> 157185.6 | Q70: =IF(Table5[[#This Row],[Oil]]="","",Q69+Table5[[#This Row],[Oil]]) -> 78482.6 | R70: =IF(Table5[[#This Row],[Corn]]="","",R69+Table5[[#This Row],[Corn]]) -> -8591.5 | S70: =IF(Table5[[#This Row],[Wheat]]="","",S69+Table5[[#This Row],[Wheat]]) -> 181779 | T70: =IF(Table5[[#This Row],[KC Wheat]]="","",T69+Table5[[#This Row],[KC Wheat]]) -> -5620.3 | U70: =IF(Table5[[#This Row],[Energies]]="","",U69+Table5[[#This Row],[Energies]]) -> 0 | V70: =IF(N70<>"",IFERROR(V69+N70,""),"") -> 635325.29 | W70: 540683 | X70: =IFERROR(N70/W70,"") -> 0.1923401 | AC70: 19677.91
A71: =TEXT(B71,"mmm") -> Mar | B71: 44266 | C71: 1518.1 | D71: -2217.7 | E71: -11808.9 | F71: -8801.7 | G71: 17506 | H71: 10885.6 | I71: 0 | J71: =IF(SUM(C71:I71)=0,"",SUM(C71:I71)) -> 7081.4 | K71: -68.75 | L71: -316.22 | M71: =IF(SUM(K71:L71)=0,"",SUM(K71:L71)) -> -384.97 | N71: =IFERROR(J71+M71,"") -> 6696.43 | O71: =IF(Table5[[#This Row],[Beans]]="","",O70+Table5[[#This Row],[Beans]]) -> 305689.4 | P71: =IF(Table5[[#This Row],[Meal]]="","",P70+Table5[[#This Row],[Meal]]) -> 154967.9 | Q71: =IF(Table5[[#This Row],[Oil]]="","",Q70+Table5[[#This Row],[Oil]]) -> 66673.7 | R71: =IF(Table5[[#This Row],[Corn]]="","",R70+Table5[[#This Row],[Corn]]) -> -17393.2 | S71: =IF(Table5[[#This Row],[Wheat]]="","",S70+Table5[[#This Row],[Wheat]]) -> 199285 | T71: =IF(Table5[[#This Row],[KC Wheat]]="","",T70+Table5[[#This Row],[KC Wheat]]) -> 5265.3 | U71: =IF(Table5[[#This Row],[Energies]]="","",U70+Table5[[#This Row],[Energies]]) -> 0 | V71: =IF(N71<>"",IFERROR(V70+N71,""),"") -> 642021.72 | W71: 578674 | X71: =IFERROR(N71/W71,"") -> 0.011572025 | AC71: 42013.69
A72: =TEXT(B72,"mmm") -> Mar | B72: 44267 | C72: -11948.9 | D72: -19035.5 | E72: -10462.6 | F72: -17472.7 | G72: 14002 | H72: 2264 | I72: 0 | J72: =IF(SUM(C72:I72)=0,"",SUM(C72:I72)) -> -42653.7 | K72: -54.5 | L72: -250.7 | M72: =IF(SUM(K72:L72)=0,"",SUM(K72:L72)) -> -305.2 | N72: =IFERROR(J72+M72,"") -> -42958.9 | O72: =IF(Table5[[#This Row],[Beans]]="","",O71+Table5[[#This Row],[Beans]]) -> 293740.5 | P72: =IF(Table5[[#This Row],[Meal]]="","",P71+Table5[[#This Row],[Meal]]) -> 135932.4 | Q72: =IF(Table5[[#This Row],[Oil]]="","",Q71+Table5[[#This Row],[Oil]]) -> 56211.1 | R72: =IF(Table5[[#This Row],[Corn]]="","",R71+Table5[[#This Row],[Corn]]) -> -34865.9 | S72: =IF(Table5[[#This Row],[Wheat]]="","",S71+Table5[[#This Row],[Wheat]]) -> 213287 | T72: =IF(Table5[[#This Row],[KC Wheat]]="","",T71+Table5[[#This Row],[KC Wheat]]) -> 7529.3 | U72: =IF(Table5[[#This Row],[Energies]]="","",U71+Table5[[#This Row],[Energies]]) -> 0 | V72: =IF(N72<>"",IFERROR(V71+N72,""),"") -> 599062.82 | W72: 789371 | X72: =IFERROR(N72/W72,"") -> -0.054421685 | Y72: -675 | AC72: -2576.01
A73: =TEXT(B73,"mmm") -> Mar | B73: 44270 | C73: -26219.9 | D73: -3043.5 | E73: 16416.4 | F73: -36982.7 | G73: -10262.2 | H73: -2713.4 | I73: 0 | J73: =IF(SUM(C73:I73)=0,"",SUM(C73:I73)) -> -62805.3 | K73: -82.05 | L73: -377.43 | M73: =IF(SUM(K73:L73)=0,"",SUM(K73:L73)) -> -459.48 | N73: =IFERROR(J73+M73,"") -> -63264.78 | O73: =IF(Table5[[#This Row],[Beans]]="","",O72+Table5[[#This Row],[Beans]]) -> 267520.6 | P73: =IF(Table5[[#This Row],[Meal]]="","",P72+Table5[[#This Row],[Meal]]) -> 132888.9 | Q73: =IF(Table5[[#This Row],[Oil]]="","",Q72+Table5[[#This Row],[Oil]]) -> 72627.5 | R73: =IF(Table5[[#This Row],[Corn]]="","",R72+Table5[[#This Row],[Corn]]) -> -71848.6 | S73: =IF(Table5[[#This Row],[Wheat]]="","",S72+Table5[[#This Row],[Wheat]]) -> 203024.8 | T73: =IF(Table5[[#This Row],[KC Wheat]]="","",T72+Table5[[#This Row],[KC Wheat]]) -> 4815.9 | U73: =IF(Table5[[#This Row],[Energies]]="","",U72+Table5[[#This Row],[Energies]]) -> 0 | V73: =IF(N73<>"",IFERROR(V72+N73,""),"") -> 535798.04 | W73: 822257 | X73: =IFERROR(N73/W73,"") -> -0.076940397 | Y73: -2500 | AC73: -49741.49
A74: =TEXT(B74,"mmm") -> Mar | B74: 44271 | C74: -451 | D74: 4361.3 | E74: 13126 | F74: -2284 | G74: -14869.1 | H74: 3124.3 | I74: 0 | J74: =IF(SUM(C74:I74)=0,"",SUM(C74:I74)) -> 3007.5 | K74: -80.25 | L74: -369.15 | M74: =IF(SUM(K74:L74)=0,"",SUM(K74:L74)) -> -449.4 | N74: =IFERROR(J74+M74,"") -> 2558.1 | O74: =IF(Table5[[#This Row],[Beans]]="","",O73+Table5[[#This Row],[Beans]]) -> 267069.6 | P74: =IF(Table5[[#This Row],[Meal]]="","",P73+Table5[[#This Row],[Meal]]) -> 137250.2 | Q74: =IF(Table5[[#This Row],[Oil]]="","",Q73+Table5[[#This Row],[Oil]]) -> 85753.5 | R74: =IF(Table5[[#This Row],[Corn]]="","",R73+Table5[[#This Row],[Corn]]) -> -74132.6 | S74: =IF(Table5[[#This Row],[Wheat]]="","",S73+Table5[[#This Row],[Wheat]]) -> 188155.7 | T74: =IF(Table5[[#This Row],[KC Wheat]]="","",T73+Table5[[#This Row],[KC Wheat]]) -> 7940.2 | U74: =IF(Table5[[#This Row],[Energies]]="","",U73+Table5[[#This Row],[Energies]]) -> 0 | V74: =IF(N74<>"",IFERROR(V73+N74,""),"") -> 538356.14 | W74: 833558 | X74: =IFERROR(N74/W74,"") -> 0.0030688926 | AC74: -68845.64
A75: =TEXT(B75,"mmm") -> Mar | B75: 44272 | C75: 10179.4 | D75: 1280 | E75: 7735.6 | F75: -2755.2 | G75: 2990.4 | H75: -3415.9 | I75: 0 | J75: =IF(SUM(C75:I75)=0,"",SUM(C75:I75)) -> 16014.3 | K75: -35.25 | L75: -162.15 | M75: =IF(SUM(K75:L75)=0,"",SUM(K75:L75)) -> -197.4 | N75: =IFERROR(J75+M75,"") -> 15816.9 | O75: =IF(Table5[[#This Row],[Beans]]="","",O74+Table5[[#This Row],[Beans]]) -> 277249 | P75: =IF(Table5[[#This Row],[Meal]]="","",P74+Table5[[#This Row],[Meal]]) -> 138530.2 | Q75: =IF(Table5[[#This Row],[Oil]]="","",Q74+Table5[[#This Row],[Oil]]) -> 93489.1 | R75: =IF(Table5[[#This Row],[Corn]]="","",R74+Table5[[#This Row],[Corn]]) -> -76887.8 | S75: =IF(Table5[[#This Row],[Wheat]]="","",S74+Table5[[#This Row],[Wheat]]) -> 191146.1 | T75: =IF(Table5[[#This Row],[KC Wheat]]="","",T74+Table5[[#This Row],[KC Wheat]]) -> 4524.3 | U75: =IF(Table5[[#This Row],[Energies]]="","",U74+Table5[[#This Row],[Energies]]) -> 0 | V75: =IF(N75<>"",IFERROR(V74+N75,""),"") -> 554173.04 | W75: 794659 | X75: =IFERROR(N75/W75,"") -> 0.019904009 | AC75: -35834.29
A76: =TEXT(B76,"mmm") -> Mar | B76: 44273 | C76: 26824 | D76: -7423.6 | E76: 10392.7 | F76: 19339 | G76: 22259.5 | H76: 9419.2 | I76: 0 | J76: =IF(SUM(C76:I76)=0,"",SUM(C76:I76)) -> 80810.8 | K76: -171.95 | L76: -790.97 | M76: =IF(SUM(K76:L76)=0,"",SUM(K76:L76)) -> -962.92 | N76: =IFERROR(J76+M76,"") -> 79847.88 | O76: =IF(Table5[[#This Row],[Beans]]="","",O75+Table5[[#This Row],[Beans]]) -> 304073 | P76: =IF(Table5[[#This Row],[Meal]]="","",P75+Table5[[#This Row],[Meal]]) -> 131106.6 | Q76: =IF(Table5[[#This Row],[Oil]]="","",Q75+Table5[[#This Row],[Oil]]) -> 103881.8 | R76: =IF(Table5[[#This Row],[Corn]]="","",R75+Table5[[#This Row],[Corn]]) -> -57548.8 | S76: =IF(Table5[[#This Row],[Wheat]]="","",S75+Table5[[#This Row],[Wheat]]) -> 213405.6 | T76: =IF(Table5[[#This Row],[KC Wheat]]="","",T75+Table5[[#This Row],[KC Wheat]]) -> 13943.5 | U76: =IF(Table5[[#This Row],[Energies]]="","",U75+Table5[[#This Row],[Energies]]) -> 0 | V76: =IF(N76<>"",IFERROR(V75+N76,""),"") -> 634020.92 | W76: 797027 | X76: =IFERROR(N76/W76,"") -> 0.10018215 | AC76: 50669.54
A77: =TEXT(B77,"mmm") -> Mar | B77: 44274 | C77: 4411.3 | D77: 16908 | E77: -11256 | F77: -15521.7 | G77: 17908 | H77: -4504.2 | I77: 0 | J77: =IF(SUM(C77:I77)=0,"",SUM(C77:I77)) -> 7945.4 | K77: -110.3 | L77: -507.38 | M77: =IF(SUM(K77:L77)=0,"",SUM(K77:L77)) -> -617.68 | N77: =IFERROR(J77+M77,"") -> 7327.72 | O77: =IF(Table5[[#This Row],[Beans]]="","",O76+Table5[[#This Row],[Beans]]) -> 308484.3 | P77: =IF(Table5[[#This Row],[Meal]]="","",P76+Table5[[#This Row],[Meal]]) -> 148014.6 | Q77: =IF(Table5[[#This Row],[Oil]]="","",Q76+Table5[[#This Row],[Oil]]) -> 92625.8 | R77: =IF(Table5[[#This Row],[Corn]]="","",R76+Table5[[#This Row],[Corn]]) -> -73070.5 | S77: =IF(Table5[[#This Row],[Wheat]]="","",S76+Table5[[#This Row],[Wheat]]) -> 231313.6 | T77: =IF(Table5[[#This Row],[KC Wheat]]="","",T76+Table5[[#This Row],[KC Wheat]]) -> 9439.3 | U77: =IF(Table5[[#This Row],[Energies]]="","",U76+Table5[[#This Row],[Energies]]) -> 0 | V77: =IF(N77<>"",IFERROR(V76+N77,""),"") -> 641348.64 | W77: 819015 | X77: =IFERROR(N77/W77,"") -> 0.0089469912 | AC77: 51157.36
A78: =TEXT(B78,"mmm") -> Mar | B78: 44277 | C78: -13582.6 | D78: -5667.2 | E78: -9258.7 | F78: -3976.4 | G78: 19248.3 | H78: 3366.6 | I78: 0 | J78: =IF(SUM(C78:I78)=0,"",SUM(C78:I78)) -> -9870 | K78: -58 | L78: -266.8 | M78: =IF(SUM(K78:L78)=0,"",SUM(K78:L78)) -> -324.8 | N78: =IFERROR(J78+M78,"") -> -10194.8 | O78: =IF(Table5[[#This Row],[Beans]]="","",O77+Table5[[#This Row],[Beans]]) -> 294901.7 | P78: =IF(Table5[[#This Row],[Meal]]="","",P77+Table5[[#This Row],[Meal]]) -> 142347.4 | Q78: =IF(Table5[[#This Row],[Oil]]="","",Q77+Table5[[#This Row],[Oil]]) -> 83367.1 | R78: =IF(Table5[[#This Row],[Corn]]="","",R77+Table5[[#This Row],[Corn]]) -> -77046.9 | S78: =IF(Table5[[#This Row],[Wheat]]="","",S77+Table5[[#This Row],[Wheat]]) -> 250561.9 | T78: =IF(Table5[[#This Row],[KC Wheat]]="","",T77+Table5[[#This Row],[KC Wheat]]) -> 12805.9 | U78: =IF(Table5[[#This Row],[Energies]]="","",U77+Table5[[#This Row],[Energies]]) -> 0 | V78: =IF(N78<>"",IFERROR(V77+N78,""),"") -> 631153.84 | W78: 837748 | X78: =IFERROR(N78/W78,"") -> -0.012169292 | AC78: -42871.44
A79: =TEXT(B79,"mmm") -> Mar | B79: 44278 | C79: -19765.2 | D79: 14154.9 | E79: 3517 | F79: 11605 | G79: 7495.9 | H79: 2115.9 | I79: 0 | J79: =IF(SUM(C79:I79)=0,"",SUM(C79:I79)) -> 19123.5 | K79: -154.75 | L79: -711.85 | M79: =IF(SUM(K79:L79)=0,"",SUM(K79:L79)) -> -866.6 | N79: =IFERROR(J79+M79,"") -> 18256.9 | O79: =IF(Table5[[#This Row],[Beans]]="","",O78+Table5[[#This Row],[Beans]]) -> 275136.5 | P79: =IF(Table5[[#This Row],[Meal]]="","",P78+Table5[[#This Row],[Meal]]) -> 156502.3 | Q79: =IF(Table5[[#This Row],[Oil]]="","",Q78+Table5[[#This Row],[Oil]]) -> 86884.1 | R79: =IF(Table5[[#This Row],[Corn]]="","",R78+Table5[[#This Row],[Corn]]) -> -65441.9 | S79: =IF(Table5[[#This Row],[Wheat]]="","",S78+Table5[[#This Row],[Wheat]]) -> 258057.8 | T79: =IF(Table5[[#This Row],[KC Wheat]]="","",T78+Table5[[#This Row],[KC Wheat]]) -> 14921.8 | U79: =IF(Table5[[#This Row],[Energies]]="","",U78+Table5[[#This Row],[Energies]]) -> 0 | V79: =IF(N79<>"",IFERROR(V78+N79,""),"") -> 649410.74 | W79: 716953 | X79: =IFERROR(N79/W79,"") -> 0.02546457 | AC79: 72278.71
A80: =TEXT(B80,"mmm") -> Mar | B80: 44279 | C80: 1453.7 | D80: 23649.3 | E80: -13223.5 | F80: -19558.4 | G80: 17540.2 | H80: -6665.3 | I80: 0 | J80: =IF(SUM(C80:I80)=0,"",SUM(C80:I80)) -> 3196 | K80: -163.4 | L80: -751.64 | M80: =IF(SUM(K80:L80)=0,"",SUM(K80:L80)) -> -915.04 | N80: =IFERROR(J80+M80,"") -> 2280.96 | O80: =IF(Table5[[#This Row],[Beans]]="","",O79+Table5[[#This Row],[Beans]]) -> 276590.2 | P80: =IF(Table5[[#This Row],[Meal]]="","",P79+Table5[[#This Row],[Meal]]) -> 180151.6 | Q80: =IF(Table5[[#This Row],[Oil]]="","",Q79+Table5[[#This Row],[Oil]]) -> 73660.6 | R80: =IF(Table5[[#This Row],[Corn]]="","",R79+Table5[[#This Row],[Corn]]) -> -85000.3 | S80: =IF(Table5[[#This Row],[Wheat]]="","",S79+Table5[[#This Row],[Wheat]]) -> 275598 | T80: =IF(Table5[[#This Row],[KC Wheat]]="","",T79+Table5[[#This Row],[KC Wheat]]) -> 8256.5 | U80: =IF(Table5[[#This Row],[Energies]]="","",U79+Table5[[#This Row],[Energies]]) -> 0 | V80: =IF(N80<>"",IFERROR(V79+N80,""),"") -> 651691.7 | W80: 759232 | X80: =IFERROR(N80/W80,"") -> 0.0030042991 | AC80: 67068.42
A81: =TEXT(B81,"mmm") -> Mar | B81: 44280 | C81: 26876.4 | D81: 32650.7 | E81: 29163.4 | F81: -29240.6 | G81: 14641.3 | H81: -1922.2 | I81: 0 | J81: =IF(SUM(C81:I81)=0,"",SUM(C81:I81)) -> 72169 | K81: -224.45 | L81: -1032.47 | M81: =IF(SUM(K81:L81)=0,"",SUM(K81:L81)) -> -1256.92 | N81: =IFERROR(J81+M81,"") -> 70912.08 | O81: =IF(Table5[[#This Row],[Beans]]="","",O80+Table5[[#This Row],[Beans]]) -> 303466.6 | P81: =IF(Table5[[#This Row],[Meal]]="","",P80+Table5[[#This Row],[Meal]]) -> 212802.3 | Q81: =IF(Table5[[#This Row],[Oil]]="","",Q80+Table5[[#This Row],[Oil]]) -> 102824 | R81: =IF(Table5[[#This Row],[Corn]]="","",R80+Table5[[#This Row],[Corn]]) -> -114240.9 | S81: =IF(Table5[[#This Row],[Wheat]]="","",S80+Table5[[#This Row],[Wheat]]) -> 290239.3 | T81: =IF(Table5[[#This Row],[KC Wheat]]="","",T80+Table5[[#This Row],[KC Wheat]]) -> 6334.3 | U81: =IF(Table5[[#This Row],[Energies]]="","",U80+Table5[[#This Row],[Energies]]) -> 0 | V81: =IF(N81<>"",IFERROR(V80+N81,""),"") -> 722603.78 | W81: 865625 | X81: =IFERROR(N81/W81,"") -> 0.081920092 | AC81: 121124.75
A82: =TEXT(B82,"mmm") -> Mar | B82: 44281 | C82: -6618.7 | D82: -1665.3 | E82: -24185.8 | F82: -4669.4 | G82: -10993.6 | H82: 511.8 | I82: 0 | J82: =IF(SUM(C82:I82)=0,"",SUM(C82:I82)) -> -47621 | K82: -428.85 | L82: -1454.34 | M82: =IF(SUM(K82:L82)=0,"",SUM(K82:L82)) -> -1883.19 | N82: =IFERROR(J82+M82,"") -> -49504.19 | O82: =IF(Table5[[#This Row],[Beans]]="","",O81+Table5[[#This Row],[Beans]]) -> 296847.9 | P82: =IF(Table5[[#This Row],[Meal]]="","",P81+Table5[[#This Row],[Meal]]) -> 211137 | Q82: =IF(Table5[[#This Row],[Oil]]="","",Q81+Table5[[#This Row],[Oil]]) -> 78638.2 | R82: =IF(Table5[[#This Row],[Corn]]="","",R81+Table5[[#This Row],[Corn]]) -> -118910.3 | S82: =IF(Table5[[#This Row],[Wheat]]="","",S81+Table5[[#This Row],[Wheat]]) -> 279245.7 | T82: =IF(Table5[[#This Row],[KC Wheat]]="","",T81+Table5[[#This Row],[KC Wheat]]) -> 6846.1 | U82: =IF(Table5[[#This Row],[Energies]]="","",U81+Table5[[#This Row],[Energies]]) -> 0 | V82: =IF(N82<>"",IFERROR(V81+N82,""),"") -> 673099.59 | W82: 889994 | X82: =IFERROR(N82/W82,"") -> -0.05562306 | AC82: 105280.56
A83: =TEXT(B83,"mmm") -> Mar | B83: 44284 | C83: 21550 | D83: -25498.5 | E83: -12789.1 | F83: 1365.5 | G83: -1465.1 | H83: 3363.3 | I83: 0 | J83: =IF(SUM(C83:I83)=0,"",SUM(C83:I83)) -> -13473.9 | K83: -66.75 | L83: -307.05 | M83: =IF(SUM(K83:L83)=0,"",SUM(K83:L83)) -> -373.8 | N83: =IFERROR(J83+M83,"") -> -13847.7 | O83: =IF(Table5[[#This Row],[Beans]]="","",O82+Table5[[#This Row],[Beans]]) -> 318397.9 | P83: =IF(Table5[[#This Row],[Meal]]="","",P82+Table5[[#This Row],[Meal]]) -> 185638.5 | Q83: =IF(Table5[[#This Row],[Oil]]="","",Q82+Table5[[#This Row],[Oil]]) -> 65849.1 | R83: =IF(Table5[[#This Row],[Corn]]="","",R82+Table5[[#This Row],[Corn]]) -> -117544.8 | S83: =IF(Table5[[#This Row],[Wheat]]="","",S82+Table5[[#This Row],[Wheat]]) -> 277780.6 | T83: =IF(Table5[[#This Row],[KC Wheat]]="","",T82+Table5[[#This Row],[KC Wheat]]) -> 10209.4 | U83: =IF(Table5[[#This Row],[Energies]]="","",U82+Table5[[#This Row],[Energies]]) -> 0 | V83: =IF(N83<>"",IFERROR(V82+N83,""),"") -> 659251.89 | W83: 834315 | X83: =IFERROR(N83/W83,"") -> -0.016597688 | AC83: 85259.26
A84: =TEXT(B84,"mmm") -> Mar | B84: 44285 | C84: -19518.2 | D84: -5067.3 | E84: -14146.1 | F84: 21310.7 | G84: 28377 | H84: 20063.6 | I84: 0 | J84: =IF(SUM(C84:I84)=0,"",SUM(C84:I84)) -> 31019.7 | K84: -153.7 | L84: -707.02 | M84: =IF(SUM(K84:L84)=0,"",SUM(K84:L84)) -> -860.72 | N84: =IFERROR(J84+M84,"") -> 30158.98 | O84: =IF(Table5[[#This Row],[Beans]]="","",O83+Table5[[#This Row],[Beans]]) -> 298879.7 | P84: =IF(Table5[[#This Row],[Meal]]="","",P83+Table5[[#This Row],[Meal]]) -> 180571.2 | Q84: =IF(Table5[[#This Row],[Oil]]="","",Q83+Table5[[#This Row],[Oil]]) -> 51703 | R84: =IF(Table5[[#This Row],[Corn]]="","",R83+Table5[[#This Row],[Corn]]) -> -96234.1 | S84: =IF(Table5[[#This Row],[Wheat]]="","",S83+Table5[[#This Row],[Wheat]]) -> 306157.6 | T84: =IF(Table5[[#This Row],[KC Wheat]]="","",T83+Table5[[#This Row],[KC Wheat]]) -> 30273 | U84: =IF(Table5[[#This Row],[Energies]]="","",U83+Table5[[#This Row],[Energies]]) -> 0 | V84: =IF(N84<>"",IFERROR(V83+N84,""),"") -> 689410.87 | W84: 774487 | X84: =IFERROR(N84/W84,"") -> 0.038940589 | AC84: 142616.29
A85: =TEXT(B85,"mmm") -> Mar | B85: 44286 | C85: =57452.2+4212.5 -> 61664.7 | D85: =80397.3-50 -> 80347.3 | E85: -9444.5 | F85: =-60728.1-29300 -> -90028.1 | G85: 14330.1 | H85: 18845.5 | I85: 0 | J85: =IF(SUM(C85:I85)=0,"",SUM(C85:I85)) -> 75715 | K85: -165.3 | L85: -760.38 | M85: =IF(SUM(K85:L85)=0,"",SUM(K85:L85)) -> -925.68 | N85: =IFERROR(J85+M85,"") -> 74789.32 | O85: =IF(Table5[[#This Row],[Beans]]="","",O84+Table5[[#This Row],[Beans]]) -> 360544.4 | P85: =IF(Table5[[#This Row],[Meal]]="","",P84+Table5[[#This Row],[Meal]]) -> 260918.5 | Q85: =IF(Table5[[#This Row],[Oil]]="","",Q84+Table5[[#This Row],[Oil]]) -> 42258.5 | R85: =IF(Table5[[#This Row],[Corn]]="","",R84+Table5[[#This Row],[Corn]]) -> -186262.2 | S85: =IF(Table5[[#This Row],[Wheat]]="","",S84+Table5[[#This Row],[Wheat]]) -> 320487.7 | T85: =IF(Table5[[#This Row],[KC Wheat]]="","",T84+Table5[[#This Row],[KC Wheat]]) -> 49118.5 | U85: =IF(Table5[[#This Row],[Energies]]="","",U84+Table5[[#This Row],[Energies]]) -> 0 | V85: =IF(N85<>"",IFERROR(V84+N85,""),"") -> 764200.19 | W85: 654873 | X85: =IFERROR(N85/W85,"") -> 0.11420431 | Y85: -8970.84 | AC85: 63473.11
A86: =TEXT(B86,"mmm") -> Apr | B86: 44287 | C86: =61675.1+250 -> 61925.1 | D86: =-3139+1330 -> -1809 | E86: -16313.7 | F86: -13003.1 | G86: 5873.5 | H86: -8328.3 | I86: 0 | J86: =IF(SUM(C86:I86)=0,"",SUM(C86:I86)) -> 28344.5 | K86: -276.4 | L86: -1271.44 | M86: =IF(SUM(K86:L86)=0,"",SUM(K86:L86)) -> -1547.84 | N86: =IFERROR(J86+M86,"") -> 26796.66 | O86: =IF(Table5[[#This Row],[Beans]]="","",O85+Table5[[#This Row],[Beans]]) -> 422469.5 | P86: =IF(Table5[[#This Row],[Meal]]="","",P85+Table5[[#This Row],[Meal]]) -> 259109.5 | Q86: =IF(Table5[[#This Row],[Oil]]="","",Q85+Table5[[#This Row],[Oil]]) -> 25944.8 | R86: =IF(Table5[[#This Row],[Corn]]="","",R85+Table5[[#This Row],[Corn]]) -> -199265.3 | S86: =IF(Table5[[#This Row],[Wheat]]="","",S85+Table5[[#This Row],[Wheat]]) -> 326361.2 | T86: =IF(Table5[[#This Row],[KC Wheat]]="","",T85+Table5[[#This Row],[KC Wheat]]) -> 40790.2 | U86: =IF(Table5[[#This Row],[Energies]]="","",U85+Table5[[#This Row],[Energies]]) -> 0 | V86: =IF(N86<>"",IFERROR(V85+N86,""),"") -> 790996.85 | W86: 794205 | X86: =IFERROR(N86/W86,"") -> 0.033740231 | Y86: -18685.27 | AC86: 193580.04
A87: =TEXT(B87,"mmm") -> Apr | B87: 44291 | C87: -16311.5 | D87: -34245 | E87: 11458.9 | F87: 26291.3 | G87: -1298.2 | H87: -14252.2 | I87: 0 | J87: =IF(SUM(C87:I87)=0,"",SUM(C87:I87)) -> -28356.7 | K87: -183.05 | L87: -842.03 | M87: =IF(SUM(K87:L87)=0,"",SUM(K87:L87)) -> -1025.08 | N87: =IFERROR(J87+M87,"") -> -29381.78 | O87: =IF(Table5[[#This Row],[Beans]]="","",O86+Table5[[#This Row],[Beans]]) -> 406158 | P87: =IF(Table5[[#This Row],[Meal]]="","",P86+Table5[[#This Row],[Meal]]) -> 224864.5 | Q87: =IF(Table5[[#This Row],[Oil]]="","",Q86+Table5[[#This Row],[Oil]]) -> 37403.7 | R87: =IF(Table5[[#This Row],[Corn]]="","",R86+Table5[[#This Row],[Corn]]) -> -172974 | S87: =IF(Table5[[#This Row],[Wheat]]="","",S86+Table5[[#This Row],[Wheat]]) -> 325063 | T87: =IF(Table5[[#This Row],[KC Wheat]]="","",T86+Table5[[#This Row],[KC Wheat]]) -> 26538 | U87: =IF(Table5[[#This Row],[Energies]]="","",U86+Table5[[#This Row],[Energies]]) -> 0 | V87: =IF(N87<>"",IFERROR(V86+N87,""),"") -> 761615.07 | W87: 841885 | X87: =IFERROR(N87/W87,"") -> -0.034899992 | Y87: 15529.5 | AC87: 150553.43
A88: =TEXT(B88,"mmm") -> Apr | B88: 44292 | C88: 60722.3 | D88: =-18308.3+1680 -> -16628.3 | E88: -8960.2 | F88: 11066.3 | G88: 26441 | H88: -5403.3 | I88: 0 | J88: =IF(SUM(C88:I88)=0,"",SUM(C88:I88)) -> 67237.8 | K88: -107.55 | L88: -494.61 | M88: =IF(SUM(K88:L88)=0,"",SUM(K88:L88)) -> -602.16 | N88: =IFERROR(J88+M88,"") -> 66635.64 | O88: =IF(Table5[[#This Row],[Beans]]="","",O87+Table5[[#This Row],[Beans]]) -> 466880.3 | P88: =IF(Table5[[#This Row],[Meal]]="","",P87+Table5[[#This Row],[Meal]]) -> 208236.2 | Q88: =IF(Table5[[#This Row],[Oil]]="","",Q87+Table5[[#This Row],[Oil]]) -> 28443.5 | R88: =IF(Table5[[#This Row],[Corn]]="","",R87+Table5[[#This Row],[Corn]]) -> -161907.7 | S88: =IF(Table5[[#This Row],[Wheat]]="","",S87+Table5[[#This Row],[Wheat]]) -> 351504 | T88: =IF(Table5[[#This Row],[KC Wheat]]="","",T87+Table5[[#This Row],[KC Wheat]]) -> 21134.7 | U88: =IF(Table5[[#This Row],[Energies]]="","",U87+Table5[[#This Row],[Energies]]) -> 0 | V88: =IF(N88<>"",IFERROR(V87+N88,""),"") -> 828250.71 | W88: 866884 | X88: =IFERROR(N88/W88,"") -> 0.076868001 | AA88: -100000 | AC88: 115289.05
A89: =TEXT(B89,"mmm") -> Apr | B89: 44293 | C89: 41301.6 | D89: -3233.7 | E89: 19542.6 | F89: -689.7 | G89: 18142.6 | H89: 11173.2 | I89: 0 | J89: =IF(SUM(C89:I89)=0,"",SUM(C89:I89)) -> 86236.6 | K89: -173.9 | L89: -797.75 | M89: =IF(SUM(K89:L89)=0,"",SUM(K89:L89)) -> -971.65 | N89: =IFERROR(J89+M89,"") -> 85264.95 | O89: =IF(Table5[[#This Row],[Beans]]="","",O88+Table5[[#This Row],[Beans]]) -> 508181.9 | P89: =IF(Table5[[#This Row],[Meal]]="","",P88+Table5[[#This Row],[Meal]]) -> 205002.5 | Q89: =IF(Table5[[#This Row],[Oil]]="","",Q88+Table5[[#This Row],[Oil]]) -> 47986.1 | R89: =IF(Table5[[#This Row],[Corn]]="","",R88+Table5[[#This Row],[Corn]]) -> -162597.4 | S89: =IF(Table5[[#This Row],[Wheat]]="","",S88+Table5[[#This Row],[Wheat]]) -> 369646.6 | T89: =IF(Table5[[#This Row],[KC Wheat]]="","",T88+Table5[[#This Row],[KC Wheat]]) -> 32307.9 | U89: =IF(Table5[[#This Row],[Energies]]="","",U88+Table5[[#This Row],[Energies]]) -> 0 | V89: =IF(N89<>"",IFERROR(V88+N89,""),"") -> 913515.66 | W89: 729087 | X89: =IFERROR(N89/W89,"") -> 0.11694757 | AC89: 214837.15
A90: =TEXT(B90,"mmm") -> Apr | B90: 44294 | C90: -1050.3 | D90: -339.2 | E90: 6546.3 | F90: -26841 | G90: 3122.4 | H90: 8070.1 | I90: 0 | J90: =IF(SUM(C90:I90)=0,"",SUM(C90:I90)) -> -10491.7 | K90: -138.45 | L90: -636.87 | M90: =IF(SUM(K90:L90)=0,"",SUM(K90:L90)) -> -775.32 | N90: =IFERROR(J90+M90,"") -> -11267.02 | O90: =IF(Table5[[#This Row],[Beans]]="","",O89+Table5[[#This Row],[Beans]]) -> 507131.6 | P90: =IF(Table5[[#This Row],[Meal]]="","",P89+Table5[[#This Row],[Meal]]) -> 204663.3 | Q90: =IF(Table5[[#This Row],[Oil]]="","",Q89+Table5[[#This Row],[Oil]]) -> 54532.4 | R90: =IF(Table5[[#This Row],[Corn]]="","",R89+Table5[[#This Row],[Corn]]) -> -189438.4 | S90: =IF(Table5[[#This Row],[Wheat]]="","",S89+Table5[[#This Row],[Wheat]]) -> 372769 | T90: =IF(Table5[[#This Row],[KC Wheat]]="","",T89+Table5[[#This Row],[KC Wheat]]) -> 40378 | U90: =IF(Table5[[#This Row],[Energies]]="","",U89+Table5[[#This Row],[Energies]]) -> 0 | V90: =IF(N90<>"",IFERROR(V89+N90,""),"") -> 902248.64 | W90: 683296 | X90: =IFERROR(N90/W90,"") -> -0.016489223 | AC90: 221480.33
A91: =TEXT(B91,"mmm") -> Apr | B91: 44295 | C91: -24676.2 | D91: -11575 | E91: -5136.9 | F91: 29424.4 | G91: 3429.7 | H91: -6234 | I91: 0 | J91: =IF(SUM(C91:I91)=0,"",SUM(C91:I91)) -> -14768 | K91: -153.15 | L91: -704.49 | M91: =IF(SUM(K91:L91)=0,"",SUM(K91:L91)) -> -857.64 | N91: =IFERROR(J91+M91,"") -> -15625.64 | O91: =IF(Table5[[#This Row],[Beans]]="","",O90+Table5[[#This Row],[Beans]]) -> 482455.4 | P91: =IF(Table5[[#This Row],[Meal]]="","",P90+Table5[[#This Row],[Meal]]) -> 193088.3 | Q91: =IF(Table5[[#This Row],[Oil]]="","",Q90+Table5[[#This Row],[Oil]]) -> 49395.5 | R91: =IF(Table5[[#This Row],[Corn]]="","",R90+Table5[[#This Row],[Corn]]) -> -160014 | S91: =IF(Table5[[#This Row],[Wheat]]="","",S90+Table5[[#This Row],[Wheat]]) -> 376198.7 | T91: =IF(Table5[[#This Row],[KC Wheat]]="","",T90+Table5[[#This Row],[KC Wheat]]) -> 34144 | U91: =IF(Table5[[#This Row],[Energies]]="","",U90+Table5[[#This Row],[Energies]]) -> 0 | V91: =IF(N91<>"",IFERROR(V90+N91,""),"") -> 886623 | W91: 819689 | X91: =IFERROR(N91/W91,"") -> -0.019062888 | Y91: =-5125 -> -5125 | AC91: 196049.19
A92: =TEXT(B92,"mmm") -> Apr | B92: 44298 | C92: -19378.7 | D92: -5118.8 | E92: 21571 | F92: 19102.7 | G92: 23354.3 | H92: 6105.3 | I92: 0 | J92: =IF(SUM(C92:I92)=0,"",SUM(C92:I92)) -> 45635.8 | K92: -187.75 | L92: -860.65 | M92: =IF(SUM(K92:L92)=0,"",SUM(K92:L92)) -> -1048.4 | N92: =IFERROR(J92+M92,"") -> 44587.4 | O92: =IF(Table5[[#This Row],[Beans]]="","",O91+Table5[[#This Row],[Beans]]) -> 463076.7 | P92: =IF(Table5[[#This Row],[Meal]]="","",P91+Table5[[#This Row],[Meal]]) -> 187969.5 | Q92: =IF(Table5[[#This Row],[Oil]]="","",Q91+Table5[[#This Row],[Oil]]) -> 70966.5 | R92: =IF(Table5[[#This Row],[Corn]]="","",R91+Table5[[#This Row],[Corn]]) -> -140911.3 | S92: =IF(Table5[[#This Row],[Wheat]]="","",S91+Table5[[#This Row],[Wheat]]) -> 399553 | T92: =IF(Table5[[#This Row],[KC Wheat]]="","",T91+Table5[[#This Row],[KC Wheat]]) -> 40249.3 | U92: =IF(Table5[[#This Row],[Energies]]="","",U91+Table5[[#This Row],[Energies]]) -> 0 | V92: =IF(N92<>"",IFERROR(V91+N92,""),"") -> 931210.4 | W92: 705839 | X92: =IFERROR(N92/W92,"") -> 0.063169363 | Y92: -1575.85 | AC92: 251604.04
A93: =TEXT(B93,"mmm") -> Apr | B93: 44299 | C93: -4697.4 | D93: 9458.2 | E93: 17459.2 | F93: -6919.5 | G93: -3690.9 | H93: 9040.4 | I93: 0 | J93: =IF(SUM(C93:I93)=0,"",SUM(C93:I93)) -> 20650 | K93: -121.75 | L93: -559.36 | M93: =IF(SUM(K93:L93)=0,"",SUM(K93:L93)) -> -681.11 | N93: =IFERROR(J93+M93,"") -> 19968.89 | O93: =IF(Table5[[#This Row],[Beans]]="","",O92+Table5[[#This Row],[Beans]]) -> 458379.3 | P93: =IF(Table5[[#This Row],[Meal]]="","",P92+Table5[[#This Row],[Meal]]) -> 197427.7 | Q93: =IF(Table5[[#This Row],[Oil]]="","",Q92+Table5[[#This Row],[Oil]]) -> 88425.7 | R93: =IF(Table5[[#This Row],[Corn]]="","",R92+Table5[[#This Row],[Corn]]) -> -147830.8 | S93: =IF(Table5[[#This Row],[Wheat]]="","",S92+Table5[[#This Row],[Wheat]]) -> 395862.1 | T93: =IF(Table5[[#This Row],[KC Wheat]]="","",T92+Table5[[#This Row],[KC Wheat]]) -> 49289.7 | U93: =IF(Table5[[#This Row],[Energies]]="","",U92+Table5[[#This Row],[Energies]]) -> 0 | V93: =IF(N93<>"",IFERROR(V92+N93,""),"") -> 951179.29 | W93: 711784 | X93: =IFERROR(N93/W93,"") -> 0.028054705 | AC93: 244007.93
A94: =TEXT(B94,"mmm") -> Apr | B94: 44300 | C94: 11021.8 | D94: -35790.1 | E94: -2412.3 | F94: -19576.8 | G94: -37634.6 | H94: -8754.1 | I94: 0 | J94: =IF(SUM(C94:I94)=0,"",SUM(C94:I94)) -> -93146.1 | K94: -59.6 | L94: -273.2 | M94: =IF(SUM(K94:L94)=0,"",SUM(K94:L94)) -> -332.8 | N94: =IFERROR(J94+M94,"") -> -93478.9 | O94: =IF(Table5[[#This Row],[Beans]]="","",O93+Table5[[#This Row],[Beans]]) -> 469401.1 | P94: =IF(Table5[[#This Row],[Meal]]="","",P93+Table5[[#This Row],[Meal]]) -> 161637.6 | Q94: =IF(Table5[[#This Row],[Oil]]="","",Q93+Table5[[#This Row],[Oil]]) -> 86013.4 | R94: =IF(Table5[[#This Row],[Corn]]="","",R93+Table5[[#This Row],[Corn]]) -> -167407.6 | S94: =IF(Table5[[#This Row],[Wheat]]="","",S93+Table5[[#This Row],[Wheat]]) -> 358227.5 | T94: =IF(Table5[[#This Row],[KC Wheat]]="","",T93+Table5[[#This Row],[KC Wheat]]) -> 40535.6 | U94: =IF(Table5[[#This Row],[Energies]]="","",U93+Table5[[#This Row],[Energies]]) -> 0 | V94: =IF(N94<>"",IFERROR(V93+N94,""),"") -> 857700.39 | W94: 612800 | X94: =IFERROR(N94/W94,"") -> -0.1525439 | AC94: 171561.13
A95: =TEXT(B95,"mmm") -> Apr | B95: 44301 | C95: -22715.9 | D95: 17854.7 | E95: 5059.9 | F95: 550.5 | G95: 660.6 | H95: -374.1 | I95: 0 | J95: =IF(SUM(C95:I95)=0,"",SUM(C95:I95)) -> 1035.7 | K95: -91.95 | L95: -422.28 | M95: =IF(SUM(K95:L95)=0,"",SUM(K95:L95)) -> -514.23 | N95: =IFERROR(J95+M95,"") -> 521.47 | O95: =IF(Table5[[#This Row],[Beans]]="","",O94+Table5[[#This Row],[Beans]]) -> 446685.2 | P95: =IF(Table5[[#This Row],[Meal]]="","",P94+Table5[[#This Row],[Meal]]) -> 179492.3 | Q95: =IF(Table5[[#This Row],[Oil]]="","",Q94+Table5[[#This Row],[Oil]]) -> 91073.3 | R95: =IF(Table5[[#This Row],[Corn]]="","",R94+Table5[[#This Row],[Corn]]) -> -166857.1 | S95: =IF(Table5[[#This Row],[Wheat]]="","",S94+Table5[[#This Row],[Wheat]]) -> 358888.1 | T95: =IF(Table5[[#This Row],[KC Wheat]]="","",T94+Table5[[#This Row],[KC Wheat]]) -> 40161.5 | U95: =IF(Table5[[#This Row],[Energies]]="","",U94+Table5[[#This Row],[Energies]]) -> 0 | V95: =IF(N95<>"",IFERROR(V94+N95,""),"") -> 858221.86 | W95: 643951 | X95: =IFERROR(N95/W95,"") -> 0.00080979764 | AC95: 156412.15
A96: =TEXT(B96,"mmm") -> Apr | B96: 44302 | C96: 27113.2 | D96: -248.4 | E96: -11826 | F96: -1943.2 | G96: -3999.9 | H96: 1944.3 | I96: 0 | J96: =IF(SUM(C96:I96)=0,"",SUM(C96:I96)) -> 11040 | K96: -52.05 | L96: -239.04 | M96: =IF(SUM(K96:L96)=0,"",SUM(K96:L96)) -> -291.09 | N96: =IFERROR(J96+M96,"") -> 10748.91 | O96: =IF(Table5[[#This Row],[Beans]]="","",O95+Table5[[#This Row],[Beans]]) -> 473798.4 | P96: =IF(Table5[[#This Row],[Meal]]="","",P95+Table5[[#This Row],[Meal]]) -> 179243.9 | Q96: =IF(Table5[[#This Row],[Oil]]="","",Q95+Table5[[#This Row],[Oil]]) -> 79247.3 | R96: =IF(Table5[[#This Row],[Corn]]="","",R95+Table5[[#This Row],[Corn]]) -> -168800.3 | S96: =IF(Table5[[#This Row],[Wheat]]="","",S95+Table5[[#This Row],[Wheat]]) -> 354888.2 | T96: =IF(Table5[[#This Row],[KC Wheat]]="","",T95+Table5[[#This Row],[KC Wheat]]) -> 42105.8 | U96: =IF(Table5[[#This Row],[Energies]]="","",U95+Table5[[#This Row],[Energies]]) -> 0 | V96: =IF(N96<>"",IFERROR(V95+N96,""),"") -> 868970.77 | W96: 777307 | X96: =IFERROR(N96/W96,"") -> 0.013828397 | Y96: -5826 | AB96: -18000 | AC96: 166884.81
A97: =TEXT(B97,"mmm") -> Apr | B97: 44305 | C97: 16723.6 | D97: -33093.6 | E97: 6694 | F97: -20029.4 | G97: -6391.4 | H97: 6377.6 | I97: 0 | J97: =IF(SUM(C97:I97)=0,"",SUM(C97:I97)) -> -29719.2 | K97: -160.3 | L97: -735.34 | M97: =IF(SUM(K97:L97)=0,"",SUM(K97:L97)) -> -895.64 | N97: =IFERROR(J97+M97,"") -> -30614.84 | O97: =IF(Table5[[#This Row],[Beans]]="","",O96+Table5[[#This Row],[Beans]]) -> 490522 | P97: =IF(Table5[[#This Row],[Meal]]="","",P96+Table5[[#This Row],[Meal]]) -> 146150.3 | Q97: =IF(Table5[[#This Row],[Oil]]="","",Q96+Table5[[#This Row],[Oil]]) -> 85941.3 | R97: =IF(Table5[[#This Row],[Corn]]="","",R96+Table5[[#This Row],[Corn]]) -> -188829.7 | S97: =IF(Table5[[#This Row],[Wheat]]="","",S96+Table5[[#This Row],[Wheat]]) -> 348496.8 | T97: =IF(Table5[[#This Row],[KC Wheat]]="","",T96+Table5[[#This Row],[KC Wheat]]) -> 48483.4 | U97: =IF(Table5[[#This Row],[Energies]]="","",U96+Table5[[#This Row],[Energies]]) -> 0 | V97: =IF(N97<>"",IFERROR(V96+N97,""),"") -> 838355.93 | W97: 701899 | X97: =IFERROR(N97/W97,"") -> -0.043617159 | AC97: 133470.42
A98: =TEXT(B98,"mmm") -> Apr | B98: 44306 | C98: 82411.5 | D98: 15967.9 | E98: -48296.3 | F98: 9365.4 | G98: 13452 | H98: -26624.4 | I98: 0 | J98: =IF(SUM(C98:I98)=0,"",SUM(C98:I98)) -> 46276.1 | K98: -176.6 | L98: -806.54 | M98: =IF(SUM(K98:L98)=0,"",SUM(K98:L98)) -> -983.14 | N98: =IFERROR(J98+M98,"") -> 45292.96 | O98: =IF(Table5[[#This Row],[Beans]]="","",O97+Table5[[#This Row],[Beans]]) -> 572933.5 | P98: =IF(Table5[[#This Row],[Meal]]="","",P97+Table5[[#This Row],[Meal]]) -> 162118.2 | Q98: =IF(Table5[[#This Row],[Oil]]="","",Q97+Table5[[#This Row],[Oil]]) -> 37645 | R98: =IF(Table5[[#This Row],[Corn]]="","",R97+Table5[[#This Row],[Corn]]) -> -179464.3 | S98: =IF(Table5[[#This Row],[Wheat]]="","",S97+Table5[[#This Row],[Wheat]]) -> 361948.8 | T98: =IF(Table5[[#This Row],[KC Wheat]]="","",T97+Table5[[#This Row],[KC Wheat]]) -> 21859 | U98: =IF(Table5[[#This Row],[Energies]]="","",U97+Table5[[#This Row],[Energies]]) -> 0 | V98: =IF(N98<>"",IFERROR(V97+N98,""),"") -> 883648.89 | W98: 527130 | X98: =IFERROR(N98/W98,"") -> 0.0859237 | AC98: 199139.28
A99: =TEXT(B99,"mmm") -> Apr | B99: 44307 | C99: 8053.8 | D99: 17295.7 | E99: 4173.5 | F99: -15857.1 | G99: 15554.1 | H99: -5906.6 | I99: 0 | J99: =IF(SUM(C99:I99)=0,"",SUM(C99:I99)) -> 23313.4 | K99: -175.05 | L99: -803.46 | M99: =IF(SUM(K99:L99)=0,"",SUM(K99:L99)) -> -978.51 | N99: =IFERROR(J99+M99,"") -> 22334.89 | O99: =IF(Table5[[#This Row],[Beans]]="","",O98+Table5[[#This Row],[Beans]]) -> 580987.3 | P99: =IF(Table5[[#This Row],[Meal]]="","",P98+Table5[[#This Row],[Meal]]) -> 179413.9 | Q99: =IF(Table5[[#This Row],[Oil]]="","",Q98+Table5[[#This Row],[Oil]]) -> 41818.5 | R99: =IF(Table5[[#This Row],[Corn]]="","",R98+Table5[[#This Row],[Corn]]) -> -195321.4 | S99: =IF(Table5[[#This Row],[Wheat]]="","",S98+Table5[[#This Row],[Wheat]]) -> 377502.9 | T99: =IF(Table5[[#This Row],[KC Wheat]]="","",T98+Table5[[#This Row],[KC Wheat]]) -> 15952.4 | U99: =IF(Table5[[#This Row],[Energies]]="","",U98+Table5[[#This Row],[Energies]]) -> 0 | V99: =IF(N99<>"",IFERROR(V98+N99,""),"") -> 905983.78 | W99: 491897 | X99: =IFERROR(N99/W99,"") -> 0.045405624 | AC99: 209755.02
A100: =TEXT(B100,"mmm") -> Apr | B100: 44308 | C100: 72392.7 | D100: 61775.4 | E100: -24857.9 | F100: -18803.3 | G100: 52819.3 | H100: -21388.4 | I100: 0 | J100: =IF(SUM(C100:I100)=0,"",SUM(C100:I100)) -> 121937.8 | K100: -176.3 | L100: -808.25 | M100: =IF(SUM(K100:L100)=0,"",SUM(K100:L100)) -> -984.55 | N100: =IFERROR(J100+M100,"") -> 120953.25 | O100: =IF(Table5[[#This Row],[Beans]]="","",O99+Table5[[#This Row],[Beans]]) -> 653380 | P100: =IF(Table5[[#This Row],[Meal]]="","",P99+Table5[[#This Row],[Meal]]) -> 241189.3 | Q100: =IF(Table5[[#This Row],[Oil]]="","",Q99+Table5[[#This Row],[Oil]]) -> 16960.6 | R100: =IF(Table5[[#This Row],[Corn]]="","",R99+Table5[[#This Row],[Corn]]) -> -214124.7 | S100: =IF(Table5[[#This Row],[Wheat]]="","",S99+Table5[[#This Row],[Wheat]]) -> 430322.2 | T100: =IF(Table5[[#This Row],[KC Wheat]]="","",T99+Table5[[#This Row],[KC Wheat]]) -> -5436 | U100: =IF(Table5[[#This Row],[Energies]]="","",U99+Table5[[#This Row],[Energies]]) -> 0 | V100: =IF(N100<>"",IFERROR(V99+N100,""),"") -> 1026937 | W100: 538206 | X100: =IFERROR(N100/W100,"") -> 0.22473412 | AC100: 395089.22
...

Sheet Yr 2026
A2: YTD PnL
A7: Trading PnL | B7: =J48 -> 519997.9
A8: Commissions | B8: =K48 -> -3060.63
A9: Exchange Fees | B9: =L48 -> -26182.65
A10: Expenses | B10: =Y48 -> -32464.34
A11: Interest | B11: =Z48 -> 470.85
A12: NET PNL | B12: =B7+(B8+B9+B10+B11) -> 458761.13
A14: Average Margin | B14: =W48 -> 674379.3
A15: RoM | B15: =B12/B14 -> 0.68027166
A16: Std Dev | B16: =X48 -> 0.13006777
A17: Sharpe | B17: =(B15-0.045)/B16 -> 4.884159
B48: TOTALS | C48: =SUM(C50:C297) -> 480151.7 | D48: =SUM(D50:D297) -> 82832.7 | E48: =SUM(E50:E297) -> 0 | F48: =SUM(F50:F297) -> -28301.8 | G48: =SUM(G50:G297) -> -14684.7 | H48: =SUM(H50:H297) -> 0 | I48: =SUM(I50:I297) -> 0 | J48: =SUM(J50:J297) -> 519997.9 | ... N48: =SUM(N50:N297) -> 490754.62 | W48: =AVERAGE(W50:W295) -> 674379.3 | X48: =_xlfn.STDEV.P(X50:X295) -> 0.13006777 | Y48: =SUM(Y50:Y295) -> -32464.34 | Z48: =SUM(Z50:Z295) -> 470.85 | AA48: =SUM(AA50:AA295) -> -262055.72 | AB48: =SUM(AB50:AB295) -> 0
A49: Month | B49: Date | C49: Beans | D49: Meal | E49: Oil | F49: Corn | G49: Wheat | H49: KC Wheat | I49: Brent | J49: Total PnL | K49: Commissions | L49: Clr/brk fees | M49: Total Fees | N49: Net PnL | O49: Cum Beans | P49: Cum Meal | Q49: Cum Oil | R49: Cum Corn | S49: Cum Wheat | T49: Cum KC | U49: Cum Brent | V49: Cum PnL | W49: Margin | X49: RoM | Y49: Expenses | Z49: Int | AA49: Distributions | AB49: Bonuses | AC49: Net Liq
A50: =TEXT(B50,"mmm") -> Jan | B50: ='Daily PnL Log'!B1281 -> 46024 | C50: ='Daily PnL Log'!C1281 -> 22511 | D50: ='Daily PnL Log'!D1281 -> -2103.6 | E50: ='Daily PnL Log'!E1281 -> 0 | F50: ='Daily PnL Log'!F1281 -> 6684.9 | G50: ='Daily PnL Log'!G1281 -> -5901.8 | H50: ='Daily PnL Log'!H1281 -> 0 | I50: ='Daily PnL Log'!I1281 -> 0 | ... N50: ='Daily PnL Log'!N1281 -> 20804.18 | O50: =C50 -> 22511 | P50: =D50 -> -2103.6 | Q50: =E50 -> 0 | R50: =F50 -> 6684.9 | S50: =G50 -> -5901.8 | T50: =H50 -> 0 | U50: =I50 -> 0 | V50: =SUM(O50:T50) -> 21190.5 | W50: =IF('Daily PnL Log'!W1281<>"",'Daily PnL Log'!W1281,"") -> 494970 | X50: =IF('Daily PnL Log'!X1281<>"",'Daily PnL Log'!X1281,"") -> 0.042031194 | Y50: =IF('Daily PnL Log'!Y1281<>"",'Daily PnL Log'!Y1281,"") | Z50: =IF('Daily PnL Log'!Z1281<>"",'Daily PnL Log'!Z1281,"") | AA50: =IF('Daily PnL Log'!AA1281<>"",'Daily PnL Log'!AA1281,"") | AB50: =IF('Daily PnL Log'!AB1281<>"",'Daily PnL Log'!AB1281,"") | AC50: =IF('Daily PnL Log'!AC1281<>"",'Daily PnL Log'!AC1281,"") -> 289426.9
A51: =TEXT(B51,"mmm") -> Jan | B51: ='Daily PnL Log'!B1282 -> 46027 | C51: ='Daily PnL Log'!C1282 -> 30643.6 | D51: ='Daily PnL Log'!D1282 -> -5802.9 | E51: ='Daily PnL Log'!E1282 -> 0 | F51: ='Daily PnL Log'!F1282 -> -2260.1 | G51: ='Daily PnL Log'!G1282 -> -19309.3 | H51: ='Daily PnL Log'!H1282 -> 0 | I51: ='Daily PnL Log'!I1282 -> 0 | ... N51: ='Daily PnL Log'!N1282 -> 2730.87 | O51: =IF(C51<>"",O50+C51,"") -> 53154.6 | P51: =IF(D51<>"",P50+D51,"") -> -7906.5 | Q51: =IF(E51<>"",Q50+E51,"") -> 0 | R51: =IF(F51<>"",R50+F51,"") -> 4424.8 | S51: =IF(G51<>"",S50+G51,"") -> -25211.1 | T51: =IF(H51<>"",T50+H51,"") -> 0 | U51: =IF(I51<>"",U50+I51,"") -> 0 | V51: =IF(J51<>"",V50+J51,"") -> 24461.8 | W51: =IF('Daily PnL Log'!W1282<>"",'Daily PnL Log'!W1282,"") -> 465552 | X51: =IF('Daily PnL Log'!X1282<>"",'Daily PnL Log'!X1282,"") -> 0.0058658753 | Y51: =IF('Daily PnL Log'!Y1282<>"",'Daily PnL Log'!Y1282,"") -> -5908.56 | Z51: =IF('Daily PnL Log'!Z1282<>"",'Daily PnL Log'!Z1282,"") | AA51: =IF('Daily PnL Log'!AA1282<>"",'Daily PnL Log'!AA1282,"") -> -262055.72 | AB51: =IF('Daily PnL Log'!AB1282<>"",'Daily PnL Log'!AB1282,"") | AC51: =IF('Daily PnL Log'!AC1282<>"",'Daily PnL Log'!AC1282,"") -> 53948.25
A52: =TEXT(B52,"mmm") -> Jan | B52: ='Daily PnL Log'!B1283 -> 46028 | C52: ='Daily PnL Log'!C1283 -> 12639.6 | D52: ='Daily PnL Log'!D1283 -> 5190.6 | E52: ='Daily PnL Log'!E1283 -> 0 | F52: ='Daily PnL Log'!F1283 -> 3803.4 | G52: ='Daily PnL Log'!G1283 -> -6787.1 | H52: ='Daily PnL Log'!H1283 -> 0 | I52: ='Daily PnL Log'!I1283 -> 0 | ... N52: ='Daily PnL Log'!N1283 -> 14244.29 | O52: =IF(C52<>"",O51+C52,"") -> 65794.2 | P52: =IF(D52<>"",P51+D52,"") -> -2715.9 | Q52: =IF(E52<>"",Q51+E52,"") -> 0 | R52: =IF(F52<>"",R51+F52,"") -> 8228.2 | S52: =IF(G52<>"",S51+G52,"") -> -31998.2 | T52: =IF(H52<>"",T51+H52,"") -> 0 | U52: =IF(I52<>"",U51+I52,"") -> 0 | V52: =IF(J52<>"",V51+J52,"") -> 39308.3 | W52: =IF('Daily PnL Log'!W1283<>"",'Daily PnL Log'!W1283,"") -> 504295 | X52: =IF('Daily PnL Log'!X1283<>"",'Daily PnL Log'!X1283,"") -> 0.028245947 | Y52: =IF('Daily PnL Log'!Y1283<>"",'Daily PnL Log'!Y1283,"") | Z52: =IF('Daily PnL Log'!Z1283<>"",'Daily PnL Log'!Z1283,"") | AA52: =IF('Daily PnL Log'!AA1283<>"",'Daily PnL Log'!AA1283,"") | AB52: =IF('Daily PnL Log'!AB1283<>"",'Daily PnL Log'!AB1283,"") | AC52: =IF('Daily PnL Log'!AC1283<>"",'Daily PnL Log'!AC1283,"") -> 74301.04
A53: =TEXT(B53,"mmm") -> Jan | B53: ='Daily PnL Log'!B1284 -> 46029 | C53: ='Daily PnL Log'!C1284 -> 25296.3 | D53: ='Daily PnL Log'!D1284 -> 11912.6 | E53: ='Daily PnL Log'!E1284 -> 0 | F53: ='Daily PnL Log'!F1284 -> 4230.8 | G53: ='Daily PnL Log'!G1284 -> -3114.6 | H53: ='Daily PnL Log'!H1284 -> 0 | I53: ='Daily PnL Log'!I1284 -> 0 | ... N53: ='Daily PnL Log'!N1284 -> 37871.4 | O53: =IF(C53<>"",O52+C53,"") -> 91090.5 | P53: =IF(D53<>"",P52+D53,"") -> 9196.7 | Q53: =IF(E53<>"",Q52+E53,"") -> 0 | R53: =IF(F53<>"",R52+F53,"") -> 12459 | S53: =IF(G53<>"",S52+G53,"") -> -35112.8 | T53: =IF(H53<>"",T52+H53,"") -> 0 | U53: =IF(I53<>"",U52+I53,"") -> 0 | V53: =IF(J53<>"",V52+J53,"") -> 77633.4 | W53: =IF('Daily PnL Log'!W1284<>"",'Daily PnL Log'!W1284,"") -> 518237 | X53: =IF('Daily PnL Log'!X1284<>"",'Daily PnL Log'!X1284,"") -> 0.073077376 | Y53: =IF('Daily PnL Log'!Y1284<>"",'Daily PnL Log'!Y1284,"") | Z53: =IF('Daily PnL Log'!Z1284<>"",'Daily PnL Log'!Z1284,"") | AA53: =IF('Daily PnL Log'!AA1284<>"",'Daily PnL Log'!AA1284,"") | AB53: =IF('Daily PnL Log'!AB1284<>"",'Daily PnL Log'!AB1284,"") | AC53: =IF('Daily PnL Log'!AC1284<>"",'Daily PnL Log'!AC1284,"") -> 94209.84
A54: =TEXT(B54,"mmm") -> Jan | B54: ='Daily PnL Log'!B1285 -> 46030 | C54: ='Daily PnL Log'!C1285 -> -9742.6 | D54: ='Daily PnL Log'!D1285 -> -7136 | E54: ='Daily PnL Log'!E1285 -> 0 | F54: ='Daily PnL Log'!F1285 -> -5227.2 | G54: ='Daily PnL Log'!G1285 -> 8633.6 | H54: ='Daily PnL Log'!H1285 -> 0 | I54: ='Daily PnL Log'!I1285 -> 0 | ... N54: ='Daily PnL Log'!N1285 -> -14427.64 | O54: =IF(C54<>"",O53+C54,"") -> 81347.9 | P54: =IF(D54<>"",P53+D54,"") -> 2060.7 | Q54: =IF(E54<>"",Q53+E54,"") -> 0 | R54: =IF(F54<>"",R53+F54,"") -> 7231.8 | S54: =IF(G54<>"",S53+G54,"") -> -26479.2 | T54: =IF(H54<>"",T53+H54,"") -> 0 | U54: =IF(I54<>"",U53+I54,"") -> 0 | V54: =IF(J54<>"",V53+J54,"") -> 64161.2 | W54: =IF('Daily PnL Log'!W1285<>"",'Daily PnL Log'!W1285,"") -> 589490 | X54: =IF('Daily PnL Log'!X1285<>"",'Daily PnL Log'!X1285,"") -> -0.024474783 | Y54: =IF('Daily PnL Log'!Y1285<>"",'Daily PnL Log'!Y1285,"") | Z54: =IF('Daily PnL Log'!Z1285<>"",'Daily PnL Log'!Z1285,"") | AA54: =IF('Daily PnL Log'!AA1285<>"",'Daily PnL Log'!AA1285,"") | AB54: =IF('Daily PnL Log'!AB1285<>"",'Daily PnL Log'!AB1285,"") | AC54: =IF('Daily PnL Log'!AC1285<>"",'Daily PnL Log'!AC1285,"") -> 108435.65
A55: =TEXT(B55,"mmm") -> Jan | B55: ='Daily PnL Log'!B1286 -> 46031 | C55: ='Daily PnL Log'!C1286 -> 1612.9 | D55: ='Daily PnL Log'!D1286 -> 4726.4 | E55: ='Daily PnL Log'!E1286 -> 0 | F55: ='Daily PnL Log'!F1286 -> -5952.5 | G55: ='Daily PnL Log'!G1286 -> -2494.8 | H55: ='Daily PnL Log'!H1286 -> 0 | I55: ='Daily PnL Log'!I1286 -> 0 | ... N55: ='Daily PnL Log'!N1286 -> -3526.17 | O55: =IF(C55<>"",O54+C55,"") -> 82960.8 | P55: =IF(D55<>"",P54+D55,"") -> 6787.1 | Q55: =IF(E55<>"",Q54+E55,"") -> 0 | R55: =IF(F55<>"",R54+F55,"") -> 1279.3 | S55: =IF(G55<>"",S54+G55,"") -> -28974 | T55: =IF(H55<>"",T54+H55,"") -> 0 | U55: =IF(I55<>"",U54+I55,"") -> 0 | V55: =IF(J55<>"",V54+J55,"") -> 62053.2 | W55: =IF('Daily PnL Log'!W1286<>"",'Daily PnL Log'!W1286,"") -> 562260 | X55: =IF('Daily PnL Log'!X1286<>"",'Daily PnL Log'!X1286,"") -> -0.0062714225 | Y55: =IF('Daily PnL Log'!Y1286<>"",'Daily PnL Log'!Y1286,"") | Z55: =IF('Daily PnL Log'!Z1286<>"",'Daily PnL Log'!Z1286,"") | AA55: =IF('Daily PnL Log'!AA1286<>"",'Daily PnL Log'!AA1286,"") | AB55: =IF('Daily PnL Log'!AB1286<>"",'Daily PnL Log'!AB1286,"") | AC55: =IF('Daily PnL Log'!AC1286<>"",'Daily PnL Log'!AC1286,"") -> 74684.98
A56: =TEXT(B56,"mmm") -> Jan | B56: ='Daily PnL Log'!B1287 -> 46034 | C56: ='Daily PnL Log'!C1287 -> -32546.3 | D56: ='Daily PnL Log'!D1287 -> 4261.2 | E56: ='Daily PnL Log'!E1287 -> 0 | F56: ='Daily PnL Log'!F1287 -> -113515.1 | G56: ='Daily PnL Log'!G1287 -> 14792.5 | H56: ='Daily PnL Log'!H1287 -> 0 | I56: ='Daily PnL Log'!I1287 -> 0 | ... N56: ='Daily PnL Log'!N1287 -> -129507.38 | O56: =IF(C56<>"",O55+C56,"") -> 50414.5 | P56: =IF(D56<>"",P55+D56,"") -> 11048.3 | Q56: =IF(E56<>"",Q55+E56,"") -> 0 | R56: =IF(F56<>"",R55+F56,"") -> -112235.8 | S56: =IF(G56<>"",S55+G56,"") -> -14181.5 | T56: =IF(H56<>"",T55+H56,"") -> 0 | U56: =IF(I56<>"",U55+I56,"") -> 0 | V56: =IF(J56<>"",V55+J56,"") -> -64954.5 | W56: =IF('Daily PnL Log'!W1287<>"",'Daily PnL Log'!W1287,"") -> 485862 | X56: =IF('Daily PnL Log'!X1287<>"",'Daily PnL Log'!X1287,"") -> -0.26655178 | Y56: =IF('Daily PnL Log'!Y1287<>"",'Daily PnL Log'!Y1287,"") -> -329.5 | Z56: =IF('Daily PnL Log'!Z1287<>"",'Daily PnL Log'!Z1287,"") | AA56: =IF('Daily PnL Log'!AA1287<>"",'Daily PnL Log'!AA1287,"") | AB56: =IF('Daily PnL Log'!AB1287<>"",'Daily PnL Log'!AB1287,"") | AC56: =IF('Daily PnL Log'!AC1287<>"",'Daily PnL Log'!AC1287,"") -> -19479.7
A57: =TEXT(B57,"mmm") -> Jan | B57: ='Daily PnL Log'!B1288 -> 46035 | C57: ='Daily PnL Log'!C1288 -> 568.3 | D57: ='Daily PnL Log'!D1288 -> 42148.2 | E57: ='Daily PnL Log'!E1288 -> 0 | F57: ='Daily PnL Log'!F1288 -> 2901.5 | G57: ='Daily PnL Log'!G1288 -> 7433.8 | H57: ='Daily PnL Log'!H1288 -> 0 | I57: ='Daily PnL Log'!I1288 -> 0 | ... N57: ='Daily PnL Log'!N1288 -> 51931.55 | O57: =IF(C57<>"",O56+C57,"") -> 50982.8 | P57: =IF(D57<>"",P56+D57,"") -> 53196.5 | Q57: =IF(E57<>"",Q56+E57,"") -> 0 | R57: =IF(F57<>"",R56+F57,"") -> -109334.3 | S57: =IF(G57<>"",S56+G57,"") -> -6747.7 | T57: =IF(H57<>"",T56+H57,"") -> 0 | U57: =IF(I57<>"",U56+I57,"") -> 0 | V57: =IF(J57<>"",V56+J57,"") -> -11902.7 | W57: =IF('Daily PnL Log'!W1288<>"",'Daily PnL Log'!W1288,"") -> 504410 | X57: =IF('Daily PnL Log'!X1288<>"",'Daily PnL Log'!X1288,"") -> 0.10295504 | Y57: =IF('Daily PnL Log'!Y1288<>"",'Daily PnL Log'!Y1288,"") | Z57: =IF('Daily PnL Log'!Z1288<>"",'Daily PnL Log'!Z1288,"") | AA57: =IF('Daily PnL Log'!AA1288<>"",'Daily PnL Log'!AA1288,"") | AB57: =IF('Daily PnL Log'!AB1288<>"",'Daily PnL Log'!AB1288,"") | AC57: =IF('Daily PnL Log'!AC1288<>"",'Daily PnL Log'!AC1288,"") -> 21252.55
A58: =TEXT(B58,"mmm") -> Jan | B58: ='Daily PnL Log'!B1289 -> 46036 | C58: ='Daily PnL Log'!C1289 -> -11063.6 | D58: ='Daily PnL Log'!D1289 -> -5351.8 | E58: ='Daily PnL Log'!E1289 -> 0 | F58: ='Daily PnL Log'!F1289 -> 1321.6 | G58: ='Daily PnL Log'!G1289 -> -2076.5 | H58: ='Daily PnL Log'!H1289 -> 0 | I58: ='Daily PnL Log'!I1289 -> 0 | ... N58: ='Daily PnL Log'!N1289 -> -17790.54 | O58: =IF(C58<>"",O57+C58,"") -> 39919.2 | P58: =IF(D58<>"",P57+D58,"") -> 47844.7 | Q58: =IF(E58<>"",Q57+E58,"") -> 0 | R58: =IF(F58<>"",R57+F58,"") -> -108012.7 | S58: =IF(G58<>"",S57+G58,"") -> -8824.2 | T58: =IF(H58<>"",T57+H58,"") -> 0 | U58: =IF(I58<>"",U57+I58,"") -> 0 | V58: =IF(J58<>"",V57+J58,"") -> -29073 | W58: =IF('Daily PnL Log'!W1289<>"",'Daily PnL Log'!W1289,"") -> 595475 | X58: =IF('Daily PnL Log'!X1289<>"",'Daily PnL Log'!X1289,"") -> -0.029876216 | Y58: =IF('Daily PnL Log'!Y1289<>"",'Daily PnL Log'!Y1289,"") -> -5276.68 | Z58: =IF('Daily PnL Log'!Z1289<>"",'Daily PnL Log'!Z1289,"") | AA58: =IF('Daily PnL Log'!AA1289<>"",'Daily PnL Log'!AA1289,"") | AB58: =IF('Daily PnL Log'!AB1289<>"",'Daily PnL Log'!AB1289,"") | AC58: =IF('Daily PnL Log'!AC1289<>"",'Daily PnL Log'!AC1289,"") -> 9553.18
A59: =TEXT(B59,"mmm") -> Jan | B59: ='Daily PnL Log'!B1290 -> 46037 | C59: ='Daily PnL Log'!C1290 -> -6370.6 | D59: ='Daily PnL Log'!D1290 -> 2741.7 | E59: ='Daily PnL Log'!E1290 -> 0 | F59: ='Daily PnL Log'!F1290 -> -13099.9 | G59: ='Daily PnL Log'!G1290 -> 700.4 | H59: ='Daily PnL Log'!H1290 -> 0 | I59: ='Daily PnL Log'!I1290 -> 0 | ... N59: ='Daily PnL Log'!N1290 -> -16656.1 | O59: =IF(C59<>"",O58+C59,"") -> 33548.6 | P59: =IF(D59<>"",P58+D59,"") -> 50586.4 | Q59: =IF(E59<>"",Q58+E59,"") -> 0 | R59: =IF(F59<>"",R58+F59,"") -> -121112.6 | S59: =IF(G59<>"",S58+G59,"") -> -8123.8 | T59: =IF(H59<>"",T58+H59,"") -> 0 | U59: =IF(I59<>"",U58+I59,"") -> 0 | V59: =IF(J59<>"",V58+J59,"") -> -45101.4 | W59: =IF('Daily PnL Log'!W1290<>"",'Daily PnL Log'!W1290,"") -> 649048 | X59: =IF('Daily PnL Log'!X1290<>"",'Daily PnL Log'!X1290,"") -> -0.025662355 | Y59: =IF('Daily PnL Log'!Y1290<>"",'Daily PnL Log'!Y1290,"") | Z59: =IF('Daily PnL Log'!Z1290<>"",'Daily PnL Log'!Z1290,"") | AA59: =IF('Daily PnL Log'!AA1290<>"",'Daily PnL Log'!AA1290,"") | AB59: =IF('Daily PnL Log'!AB1290<>"",'Daily PnL Log'!AB1290,"") | AC59: =IF('Daily PnL Log'!AC1290<>"",'Daily PnL Log'!AC1290,"") -> -15774.52
A60: =TEXT(B60,"mmm") -> Jan | B60: ='Daily PnL Log'!B1291 -> 46038 | C60: ='Daily PnL Log'!C1291 -> 25688.7 | D60: ='Daily PnL Log'!D1291 -> -12081.3 | E60: ='Daily PnL Log'!E1291 -> 0 | F60: ='Daily PnL Log'!F1291 -> -2583.3 | G60: ='Daily PnL Log'!G1291 -> -5760.5 | H60: ='Daily PnL Log'!H1291 -> 0 | I60: ='Daily PnL Log'!I1291 -> 0 | ... N60: ='Daily PnL Log'!N1291 -> 4841.31 | O60: =IF(C60<>"",O59+C60,"") -> 59237.3 | P60: =IF(D60<>"",P59+D60,"") -> 38505.1 | Q60: =IF(E60<>"",Q59+E60,"") -> 0 | R60: =IF(F60<>"",R59+F60,"") -> -123695.9 | S60: =IF(G60<>"",S59+G60,"") -> -13884.3 | T60: =IF(H60<>"",T59+H60,"") -> 0 | U60: =IF(I60<>"",U59+I60,"") -> 0 | V60: =IF(J60<>"",V59+J60,"") -> -39837.8 | W60: =IF('Daily PnL Log'!W1291<>"",'Daily PnL Log'!W1291,"") -> 726725 | X60: =IF('Daily PnL Log'!X1291<>"",'Daily PnL Log'!X1291,"") -> 0.0066618184 | Y60: =IF('Daily PnL Log'!Y1291<>"",'Daily PnL Log'!Y1291,"") | Z60: =IF('Daily PnL Log'!Z1291<>"",'Daily PnL Log'!Z1291,"") | AA60: =IF('Daily PnL Log'!AA1291<>"",'Daily PnL Log'!AA1291,"") | AB60: =IF('Daily PnL Log'!AB1291<>"",'Daily PnL Log'!AB1291,"") | AC60: =IF('Daily PnL Log'!AC1291<>"",'Daily PnL Log'!AC1291,"") -> -29986.81
A61: =TEXT(B61,"mmm") -> Jan | B61: ='Daily PnL Log'!B1292 -> 46042 | C61: ='Daily PnL Log'!C1292 -> -10510.6 | D61: ='Daily PnL Log'!D1292 -> -3232.4 | E61: ='Daily PnL Log'!E1292 -> 0 | F61: ='Daily PnL Log'!F1292 -> -25436.1 | G61: ='Daily PnL Log'!G1292 -> -1976.9 | H61: ='Daily PnL Log'!H1292 -> 0 | I61: ='Daily PnL Log'!I1292 -> 0 | ... N61: ='Daily PnL Log'!N1292 -> -41499.1 | O61: =IF(C61<>"",O60+C61,"") -> 48726.7 | P61: =IF(D61<>"",P60+D61,"") -> 35272.7 | Q61: =IF(E61<>"",Q60+E61,"") -> 0 | R61: =IF(F61<>"",R60+F61,"") -> -149132 | S61: =IF(G61<>"",S60+G61,"") -> -15861.2 | T61: =IF(H61<>"",T60+H61,"") -> 0 | U61: =IF(I61<>"",U60+I61,"") -> 0 | V61: =IF(J61<>"",V60+J61,"") -> -80993.8 | W61: =IF('Daily PnL Log'!W1292<>"",'Daily PnL Log'!W1292,"") -> 686096 | X61: =IF('Daily PnL Log'!X1292<>"",'Daily PnL Log'!X1292,"") -> -0.06048585 | Y61: =IF('Daily PnL Log'!Y1292<>"",'Daily PnL Log'!Y1292,"") | Z61: =IF('Daily PnL Log'!Z1292<>"",'Daily PnL Log'!Z1292,"") | AA61: =IF('Daily PnL Log'!AA1292<>"",'Daily PnL Log'!AA1292,"") | AB61: =IF('Daily PnL Log'!AB1292<>"",'Daily PnL Log'!AB1292,"") | AC61: =IF('Daily PnL Log'!AC1292<>"",'Daily PnL Log'!AC1292,"") -> -52157.41
A62: =TEXT(B62,"mmm") -> Jan | B62: ='Daily PnL Log'!B1293 -> 46043 | C62: ='Daily PnL Log'!C1293 -> 28757.5 | D62: ='Daily PnL Log'!D1293 -> -22309.5 | E62: ='Daily PnL Log'!E1293 -> 0 | F62: ='Daily PnL Log'!F1293 -> -35551.5 | G62: ='Daily PnL Log'!G1293 -> -4108.5 | H62: ='Daily PnL Log'!H1293 -> 0 | I62: ='Daily PnL Log'!I1293 -> 0 | ... N62: ='Daily PnL Log'!N1293 -> -34293.1 | O62: =IF(C62<>"",O61+C62,"") -> 77484.2 | P62: =IF(D62<>"",P61+D62,"") -> 12963.2 | Q62: =IF(E62<>"",Q61+E62,"") -> 0 | R62: =IF(F62<>"",R61+F62,"") -> -184683.5 | S62: =IF(G62<>"",S61+G62,"") -> -19969.7 | T62: =IF(H62<>"",T61+H62,"") -> 0 | U62: =IF(I62<>"",U61+I62,"") -> 0 | V62: =IF(J62<>"",V61+J62,"") -> -114205.8 | W62: =IF('Daily PnL Log'!W1293<>"",'Daily PnL Log'!W1293,"") -> 728236 | X62: =IF('Daily PnL Log'!X1293<>"",'Daily PnL Log'!X1293,"") -> -0.047090641 | Y62: =IF('Daily PnL Log'!Y1293<>"",'Daily PnL Log'!Y1293,"") -> -4179.83 | Z62: =IF('Daily PnL Log'!Z1293<>"",'Daily PnL Log'!Z1293,"") | AA62: =IF('Daily PnL Log'!AA1293<>"",'Daily PnL Log'!AA1293,"") | AB62: =IF('Daily PnL Log'!AB1293<>"",'Daily PnL Log'!AB1293,"") | AC62: =IF('Daily PnL Log'!AC1293<>"",'Daily PnL Log'!AC1293,"") -> -81976.01
... A300: =TEXT(B300,"mmm") -> Jan | B300: ='Daily PnL Log'!B1531 -> 0 | C300: ='Daily PnL Log'!C1531 -> 0 | D300: ='Daily PnL Log'!D1531 -> 0 | E300: ='Daily PnL Log'!E1531 -> 0 | F300: ='Daily PnL Log'!F1531 -> 0 | G300: ='Daily PnL Log'!G1531 -> 0 | H300: ='Daily PnL Log'!H1531 -> 0 | I300: ='Daily PnL Log'!I1531 -> 0 | ... N300: ='Daily PnL Log'!N1531 -> 0 | O300: =IF(C300<>"",O299+C300,"") -> 480151.7 | P300: =IF(D300<>"",P299+D300,"") -> 82832.7 | Q300: =IF(E300<>"",Q299+E300,"") -> 0 | R300: =IF(F300<>"",R299+F300,"") -> -28301.8 | S300: =IF(G300<>"",S299+G300,"") -> -14684.7 | T300: =IF(H300<>"",T299+H300,"") -> 0 | U300: =IF(I300<>"",U299+I300,"") -> 0 | V300: =IF(J300<>"",V299+J300,"") -> #VALUE! | W300: =IF('Daily PnL Log'!W1531<>"",'Daily PnL Log'!W1531,"") | X300: =IF('Daily PnL Log'!X1531<>"",'Daily PnL Log'!X1531,"") | Y300: =IF('Daily PnL Log'!Y1531<>"",'Daily PnL Log'!Y1531,"") | Z300: =IF('Daily PnL Log'!Z1531<>"",'Daily PnL Log'!Z1531,"") | AA300: =IF('Daily PnL Log'!AA1531<>"",'Daily PnL Log'!AA1531,"") | AB300: =IF('Daily PnL Log'!AB1531<>"",'Daily PnL Log'!AB1531,"") | AC300: =IF('Daily PnL Log'!AC1531<>"",'Daily PnL Log'!AC1531,"")

Sheet February 2026
A2: Month To Date PnL
A7: Trading PnL | B7: =J48 -> 569444.7
A8: Commissions | B8: =K48 -> -1213.2
A9: Exchange Fees | B9: =L48 -> -10676.39
A10: Expenses | B10: =Y48 -> -11505.39
A11: NET PNL | B11: =B7+(B8+B9+B10) -> 546049.72
A14: Average Margin | B14: =W48 -> 725305.89
A15: RoM | B15: =B11/B14 -> 0.75285438
A16: Std Dev | B16: =X48 -> 0.065707768
A17: Sharpe | B17: =B15/B16 -> 11.457616
B48: TOTALS | C48: =SUM(C50:C73) -> 418270.5 | D48: =SUM(D50:D73) -> 58159.5 | E48: =SUM(E50:E73) -> 0 | F48: =SUM(F50:F73) -> 96934.6 | G48: =SUM(G50:G73) -> -3919.9 | H48: =SUM(H50:H73) -> 0 | I48: =SUM(I50:I73) -> 0 | J48: =SUM(J50:J73) -> 569444.7 | ... N48: =SUM(N50:N73) -> 557555.11 | W48: =AVERAGE(W50:W73) -> 725305.89 | X48: =AVERAGE(X50:X73) -> 0.065707768 | Y48: =SUM(Y50:Y68) -> -11505.39 | Z48: =SUM(Z50:Z68) -> 470.85
A49: Month | B49: Date | C49: Beans | D49: Meal | E49: Oil | F49: Corn | G49: Wheat | H49: KC Wheat | I49: Brent | J49: Total PnL | K49: Commissions | L49: Clr/brk fees | M49: Total Fees | N49: Net PnL | O49: Cum Beans | P49: Cum Meal | Q49: Cum Oil | R49: Cum Corn | S49: Cum Wheat | T49: Cum KC | U49: Cum Brent | V49: Cum PnL | W49: Margin | X49: RoM | Y49: Expenses | Z49: Distributions | AA49: Net Liq
A50: =TEXT(B50,"mmm") -> Feb | B50: ='Daily PnL Log'!B1301 -> 46055 | C50: =IF('Daily PnL Log'!C1301<>"",'Daily PnL Log'!C1301,"") -> 2955.5 | D50: =IF('Daily PnL Log'!D1301<>"",'Daily PnL Log'!D1301,"") -> -11400.6 | E50: =IF('Daily PnL Log'!E1301<>"",'Daily PnL Log'!E1301,"") -> 0 | F50: =IF('Daily PnL Log'!F1301<>"",'Daily PnL Log'!F1301,"") -> -12511.5 | G50: =IF('Daily PnL Log'!G1301<>"",'Daily PnL Log'!G1301,"") -> 5375.9 | H50: =IF('Daily PnL Log'!H1301<>"",'Daily PnL Log'!H1301,"") -> 0 | I50: =IF('Daily PnL Log'!I1301<>"",'Daily PnL Log'!I1301,"") -> 0 | J50: =IF('Daily PnL Log'!J1301<>"",'Daily PnL Log'!J1301,"") -> -15580.7 | ... N50: =IF('Daily PnL Log'!N1301<>"",'Daily PnL Log'!N1301,"") -> -16261.12 | O50: =C50 -> 2955.5 | P50: =D50 -> -11400.6 | Q50: =E50 -> 0 | R50: =F50 -> -12511.5 | S50: =G50 -> 5375.9 | T50: =H50 -> 0 | U50: =I50 -> 0 | V50: =SUM(O50:T50) -> -15580.7 | W50: =IF('Daily PnL Log'!W1301<>"",'Daily PnL Log'!W1301,"") -> 685610 | X50: =IF('Daily PnL Log'!X1301<>"",'Daily PnL Log'!X1301,"") -> -0.02371774 | Y50: =IF('Daily PnL Log'!Y1301<>"",'Daily PnL Log'!Y1301,"") -> -5972.56 | Z50: =IF('Daily PnL Log'!Z1301<>"",'Daily PnL Log'!Z1301,"") | AA50: =IF('Daily PnL Log'!AC1301<>"",'Daily PnL Log'!AC1301,"") -> -49979.49
A51: =TEXT(B51,"mmm") -> Feb | B51: ='Daily PnL Log'!B1302 -> 46056 | C51: =IF('Daily PnL Log'!C1302<>"",'Daily PnL Log'!C1302,"") -> -13337.3 | D51: =IF('Daily PnL Log'!D1302<>"",'Daily PnL Log'!D1302,"") -> -4555.3 | E51: =IF('Daily PnL Log'!E1302<>"",'Daily PnL Log'!E1302,"") -> 0 | F51: =IF('Daily PnL Log'!F1302<>"",'Daily PnL Log'!F1302,"") -> -18517.6 | G51: =IF('Daily PnL Log'!G1302<>"",'Daily PnL Log'!G1302,"") -> -2850.6 | H51: =IF('Daily PnL Log'!H1302<>"",'Daily PnL Log'!H1302,"") -> 0 | I51: =IF('Daily PnL Log'!I1302<>"",'Daily PnL Log'!I1302,"") -> 0 | J51: =IF('Daily PnL Log'!J1302<>"",'Daily PnL Log'!J1302,"") -> -39260.8 | ... N51: =IF('Daily PnL Log'!N1302<>"",'Daily PnL Log'!N1302,"") -> -39917.85 | O51: =IF(C51<>"",O50+C51,"") -> -10381.8 | P51: =IF(D51<>"",P50+D51,"") -> -15955.9 | Q51: =IF(E51<>"",Q50+E51,"") -> 0 | R51: =IF(F51<>"",R50+F51,"") -> -31029.1 | S51: =IF(G51<>"",S50+G51,"") -> 2525.3 | T51: =IF(H51<>"",T50+H51,"") -> 0 | U51: =IF(I51<>"",U50+I51,"") -> 0 | V51: =IF(J51<>"",V50+J51,"") -> -54841.5 | W51: =IF('Daily PnL Log'!W1302<>"",'Daily PnL Log'!W1302,"") -> 731684 | X51: =IF('Daily PnL Log'!X1302<>"",'Daily PnL Log'!X1302,"") -> -0.054556134 | Y51: =IF('Daily PnL Log'!Y1302<>"",'Daily PnL Log'!Y1302,"") | Z51: =IF('Daily PnL Log'!Z1302<>"",'Daily PnL Log'!Z1302,"") | AA51: =IF('Daily PnL Log'!AC1302<>"",'Daily PnL Log'!AC1302,"") -> -98364.04
A52: =TEXT(B52,"mmm") -> Feb | B52: ='Daily PnL Log'!B1303 -> 46057 | C52: =IF('Daily PnL Log'!C1303<>"",'Daily PnL Log'!C1303,"") -> 286746.2 | D52: =IF('Daily PnL Log'!D1303<>"",'Daily PnL Log'!D1303,"") -> 32903.5 | E52: =IF('Daily PnL Log'!E1303<>"",'Daily PnL Log'!E1303,"") -> 0 | F52: =IF('Daily PnL Log'!F1303<>"",'Daily PnL Log'!F1303,"") -> -1708.9 | G52: =IF('Daily PnL Log'!G1303<>"",'Daily PnL Log'!G1303,"") -> 816.8 | H52: =IF('Daily PnL Log'!H1303<>"",'Daily PnL Log'!H1303,"") -> 0 | I52: =IF('Daily PnL Log'!I1303<>"",'Daily PnL Log'!I1303,"") -> 0 | J52: =IF('Daily PnL Log'!J1303<>"",'Daily PnL Log'!J1303,"") -> 318757.6 | ... N52: =IF('Daily PnL Log'!N1303<>"",'Daily PnL Log'!N1303,"") -> 317553.17 | O52: =IF(C52<>"",O51+C52,"") -> 276364.4 | P52: =IF(D52<>"",P51+D52,"") -> 16947.6 | Q52: =IF(E52<>"",Q51+E52,"") -> 0 | R52: =IF(F52<>"",R51+F52,"") -> -32738 | S52: =IF(G52<>"",S51+G52,"") -> 3342.1 | T52: =IF(H52<>"",T51+H52,"") -> 0 | U52: =IF(I52<>"",U51+I52,"") -> 0 | V52: =IF(J52<>"",V51+J52,"") -> 263916.1 | W52: =IF('Daily PnL Log'!W1303<>"",'Daily PnL Log'!W1303,"") -> 735645 | X52: =IF('Daily PnL Log'!X1303<>"",'Daily PnL Log'!X1303,"") -> 0.43166632 | Y52: =IF('Daily PnL Log'!Y1303<>"",'Daily PnL Log'!Y1303,"") | Z52: =IF('Daily PnL Log'!Z1303<>"",'Daily PnL Log'!Z1303,"") | AA52: =IF('Daily PnL Log'!AC1303<>"",'Daily PnL Log'!AC1303,"") -> 237192.78
A53: =TEXT(B53,"mmm") -> Feb | B53: ='Daily PnL Log'!B1304 -> 46058 | C53: =IF('Daily PnL Log'!C1304<>"",'Daily PnL Log'!C1304,"") -> 160731.8 | D53: =IF('Daily PnL Log'!D1304<>"",'Daily PnL Log'!D1304,"") -> 726 | E53: =IF('Daily PnL Log'!E1304<>"",'Daily PnL Log'!E1304,"") -> 0 | F53: =IF('Daily PnL Log'!F1304<>"",'Daily PnL Log'!F1304,"") -> 64611.7 | G53: =IF('Daily PnL Log'!G1304<>"",'Daily PnL Log'!G1304,"") -> 12171.2 | H53: =IF('Daily PnL Log'!H1304<>"",'Daily PnL Log'!H1304,"") -> 0 | I53: =IF('Daily PnL Log'!I1304<>"",'Daily PnL Log'!I1304,"") -> 0 | J53: =IF('Daily PnL Log'!J1304<>"",'Daily PnL Log'!J1304,"") -> 238240.7 | ... N53: =IF('Daily PnL Log'!N1304<>"",'Daily PnL Log'!N1304,"") -> 237006.13 | O53: =IF(C53<>"",O52+C53,"") -> 437096.2 | P53: =IF(D53<>"",P52+D53,"") -> 17673.6 | Q53: =IF(E53<>"",Q52+E53,"") -> 0 | R53: =IF(F53<>"",R52+F53,"") -> 31873.7 | S53: =IF(G53<>"",S52+G53,"") -> 15513.3 | T53: =IF(H53<>"",T52+H53,"") -> 0 | U53: =IF(I53<>"",U52+I53,"") -> 0 | V53: =IF(J53<>"",V52+J53,"") -> 502156.8 | W53: =IF('Daily PnL Log'!W1304<>"",'Daily PnL Log'!W1304,"") -> 700764 | X53: =IF('Daily PnL Log'!X1304<>"",'Daily PnL Log'!X1304,"") -> 0.33821105 | Y53: =IF('Daily PnL Log'!Y1304<>"",'Daily PnL Log'!Y1304,"") | Z53: =IF('Daily PnL Log'!Z1304<>"",'Daily PnL Log'!Z1304,"") | AA53: =IF('Daily PnL Log'!AC1304<>"",'Daily PnL Log'!AC1304,"") -> 451775.71
A54: =TEXT(B54,"mmm") -> Feb | B54: ='Daily PnL Log'!B1305 -> 46059 | C54: =IF('Daily PnL Log'!C1305<>"",'Daily PnL Log'!C1305,"") -> 45321.5 | D54: =IF('Daily PnL Log'!D1305<>"",'Daily PnL Log'!D1305,"") -> -6719.2 | E54: =IF('Daily PnL Log'!E1305<>"",'Daily PnL Log'!E1305,"") -> 0 | F54: =IF('Daily PnL Log'!F1305<>"",'Daily PnL Log'!F1305,"") -> -8770.6 | G54: =IF('Daily PnL Log'!G1305<>"",'Daily PnL Log'!G1305,"") -> -2239.5 | H54: =IF('Daily PnL Log'!H1305<>"",'Daily PnL Log'!H1305,"") -> 0 | I54: =IF('Daily PnL Log'!I1305<>"",'Daily PnL Log'!I1305,"") -> 0 | J54: =IF('Daily PnL Log'!J1305<>"",'Daily PnL Log'!J1305,"") -> 27592.2 | ... N54: =IF('Daily PnL Log'!N1305<>"",'Daily PnL Log'!N1305,"") -> 26384.97 | O54: =IF(C54<>"",O53+C54,"") -> 482417.7 | P54: =IF(D54<>"",P53+D54,"") -> 10954.4 | Q54: =IF(E54<>"",Q53+E54,"") -> 0 | R54: =IF(F54<>"",R53+F54,"") -> 23103.1 | S54: =IF(G54<>"",S53+G54,"") -> 13273.8 | T54: =IF(H54<>"",T53+H54,"") -> 0 | U54: =IF(I54<>"",U53+I54,"") -> 0 | V54: =IF(J54<>"",V53+J54,"") -> 529749 | W54: =IF('Daily PnL Log'!W1305<>"",'Daily PnL Log'!W1305,"") -> 766023 | X54: =IF('Daily PnL Log'!X1305<>"",'Daily PnL Log'!X1305,"") -> 0.034444096 | Y54: =IF('Daily PnL Log'!Y1305<>"",'Daily PnL Log'!Y1305,"") | Z54: =IF('Daily PnL Log'!Z1305<>"",'Daily PnL Log'!Z1305,"") | AA54: =IF('Daily PnL Log'!AC1305<>"",'Daily PnL Log'!AC1305,"") -> 492930.98
A55: =TEXT(B55,"mmm") -> Feb | B55: ='Daily PnL Log'!B1306 -> 46062 | C55: =IF('Daily PnL Log'!C1306<>"",'Daily PnL Log'!C1306,"") -> -84796.9 | D55: =IF('Daily PnL Log'!D1306<>"",'Daily PnL Log'!D1306,"") -> 1191.5 | E55: =IF('Daily PnL Log'!E1306<>"",'Daily PnL Log'!E1306,"") -> 0 | F55: =IF('Daily PnL Log'!F1306<>"",'Daily PnL Log'!F1306,"") -> -33922.3 | G55: =IF('Daily PnL Log'!G1306<>"",'Daily PnL Log'!G1306,"") -> -3896.3 | H55: =IF('Daily PnL Log'!H1306<>"",'Daily PnL Log'!H1306,"") -> 0 | I55: =IF('Daily PnL Log'!I1306<>"",'Daily PnL Log'!I1306,"") -> 0 | J55: =IF('Daily PnL Log'!J1306<>"",'Daily PnL Log'!J1306,"") -> -121424 | ... N55: =IF('Daily PnL Log'!N1306<>"",'Daily PnL Log'!N1306,"") -> -122249.95 | O55: =IF(C55<>"",O54+C55,"") -> 397620.8 | P55: =IF(D55<>"",P54+D55,"") -> 12145.9 | Q55: =IF(E55<>"",Q54+E55,"") -> 0 | R55: =IF(F55<>"",R54+F55,"") -> -10819.2 | S55: =IF(G55<>"",S54+G55,"") -> 9377.5 | T55: =IF(H55<>"",T54+H55,"") -> 0 | U55: =IF(I55<>"",U54+I55,"") -> 0 | V55: =IF(J55<>"",V54+J55,"") -> 408325 | W55: =IF('Daily PnL Log'!W1306<>"",'Daily PnL Log'!W1306,"") -> 650699 | X55: =IF('Daily PnL Log'!X1306<>"",'Daily PnL Log'!X1306,"") -> -0.18787481 | Y55: =IF('Daily PnL Log'!Y1306<>"",'Daily PnL Log'!Y1306,"") -> -283.3 | Z55: =IF('Daily PnL Log'!Z1306<>"",'Daily PnL Log'!Z1306,"") | AA55: =IF('Daily PnL Log'!AC1306<>"",'Daily PnL Log'!AC1306,"") -> 379562.53
A56: =TEXT(B56,"mmm") -> Feb | B56: ='Daily PnL Log'!B1307 -> 46063 | C56: =IF('Daily PnL Log'!C1307<>"",'Daily PnL Log'!C1307,"") -> 28795.8 | D56: =IF('Daily PnL Log'!D1307<>"",'Daily PnL Log'!D1307,"") -> 14573.8 | E56: =IF('Daily PnL Log'!E1307<>"",'Daily PnL Log'!E1307,"") -> 0 | F56: =IF('Daily PnL Log'!F1307<>"",'Daily PnL Log'!F1307,"") -> 9988.6 | G56: =IF('Daily PnL Log'!G1307<>"",'Daily PnL Log'!G1307,"") -> -2821.5 | H56: =IF('Daily PnL Log'!H1307<>"",'Daily PnL Log'!H1307,"") -> 0 | I56: =IF('Daily PnL Log'!I1307<>"",'Daily PnL Log'!I1307,"") -> 0 | J56: =IF('Daily PnL Log'!J1307<>"",'Daily PnL Log'!J1307,"") -> 50536.7 | ... N56: =IF('Daily PnL Log'!N1307<>"",'Daily PnL Log'!N1307,"") -> 49471.5 | O56: =IF(C56<>"",O55+C56,"") -> 426416.6 | P56: =IF(D56<>"",P55+D56,"") -> 26719.7 | Q56: =IF(E56<>"",Q55+E56,"") -> 0 | R56: =IF(F56<>"",R55+F56,"") -> -830.6 | S56: =IF(G56<>"",S55+G56,"") -> 6556 | T56: =IF(H56<>"",T55+H56,"") -> 0 | U56: =IF(I56<>"",U55+I56,"") -> 0 | V56: =IF(J56<>"",V55+J56,"") -> 458861.7 | W56: =IF('Daily PnL Log'!W1307<>"",'Daily PnL Log'!W1307,"") -> 758428 | X56: =IF('Daily PnL Log'!X1307<>"",'Daily PnL Log'!X1307,"") -> 0.065229 | Y56: =IF('Daily PnL Log'!Y1307<>"",'Daily PnL Log'!Y1307,"") -> -5249.53 | Z56: =IF('Daily PnL Log'!Z1307<>"",'Daily PnL Log'!Z1307,"") | AA56: =IF('Daily PnL Log'!AC1307<>"",'Daily PnL Log'!AC1307,"") -> 406663.58
A57: =TEXT(B57,"mmm") -> Feb | B57: ='Daily PnL Log'!B1308 -> 46064 | C57: =IF('Daily PnL Log'!C1308<>"",'Daily PnL Log'!C1308,"") -> 28795.8 | D57: =IF('Daily PnL Log'!D1308<>"",'Daily PnL Log'!D1308,"") -> 14573.8 | E57: =IF('Daily PnL Log'!E1308<>"",'Daily PnL Log'!E1308,"") -> 0 | F57: =IF('Daily PnL Log'!F1308<>"",'Daily PnL Log'!F1308,"") -> 9988.6 | G57: =IF('Daily PnL Log'!G1308<>"",'Daily PnL Log'!G1308,"") -> -2821.5 | H57: =IF('Daily PnL Log'!H1308<>"",'Daily PnL Log'!H1308,"") -> 0 | I57: =IF('Daily PnL Log'!I1308<>"",'Daily PnL Log'!I1308,"") -> 0 | J57: =IF('Daily PnL Log'!J1308<>"",'Daily PnL Log'!J1308,"") -> 50536.7 | ... N57: =IF('Daily PnL Log'!N1308<>"",'Daily PnL Log'!N1308,"") -> 49579.29 | O57: =IF(C57<>"",O56+C57,"") -> 455212.4 | P57: =IF(D57<>"",P56+D57,"") -> 41293.5 | Q57: =IF(E57<>"",Q56+E57,"") -> 0 | R57: =IF(F57<>"",R56+F57,"") -> 9158 | S57: =IF(G57<>"",S56+G57,"") -> 3734.5 | T57: =IF(H57<>"",T56+H57,"") -> 0 | U57: =IF(I57<>"",U56+I57,"") -> 0 | V57: =IF(J57<>"",V56+J57,"") -> 509398.4 | W57: =IF('Daily PnL Log'!W1308<>"",'Daily PnL Log'!W1308,"") -> 789607 | X57: =IF('Daily PnL Log'!X1308<>"",'Daily PnL Log'!X1308,"") -> 0.062789831 | Y57: =IF('Daily PnL Log'!Y1308<>"",'Daily PnL Log'!Y1308,"") | Z57: =IF('Daily PnL Log'!Z1308<>"",'Daily PnL Log'!Z1308,"") | AA57: =IF('Daily PnL Log'!AC1308<>"",'Daily PnL Log'!AC1308,"") -> 460777.42
A58: =TEXT(B58,"mmm") -> Feb | B58: ='Daily PnL Log'!B1309 -> 46065 | C58: =IF('Daily PnL Log'!C1309<>"",'Daily PnL Log'!C1309,"") -> 28370.1 | D58: =IF('Daily PnL Log'!D1309<>"",'Daily PnL Log'!D1309,"") -> 18432.8 | E58: =IF('Daily PnL Log'!E1309<>"",'Daily PnL Log'!E1309,"") -> 0 | F58: =IF('Daily PnL Log'!F1309<>"",'Daily PnL Log'!F1309,"") -> 93295.3 | G58: =IF('Daily PnL Log'!G1309<>"",'Daily PnL Log'!G1309,"") -> 1598.9 | H58: =IF('Daily PnL Log'!H1309<>"",'Daily PnL Log'!H1309,"") -> 0 | I58: =IF('Daily PnL Log'!I1309<>"",'Daily PnL Log'!I1309,"") -> 0 | J58: =IF('Daily PnL Log'!J1309<>"",'Daily PnL Log'!J1309,"") -> 141697.1 | ... N58: =IF('Daily PnL Log'!N1309<>"",'Daily PnL Log'!N1309,"") -> 139807.14 | O58: =IF(C58<>"",O57+C58,"") -> 483582.5 | P58: =IF(D58<>"",P57+D58,"") -> 59726.3 | Q58: =IF(E58<>"",Q57+E58,"") -> 0 | R58: =IF(F58<>"",R57+F58,"") -> 102453.3 | S58: =IF(G58<>"",S57+G58,"") -> 5333.4 | T58: =IF(H58<>"",T57+H58,"") -> 0 | U58: =IF(I58<>"",U57+I58,"") -> 0 | V58: =IF(J58<>"",V57+J58,"") -> 651095.5 | W58: =IF('Daily PnL Log'!W1309<>"",'Daily PnL Log'!W1309,"") -> 590478.71 | X58: =IF('Daily PnL Log'!X1309<>"",'Daily PnL Log'!X1309,"") -> 0.23676915 | Y58: =IF('Daily PnL Log'!Y1309<>"",'Daily PnL Log'!Y1309,"") | Z58: =IF('Daily PnL Log'!Z1309<>"",'Daily PnL Log'!Z1309,"") | AA58: =IF('Daily PnL Log'!AC1309<>"",'Daily PnL Log'!AC1309,"") -> 590478.71
A59: =TEXT(B59,"mmm") -> Feb | B59: ='Daily PnL Log'!B1310 -> 46066 | C59: =IF('Daily PnL Log'!C1310<>"",'Daily PnL Log'!C1310,"") -> -43227.5 | D59: =IF('Daily PnL Log'!D1310<>"",'Daily PnL Log'!D1310,"") -> -2509 | E59: =IF('Daily PnL Log'!E1310<>"",'Daily PnL Log'!E1310,"") -> 0 | F59: =IF('Daily PnL Log'!F1310<>"",'Daily PnL Log'!F1310,"") -> -7390.2 | G59: =IF('Daily PnL Log'!G1310<>"",'Daily PnL Log'!G1310,"") -> 344.9 | H59: =IF('Daily PnL Log'!H1310<>"",'Daily PnL Log'!H1310,"") -> 0 | I59: =IF('Daily PnL Log'!I1310<>"",'Daily PnL Log'!I1310,"") -> 0 | J59: =IF('Daily PnL Log'!J1310<>"",'Daily PnL Log'!J1310,"") -> -52781.8 | ... N59: =IF('Daily PnL Log'!N1310<>"",'Daily PnL Log'!N1310,"") -> -53739.15 | O59: =IF(C59<>"",O58+C59,"") -> 440355 | P59: =IF(D59<>"",P58+D59,"") -> 57217.3 | Q59: =IF(E59<>"",Q58+E59,"") -> 0 | R59: =IF(F59<>"",R58+F59,"") -> 95063.1 | S59: =IF(G59<>"",S58+G59,"") -> 5678.3 | T59: =IF(H59<>"",T58+H59,"") -> 0 | U59: =IF(I59<>"",U58+I59,"") -> 0 | V59: =IF(J59<>"",V58+J59,"") -> 598313.7 | W59: =IF('Daily PnL Log'!W1310<>"",'Daily PnL Log'!W1310,"") -> 750943 | X59: =IF('Daily PnL Log'!X1310<>"",'Daily PnL Log'!X1310,"") -> -0.071562222 | Y59: =IF('Daily PnL Log'!Y1310<>"",'Daily PnL Log'!Y1310,"") | Z59: =IF('Daily PnL Log'!Z1310<>"",'Daily PnL Log'!Z1310,"") -> 470.85 | AA59: =IF('Daily PnL Log'!AC1310<>"",'Daily PnL Log'!AC1310,"") -> 538158.86
A60: =TEXT(B60,"mmm") -> Feb | B60: ='Daily PnL Log'!B1311 -> 46070 | C60: =IF('Daily PnL Log'!C1311<>"",'Daily PnL Log'!C1311,"") -> -36854.7 | D60: =IF('Daily PnL Log'!D1311<>"",'Daily PnL Log'!D1311,"") -> -5993 | E60: =IF('Daily PnL Log'!E1311<>"",'Daily PnL Log'!E1311,"") -> 0 | F60: =IF('Daily PnL Log'!F1311<>"",'Daily PnL Log'!F1311,"") -> 2005.7 | G60: =IF('Daily PnL Log'!G1311<>"",'Daily PnL Log'!G1311,"") -> -21407.8 | H60: =IF('Daily PnL Log'!H1311<>"",'Daily PnL Log'!H1311,"") -> 0 | I60: =IF('Daily PnL Log'!I1311<>"",'Daily PnL Log'!I1311,"") -> 0 | J60: =IF('Daily PnL Log'!J1311<>"",'Daily PnL Log'!J1311,"") -> -62249.8 | ... N60: =IF('Daily PnL Log'!N1311<>"",'Daily PnL Log'!N1311,"") -> -62582.35 | O60: =IF(C60<>"",O59+C60,"") -> 403500.3 | P60: =IF(D60<>"",P59+D60,"") -> 51224.3 | Q60: =IF(E60<>"",Q59+E60,"") -> 0 | R60: =IF(F60<>"",R59+F60,"") -> 97068.8 | S60: =IF(G60<>"",S59+G60,"") -> -15729.5 | T60: =IF(H60<>"",T59+H60,"") -> 0 | U60: =IF(I60<>"",U59+I60,"") -> 0 | V60: =IF(J60<>"",V59+J60,"") -> 536063.9 | W60: =IF('Daily PnL Log'!W1311<>"",'Daily PnL Log'!W1311,"") -> 747490 | X60: =IF('Daily PnL Log'!X1311<>"",'Daily PnL Log'!X1311,"") -> -0.083723327 | Y60: =IF('Daily PnL Log'!Y1311<>"",'Daily PnL Log'!Y1311,"") | Z60: =IF('Daily PnL Log'!Z1311<>"",'Daily PnL Log'!Z1311,"") | AA60: =IF('Daily PnL Log'!AC1311<>"",'Daily PnL Log'!AC1311,"") -> 487326.91
A61: =TEXT(B61,"mmm") -> Feb | B61: ='Daily PnL Log'!B1312 -> 46071 | C61: =IF('Daily PnL Log'!C1312<>"",'Daily PnL Log'!C1312,"") -> 14770.2 | D61: =IF('Daily PnL Log'!D1312<>"",'Daily PnL Log'!D1312,"") -> 6935.2 | E61: =IF('Daily PnL Log'!E1312<>"",'Daily PnL Log'!E1312,"") -> 0 | F61: =IF('Daily PnL Log'!F1312<>"",'Daily PnL Log'!F1312,"") -> -134.2 | G61: =IF('Daily PnL Log'!G1312<>"",'Daily PnL Log'!G1312,"") -> 11809.6 | H61: =IF('Daily PnL Log'!H1312<>"",'Daily PnL Log'!H1312,"") -> 0 | I61: =IF('Daily PnL Log'!I1312<>"",'Daily PnL Log'!I1312,"") -> 0 | J61: =IF('Daily PnL Log'!J1312<>"",'Daily PnL Log'!J1312,"") -> 33380.8 | ... N61: =IF('Daily PnL Log'!N1312<>"",'Daily PnL Log'!N1312,"") -> 32503.33 | O61: =IF(C61<>"",O60+C61,"") -> 418270.5 | P61: =IF(D61<>"",P60+D61,"") -> 58159.5 | Q61: =IF(E61<>"",Q60+E61,"") -> 0 | R61: =IF(F61<>"",R60+F61,"") -> 96934.6 | S61: =IF(G61<>"",S60+G61,"") -> -3919.9 | T61: =IF(H61<>"",T60+H61,"") -> 0 | U61: =IF(I61<>"",U60+I61,"") -> 0 | V61: =IF(J61<>"",V60+J61,"") -> 569444.7 | W61: =IF('Daily PnL Log'!W1312<>"",'Daily PnL Log'!W1312,"") -> 796299 | X61: =IF('Daily PnL Log'!X1312<>"",'Daily PnL Log'!X1312,"") -> 0.040817997 | Y61: =IF('Daily PnL Log'!Y1312<>"",'Daily PnL Log'!Y1312,"") | Z61: =IF('Daily PnL Log'!Z1312<>"",'Daily PnL Log'!Z1312,"") | AA61: =IF('Daily PnL Log'!AC1312<>"",'Daily PnL Log'!AC1312,"") -> 543026.94
A62: =TEXT(B62,"mmm") -> Feb | B62: ='Daily PnL Log'!B1313 -> 46072 | C62: =IF('Daily PnL Log'!C1313<>"",'Daily PnL Log'!C1313,"") | D62: =IF('Daily PnL Log'!D1313<>"",'Daily PnL Log'!D1313,"") | E62: =IF('Daily PnL Log'!E1313<>"",'Daily PnL Log'!E1313,"") | F62: =IF('Daily PnL Log'!F1313<>"",'Daily PnL Log'!F1313,"") | G62: =IF('Daily PnL Log'!G1313<>"",'Daily PnL Log'!G1313,"") | H62: =IF('Daily PnL Log'!H1313<>"",'Daily PnL Log'!H1313,"") | I62: =IF('Daily PnL Log'!I1313<>"",'Daily PnL Log'!I1313,"") | J62: =IF('Daily PnL Log'!J1313<>"",'Daily PnL Log'!J1313,"") | ... N62: =IF('Daily PnL Log'!N1313<>"",'Daily PnL Log'!N1313,"") | O62: =IF(C62<>"",O61+C62,"") | P62: =IF(D62<>"",P61+D62,"") | Q62: =IF(E62<>"",Q61+E62,"") | R62: =IF(F62<>"",R61+F62,"") | S62: =IF(G62<>"",S61+G62,"") | T62: =IF(H62<>"",T61+H62,"") | U62: =IF(I62<>"",U61+I62,"") | V62: =IF(J62<>"",V61+J62,"") | W62: =IF('Daily PnL Log'!W1313<>"",'Daily PnL Log'!W1313,"") | X62: =IF('Daily PnL Log'!X1313<>"",'Daily PnL Log'!X1313,"") | Y62: =IF('Daily PnL Log'!Y1313<>"",'Daily PnL Log'!Y1313,"") | Z62: =IF('Daily PnL Log'!Z1313<>"",'Daily PnL Log'!Z1313,"") | AA62: =IF('Daily PnL Log'!AC1313<>"",'Daily PnL Log'!AC1313,"")
... A68: =TEXT(B68,"mmm") -> Feb | B68: ='Daily PnL Log'!B1319 -> 46080 | C68: =IF('Daily PnL Log'!C1319<>"",'Daily PnL Log'!C1319,"") | D68: =IF('Daily PnL Log'!D1319<>"",'Daily PnL Log'!D1319,"") | E68: =IF('Daily PnL Log'!E1319<>"",'Daily PnL Log'!E1319,"") | F68: =IF('Daily PnL Log'!F1319<>"",'Daily PnL Log'!F1319,"") | G68: =IF('Daily PnL Log'!G1319<>"",'Daily PnL Log'!G1319,"") | H68: =IF('Daily PnL Log'!H1319<>"",'Daily PnL Log'!H1319,"") | I68: =IF('Daily PnL Log'!I1319<>"",'Daily PnL Log'!I1319,"") | J68: =IF('Daily PnL Log'!J1319<>"",'Daily PnL Log'!J1319,"") | ... N68: =IF('Daily PnL Log'!N1319<>"",'Daily PnL Log'!N1319,"") | O68: =IF(C68<>"",O67+C68,"") | P68: =IF(D68<>"",P67+D68,"") | Q68: =IF(E68<>"",Q67+E68,"") | R68: =IF(F68<>"",R67+F68,"") | S68: =IF(G68<>"",S67+G68,"") | T68: =IF(H68<>"",T67+H68,"") | U68: =IF(I68<>"",U67+I68,"") | V68: =IF(J68<>"",V67+J68,"") | W68: =IF('Daily PnL Log'!W1319<>"",'Daily PnL Log'!W1319,"") | X68: =IF('Daily PnL Log'!X1319<>"",'Daily PnL Log'!X1319,"") | Y68: =IF('Daily PnL Log'!Y1319<>"",'Daily PnL Log'!Y1319,"") | Z68: =IF('Daily PnL Log'!Z1319<>"",'Daily PnL Log'!Z1319,"") | AA68: =IF('Daily PnL Log'!AC1319<>"",'Daily PnL Log'!AC1319,"")

Sheet January 2026
A2: Month To Date PnL
A7: Trading PnL | B7: =J48 -> -49446.8
A8: Commissions | B8: =K48 -> -1847.43
A9: Exchange Fees | B9: =L48 -> -15506.26
A10: Expenses | B10: =Y48 -> -20958.95
A11: NET PNL | B11: =B7+(B8+B9+B10) -> -87759.44
A14: Average Margin | B14: =W48 -> 643823.35
A15: RoM | B15: =B11/B14 -> -0.13630981
A16: Std Dev | B16: =X48 -> -0.0060165594
A17: Sharpe | B17: =B15/B16 -> 22.655774
B48: TOTALS | C48: =SUM(C50:C74) -> 61881.2 | D48: =SUM(D50:D74) -> 24673.2 | E48: =SUM(E50:E74) -> 0 | F48: =SUM(F50:F74) -> -125236.4 | G48: =SUM(G50:G74) -> -10764.8 | H48: =SUM(H50:H74) -> 0 | I48: =SUM(I50:I74) -> 0 | J48: =SUM(J50:J74) -> -49446.8 | ... N48: =SUM(N50:N74) -> -66800.49 | W48: =AVERAGE(W50:W74) -> 643823.35 | X48: =AVERAGE(X50:X74) -> -0.0060165594 | Y48: =SUM(Y50:Y69) -> -20958.95 | Z48: =SUM(Z50:Z69) -> 0
A49: Month | B49: Date | C49: Beans | D49: Meal | E49: Oil | F49: Corn | G49: Wheat | H49: KC Wheat | I49: Brent | J49: Total PnL | K49: Commissions | L49: Clr/brk fees | M49: Total Fees | N49: Net PnL | O49: Cum Beans | P49: Cum Meal | Q49: Cum Oil | R49: Cum Corn | S49: Cum Wheat | T49: Cum KC | U49: Cum Brent | V49: Cum PnL | W49: Margin | X49: RoM | Y49: Expenses | Z49: Distributions | AA49: Net Liq
A50: =TEXT(B50,"mmm") -> Jan | B50: ='Daily PnL Log'!B1281 -> 46024 | C50: =IF('Daily PnL Log'!C1281<>"",'Daily PnL Log'!C1281,"") -> 22511 | D50: =IF('Daily PnL Log'!D1281<>"",'Daily PnL Log'!D1281,"") -> -2103.6 | E50: =IF('Daily PnL Log'!E1281<>"",'Daily PnL Log'!E1281,"") -> 0 | F50: =IF('Daily PnL Log'!F1281<>"",'Daily PnL Log'!F1281,"") -> 6684.9 | G50: =IF('Daily PnL Log'!G1281<>"",'Daily PnL Log'!G1281,"") -> -5901.8 | H50: =IF('Daily PnL Log'!H1281<>"",'Daily PnL Log'!H1281,"") -> 0 | I50: =IF('Daily PnL Log'!I1281<>"",'Daily PnL Log'!I1281,"") -> 0 | J50: =IF('Daily PnL Log'!J1281<>"",'Daily PnL Log'!J1281,"") -> 21190.5 | ... N50: =IF('Daily PnL Log'!N1281<>"",'Daily PnL Log'!N1281,"") -> 20804.18 | O50: =C50 -> 22511 | P50: =D50 -> -2103.6 | Q50: =E50 -> 0 | R50: =F50 -> 6684.9 | S50: =G50 -> -5901.8 | T50: =H50 -> 0 | U50: =I50 -> 0 | V50: =SUM(O50:T50) -> 21190.5 | W50: =IF('Daily PnL Log'!W1281<>"",'Daily PnL Log'!W1281,"") -> 494970 | X50: =IF('Daily PnL Log'!X1281<>"",'Daily PnL Log'!X1281,"") -> 0.042031194 | Y50: =IF('Daily PnL Log'!Y1281<>"",'Daily PnL Log'!Y1281,"") | Z50: =IF('Daily PnL Log'!Z1281<>"",'Daily PnL Log'!Z1281,"") | AA50: =IF('Daily PnL Log'!AC1281<>"",'Daily PnL Log'!AC1281,"") -> 289426.9
A51: =TEXT(B51,"mmm") -> Jan | B51: ='Daily PnL Log'!B1282 -> 46027 | C51: =IF('Daily PnL Log'!C1282<>"",'Daily PnL Log'!C1282,"") -> 30643.6 | D51: =IF('Daily PnL Log'!D1282<>"",'Daily PnL Log'!D1282,"") -> -5802.9 | E51: =IF('Daily PnL Log'!E1282<>"",'Daily PnL Log'!E1282,"") -> 0 | F51: =IF('Daily PnL Log'!F1282<>"",'Daily PnL Log'!F1282,"") -> -2260.1 | G51: =IF('Daily PnL Log'!G1282<>"",'Daily PnL Log'!G1282,"") -> -19309.3 | H51: =IF('Daily PnL Log'!H1282<>"",'Daily PnL Log'!H1282,"") -> 0 | I51: =IF('Daily PnL Log'!I1282<>"",'Daily PnL Log'!I1282,"") -> 0 | J51: =IF('Daily PnL Log'!J1282<>"",'Daily PnL Log'!J1282,"") -> 3271.3 | ... N51: =IF('Daily PnL Log'!N1282<>"",'Daily PnL Log'!N1282,"") -> 2730.87 | O51: =IF(C51<>"",O50+C51,"") -> 53154.6 | P51: =IF(D51<>"",P50+D51,"") -> -7906.5 | Q51: =IF(E51<>"",Q50+E51,"") -> 0 | R51: =IF(F51<>"",R50+F51,"") -> 4424.8 | S51: =IF(G51<>"",S50+G51,"") -> -25211.1 | T51: =IF(H51<>"",T50+H51,"") -> 0 | U51: =IF(I51<>"",U50+I51,"") -> 0 | V51: =IF(J51<>"",V50+J51,"") -> 24461.8 | W51: =IF('Daily PnL Log'!W1282<>"",'Daily PnL Log'!W1282,"") -> 465552 | X51: =IF('Daily PnL Log'!X1282<>"",'Daily PnL Log'!X1282,"") -> 0.0058658753 | Y51: =IF('Daily PnL Log'!Y1282<>"",'Daily PnL Log'!Y1282,"") -> -5908.56 | Z51: =IF('Daily PnL Log'!Z1282<>"",'Daily PnL Log'!Z1282,"") | AA51: =IF('Daily PnL Log'!AC1282<>"",'Daily PnL Log'!AC1282,"") -> 53948.25
A52: =TEXT(B52,"mmm") -> Jan | B52: ='Daily PnL Log'!B1283 -> 46028 | C52: =IF('Daily PnL Log'!C1283<>"",'Daily PnL Log'!C1283,"") -> 12639.6 | D52: =IF('Daily PnL Log'!D1283<>"",'Daily PnL Log'!D1283,"") -> 5190.6 | E52: =IF('Daily PnL Log'!E1283<>"",'Daily PnL Log'!E1283,"") -> 0 | F52: =IF('Daily PnL Log'!F1283<>"",'Daily PnL Log'!F1283,"") -> 3803.4 | G52: =IF('Daily PnL Log'!G1283<>"",'Daily PnL Log'!G1283,"") -> -6787.1 | H52: =IF('Daily PnL Log'!H1283<>"",'Daily PnL Log'!H1283,"") -> 0 | I52: =IF('Daily PnL Log'!I1283<>"",'Daily PnL Log'!I1283,"") -> 0 | J52: =IF('Daily PnL Log'!J1283<>"",'Daily PnL Log'!J1283,"") -> 14846.5 | ... N52: =IF('Daily PnL Log'!N1283<>"",'Daily PnL Log'!N1283,"") -> 14244.29 | O52: =IF(C52<>"",O51+C52,"") -> 65794.2 | P52: =IF(D52<>"",P51+D52,"") -> -2715.9 | Q52: =IF(E52<>"",Q51+E52,"") -> 0 | R52: =IF(F52<>"",R51+F52,"") -> 8228.2 | S52: =IF(G52<>"",S51+G52,"") -> -31998.2 | T52: =IF(H52<>"",T51+H52,"") -> 0 | U52: =IF(I52<>"",U51+I52,"") -> 0 | V52: =IF(J52<>"",V51+J52,"") -> 39308.3 | W52: =IF('Daily PnL Log'!W1283<>"",'Daily PnL Log'!W1283,"") -> 504295 | X52: =IF('Daily PnL Log'!X1283<>"",'Daily PnL Log'!X1283,"") -> 0.028245947 | Y52: =IF('Daily PnL Log'!Y1283<>"",'Daily PnL Log'!Y1283,"") | Z52: =IF('Daily PnL Log'!Z1283<>"",'Daily PnL Log'!Z1283,"") | AA52: =IF('Daily PnL Log'!AC1283<>"",'Daily PnL Log'!AC1283,"") -> 74301.04
A53: =TEXT(B53,"mmm") -> Jan | B53: ='Daily PnL Log'!B1284 -> 46029 | C53: =IF('Daily PnL Log'!C1284<>"",'Daily PnL Log'!C1284,"") -> 25296.3 | D53: =IF('Daily PnL Log'!D1284<>"",'Daily PnL Log'!D1284,"") -> 11912.6 | E53: =IF('Daily PnL Log'!E1284<>"",'Daily PnL Log'!E1284,"") -> 0 | F53: =IF('Daily PnL Log'!F1284<>"",'Daily PnL Log'!F1284,"") -> 4230.8 | G53: =IF('Daily PnL Log'!G1284<>"",'Daily PnL Log'!G1284,"") -> -3114.6 | H53: =IF('Daily PnL Log'!H1284<>"",'Daily PnL Log'!H1284,"") -> 0 | I53: =IF('Daily PnL Log'!I1284<>"",'Daily PnL Log'!I1284,"") -> 0 | J53: =IF('Daily PnL Log'!J1284<>"",'Daily PnL Log'!J1284,"") -> 38325.1 | ... N53: =IF('Daily PnL Log'!N1284<>"",'Daily PnL Log'!N1284,"") -> 37871.4 | O53: =IF(C53<>"",O52+C53,"") -> 91090.5 | P53: =IF(D53<>"",P52+D53,"") -> 9196.7 | Q53: =IF(E53<>"",Q52+E53,"") -> 0 | R53: =IF(F53<>"",R52+F53,"") -> 12459 | S53: =IF(G53<>"",S52+G53,"") -> -35112.8 | T53: =IF(H53<>"",T52+H53,"") -> 0 | U53: =IF(I53<>"",U52+I53,"") -> 0 | V53: =IF(J53<>"",V52+J53,"") -> 77633.4 | W53: =IF('Daily PnL Log'!W1284<>"",'Daily PnL Log'!W1284,"") -> 518237 | X53: =IF('Daily PnL Log'!X1284<>"",'Daily PnL Log'!X1284,"") -> 0.073077376 | Y53: =IF('Daily PnL Log'!Y1284<>"",'Daily PnL Log'!Y1284,"") | Z53: =IF('Daily PnL Log'!Z1284<>"",'Daily PnL Log'!Z1284,"") | AA53: =IF('Daily PnL Log'!AC1284<>"",'Daily PnL Log'!AC1284,"") -> 94209.84
A54: =TEXT(B54,"mmm") -> Jan | B54: ='Daily PnL Log'!B1285 -> 46030 | C54: =IF('Daily PnL Log'!C1285<>"",'Daily PnL Log'!C1285,"") -> -9742.6 | D54: =IF('Daily PnL Log'!D1285<>"",'Daily PnL Log'!D1285,"") -> -7136 | E54: =IF('Daily PnL Log'!E1285<>"",'Daily PnL Log'!E1285,"") -> 0 | F54: =IF('Daily PnL Log'!F1285<>"",'Daily PnL Log'!F1285,"") -> -5227.2 | G54: =IF('Daily PnL Log'!G1285<>"",'Daily PnL Log'!G1285,"") -> 8633.6 | H54: =IF('Daily PnL Log'!H1285<>"",'Daily PnL Log'!H1285,"") -> 0 | I54: =IF('Daily PnL Log'!I1285<>"",'Daily PnL Log'!I1285,"") -> 0 | J54: =IF('Daily PnL Log'!J1285<>"",'Daily PnL Log'!J1285,"") -> -13472.2 | ... N54: =IF('Daily PnL Log'!N1285<>"",'Daily PnL Log'!N1285,"") -> -14427.64 | O54: =IF(C54<>"",O53+C54,"") -> 81347.9 | P54: =IF(D54<>"",P53+D54,"") -> 2060.7 | Q54: =IF(E54<>"",Q53+E54,"") -> 0 | R54: =IF(F54<>"",R53+F54,"") -> 7231.8 | S54: =IF(G54<>"",S53+G54,"") -> -26479.2 | T54: =IF(H54<>"",T53+H54,"") -> 0 | U54: =IF(I54<>"",U53+I54,"") -> 0 | V54: =IF(J54<>"",V53+J54,"") -> 64161.2 | W54: =IF('Daily PnL Log'!W1285<>"",'Daily PnL Log'!W1285,"") -> 589490 | X54: =IF('Daily PnL Log'!X1285<>"",'Daily PnL Log'!X1285,"") -> -0.024474783 | Y54: =IF('Daily PnL Log'!Y1285<>"",'Daily PnL Log'!Y1285,"") | Z54: =IF('Daily PnL Log'!Z1285<>"",'Daily PnL Log'!Z1285,"") | AA54: =IF('Daily PnL Log'!AC1285<>"",'Daily PnL Log'!AC1285,"") -> 108435.65
A55: =TEXT(B55,"mmm") -> Jan | B55: ='Daily PnL Log'!B1286 -> 46031 | C55: =IF('Daily PnL Log'!C1286<>"",'Daily PnL Log'!C1286,"") -> 1612.9 | D55: =IF('Daily PnL Log'!D1286<>"",'Daily PnL Log'!D1286,"") -> 4726.4 | E55: =IF('Daily PnL Log'!E1286<>"",'Daily PnL Log'!E1286,"") -> 0 | F55: =IF('Daily PnL Log'!F1286<>"",'Daily PnL Log'!F1286,"") -> -5952.5 | G55: =IF('Daily PnL Log'!G1286<>"",'Daily PnL Log'!G1286,"") -> -2494.8 | H55: =IF('Daily PnL Log'!H1286<>"",'Daily PnL Log'!H1286,"") -> 0 | I55: =IF('Daily PnL Log'!I1286<>"",'Daily PnL Log'!I1286,"") -> 0 | J55: =IF('Daily PnL Log'!J1286<>"",'Daily PnL Log'!J1286,"") -> -2108 | ... N55: =IF('Daily PnL Log'!N1286<>"",'Daily PnL Log'!N1286,"") -> -3526.17 | O55: =IF(C55<>"",O54+C55,"") -> 82960.8 | P55: =IF(D55<>"",P54+D55,"") -> 6787.1 | Q55: =IF(E55<>"",Q54+E55,"") -> 0 | R55: =IF(F55<>"",R54+F55,"") -> 1279.3 | S55: =IF(G55<>"",S54+G55,"") -> -28974 | T55: =IF(H55<>"",T54+H55,"") -> 0 | U55: =IF(I55<>"",U54+I55,"") -> 0 | V55: =IF(J55<>"",V54+J55,"") -> 62053.2 | W55: =IF('Daily PnL Log'!W1286<>"",'Daily PnL Log'!W1286,"") -> 562260 | X55: =IF('Daily PnL Log'!X1286<>"",'Daily PnL Log'!X1286,"") -> -0.0062714225 | Y55: =IF('Daily PnL Log'!Y1286<>"",'Daily PnL Log'!Y1286,"") | Z55: =IF('Daily PnL Log'!Z1286<>"",'Daily PnL Log'!Z1286,"") | AA55: =IF('Daily PnL Log'!AC1286<>"",'Daily PnL Log'!AC1286,"") -> 74684.98
A56: =TEXT(B56,"mmm") -> Jan | B56: ='Daily PnL Log'!B1287 -> 46034 | C56: =IF('Daily PnL Log'!C1287<>"",'Daily PnL Log'!C1287,"") -> -32546.3 | D56: =IF('Daily PnL Log'!D1287<>"",'Daily PnL Log'!D1287,"") -> 4261.2 | E56: =IF('Daily PnL Log'!E1287<>"",'Daily PnL Log'!E1287,"") -> 0 | F56: =IF('Daily PnL Log'!F1287<>"",'Daily PnL Log'!F1287,"") -> -113515.1 | G56: =IF('Daily PnL Log'!G1287<>"",'Daily PnL Log'!G1287,"") -> 14792.5 | H56: =IF('Daily PnL Log'!H1287<>"",'Daily PnL Log'!H1287,"") -> 0 | I56: =IF('Daily PnL Log'!I1287<>"",'Daily PnL Log'!I1287,"") -> 0 | J56: =IF('Daily PnL Log'!J1287<>"",'Daily PnL Log'!J1287,"") -> -127007.7 | ... N56: =IF('Daily PnL Log'!N1287<>"",'Daily PnL Log'!N1287,"") -> -129507.38 | O56: =IF(C56<>"",O55+C56,"") -> 50414.5 | P56: =IF(D56<>"",P55+D56,"") -> 11048.3 | Q56: =IF(E56<>"",Q55+E56,"") -> 0 | R56: =IF(F56<>"",R55+F56,"") -> -112235.8 | S56: =IF(G56<>"",S55+G56,"") -> -14181.5 | T56: =IF(H56<>"",T55+H56,"") -> 0 | U56: =IF(I56<>"",U55+I56,"") -> 0 | V56: =IF(J56<>"",V55+J56,"") -> -64954.5 | W56: =IF('Daily PnL Log'!W1287<>"",'Daily PnL Log'!W1287,"") -> 485862 | X56: =IF('Daily PnL Log'!X1287<>"",'Daily PnL Log'!X1287,"") -> -0.26655178 | Y56: =IF('Daily PnL Log'!Y1287<>"",'Daily PnL Log'!Y1287,"") -> -329.5 | Z56: =IF('Daily PnL Log'!Z1287<>"",'Daily PnL Log'!Z1287,"") | AA56: =IF('Daily PnL Log'!AC1287<>"",'Daily PnL Log'!AC1287,"") -> -19479.7
A57: =TEXT(B57,"mmm") -> Jan | B57: ='Daily PnL Log'!B1288 -> 46035 | C57: =IF('Daily PnL Log'!C1288<>"",'Daily PnL Log'!C1288,"") -> 568.3 | D57: =IF('Daily PnL Log'!D1288<>"",'Daily PnL Log'!D1288,"") -> 42148.2 | E57: =IF('Daily PnL Log'!E1288<>"",'Daily PnL Log'!E1288,"") -> 0 | F57: =IF('Daily PnL Log'!F1288<>"",'Daily PnL Log'!F1288,"") -> 2901.5 | G57: =IF('Daily PnL Log'!G1288<>"",'Daily PnL Log'!G1288,"") -> 7433.8 | H57: =IF('Daily PnL Log'!H1288<>"",'Daily PnL Log'!H1288,"") -> 0 | I57: =IF('Daily PnL Log'!I1288<>"",'Daily PnL Log'!I1288,"") -> 0 | J57: =IF('Daily PnL Log'!J1288<>"",'Daily PnL Log'!J1288,"") -> 53051.8 | ... N57: =IF('Daily PnL Log'!N1288<>"",'Daily PnL Log'!N1288,"") -> 51931.55 | O57: =IF(C57<>"",O56+C57,"") -> 50982.8 | P57: =IF(D57<>"",P56+D57,"") -> 53196.5 | Q57: =IF(E57<>"",Q56+E57,"") -> 0 | R57: =IF(F57<>"",R56+F57,"") -> -109334.3 | S57: =IF(G57<>"",S56+G57,"") -> -6747.7 | T57: =IF(H57<>"",T56+H57,"") -> 0 | U57: =IF(I57<>"",U56+I57,"") -> 0 | V57: =IF(J57<>"",V56+J57,"") -> -11902.7 | W57: =IF('Daily PnL Log'!W1288<>"",'Daily PnL Log'!W1288,"") -> 504410 | X57: =IF('Daily PnL Log'!X1288<>"",'Daily PnL Log'!X1288,"") -> 0.10295504 | Y57: =IF('Daily PnL Log'!Y1288<>"",'Daily PnL Log'!Y1288,"") | Z57: =IF('Daily PnL Log'!Z1288<>"",'Daily PnL Log'!Z1288,"") | AA57: =IF('Daily PnL Log'!AC1288<>"",'Daily PnL Log'!AC1288,"") -> 21252.55
A58: =TEXT(B58,"mmm") -> Jan | B58: ='Daily PnL Log'!B1289 -> 46036 | C58: =IF('Daily PnL Log'!C1289<>"",'Daily PnL Log'!C1289,"") -> -11063.6 | D58: =IF('Daily PnL Log'!D1289<>"",'Daily PnL Log'!D1289,"") -> -5351.8 | E58: =IF('Daily PnL Log'!E1289<>"",'Daily PnL Log'!E1289,"") -> 0 | F58: =IF('Daily PnL Log'!F1289<>"",'Daily PnL Log'!F1289,"") -> 1321.6 | G58: =IF('Daily PnL Log'!G1289<>"",'Daily PnL Log'!G1289,"") -> -2076.5 | H58: =IF('Daily PnL Log'!H1289<>"",'Daily PnL Log'!H1289,"") -> 0 | I58: =IF('Daily PnL Log'!I1289<>"",'Daily PnL Log'!I1289,"") -> 0 | J58: =IF('Daily PnL Log'!J1289<>"",'Daily PnL Log'!J1289,"") -> -17170.3 | ... N58: =IF('Daily PnL Log'!N1289<>"",'Daily PnL Log'!N1289,"") -> -17790.54 | O58: =IF(C58<>"",O57+C58,"") -> 39919.2 | P58: =IF(D58<>"",P57+D58,"") -> 47844.7 | Q58: =IF(E58<>"",Q57+E58,"") -> 0 | R58: =IF(F58<>"",R57+F58,"") -> -108012.7 | S58: =IF(G58<>"",S57+G58,"") -> -8824.2 | T58: =IF(H58<>"",T57+H58,"") -> 0 | U58: =IF(I58<>"",U57+I58,"") -> 0 | V58: =IF(J58<>"",V57+J58,"") -> -29073 | W58: =IF('Daily PnL Log'!W1289<>"",'Daily PnL Log'!W1289,"") -> 595475 | X58: =IF('Daily PnL Log'!X1289<>"",'Daily PnL Log'!X1289,"") -> -0.029876216 | Y58: =IF('Daily PnL Log'!Y1289<>"",'Daily PnL Log'!Y1289,"") -> -5276.68 | Z58: =IF('Daily PnL Log'!Z1289<>"",'Daily PnL Log'!Z1289,"") | AA58: =IF('Daily PnL Log'!AC1289<>"",'Daily PnL Log'!AC1289,"") -> 9553.18
A59: =TEXT(B59,"mmm") -> Jan | B59: ='Daily PnL Log'!B1290 -> 46037 | C59: =IF('Daily PnL Log'!C1290<>"",'Daily PnL Log'!C1290,"") -> -6370.6 | D59: =IF('Daily PnL Log'!D1290<>"",'Daily PnL Log'!D1290,"") -> 2741.7 | E59: =IF('Daily PnL Log'!E1290<>"",'Daily PnL Log'!E1290,"") -> 0 | F59: =IF('Daily PnL Log'!F1290<>"",'Daily PnL Log'!F1290,"") -> -13099.9 | G59: =IF('Daily PnL Log'!G1290<>"",'Daily PnL Log'!G1290,"") -> 700.4 | H59: =IF('Daily PnL Log'!H1290<>"",'Daily PnL Log'!H1290,"") -> 0 | I59: =IF('Daily PnL Log'!I1290<>"",'Daily PnL Log'!I1290,"") -> 0 | J59: =IF('Daily PnL Log'!J1290<>"",'Daily PnL Log'!J1290,"") -> -16028.4 | ... N59: =IF('Daily PnL Log'!N1290<>"",'Daily PnL Log'!N1290,"") -> -16656.1 | O59: =IF(C59<>"",O58+C59,"") -> 33548.6 | P59: =IF(D59<>"",P58+D59,"") -> 50586.4 | Q59: =IF(E59<>"",Q58+E59,"") -> 0 | R59: =IF(F59<>"",R58+F59,"") -> -121112.6 | S59: =IF(G59<>"",S58+G59,"") -> -8123.8 | T59: =IF(H59<>"",T58+H59,"") -> 0 | U59: =IF(I59<>"",U58+I59,"") -> 0 | V59: =IF(J59<>"",V58+J59,"") -> -45101.4 | W59: =IF('Daily PnL Log'!W1290<>"",'Daily PnL Log'!W1290,"") -> 649048 | X59: =IF('Daily PnL Log'!X1290<>"",'Daily PnL Log'!X1290,"") -> -0.025662355 | Y59: =IF('Daily PnL Log'!Y1290<>"",'Daily PnL Log'!Y1290,"") | Z59: =IF('Daily PnL Log'!Z1290<>"",'Daily PnL Log'!Z1290,"") | AA59: =IF('Daily PnL Log'!AC1290<>"",'Daily PnL Log'!AC1290,"") -> -15774.52
A60: =TEXT(B60,"mmm") -> Jan | B60: ='Daily PnL Log'!B1291 -> 46038 | C60: =IF('Daily PnL Log'!C1291<>"",'Daily PnL Log'!C1291,"") -> 25688.7 | D60: =IF('Daily PnL Log'!D1291<>"",'Daily PnL Log'!D1291,"") -> -12081.3 | E60: =IF('Daily PnL Log'!E1291<>"",'Daily PnL Log'!E1291,"") -> 0 | F60: =IF('Daily PnL Log'!F1291<>"",'Daily PnL Log'!F1291,"") -> -2583.3 | G60: =IF('Daily PnL Log'!G1291<>"",'Daily PnL Log'!G1291,"") -> -5760.5 | H60: =IF('Daily PnL Log'!H1291<>"",'Daily PnL Log'!H1291,"") -> 0 | I60: =IF('Daily PnL Log'!I1291<>"",'Daily PnL Log'!I1291,"") -> 0 | J60: =IF('Daily PnL Log'!J1291<>"",'Daily PnL Log'!J1291,"") -> 5263.6 | ... N60: =IF('Daily PnL Log'!N1291<>"",'Daily PnL Log'!N1291,"") -> 4841.31 | O60: =IF(C60<>"",O59+C60,"") -> 59237.3 | P60: =IF(D60<>"",P59+D60,"") -> 38505.1 | Q60: =IF(E60<>"",Q59+E60,"") -> 0 | R60: =IF(F60<>"",R59+F60,"") -> -123695.9 | S60: =IF(G60<>"",S59+G60,"") -> -13884.3 | T60: =IF(H60<>"",T59+H60,"") -> 0 | U60: =IF(I60<>"",U59+I60,"") -> 0 | V60: =IF(J60<>"",V59+J60,"") -> -39837.8 | W60: =IF('Daily PnL Log'!W1291<>"",'Daily PnL Log'!W1291,"") -> 726725 | X60: =IF('Daily PnL Log'!X1291<>"",'Daily PnL Log'!X1291,"") -> 0.0066618184 | Y60: =IF('Daily PnL Log'!Y1291<>"",'Daily PnL Log'!Y1291,"") | Z60: =IF('Daily PnL Log'!Z1291<>"",'Daily PnL Log'!Z1291,"") | AA60: =IF('Daily PnL Log'!AC1291<>"",'Daily PnL Log'!AC1291,"") -> -29986.81
A61: =TEXT(B61,"mmm") -> Jan | B61: ='Daily PnL Log'!B1292 -> 46042 | C61: =IF('Daily PnL Log'!C1292<>"",'Daily PnL Log'!C1292,"") -> -10510.6 | D61: =IF('Daily PnL Log'!D1292<>"",'Daily PnL Log'!D1292,"") -> -3232.4 | E61: =IF('Daily PnL Log'!E1292<>"",'Daily PnL Log'!E1292,"") -> 0 | F61: =IF('Daily PnL Log'!F1292<>"",'Daily PnL Log'!F1292,"") -> -25436.1 | G61: =IF('Daily PnL Log'!G1292<>"",'Daily PnL Log'!G1292,"") -> -1976.9 | H61: =IF('Daily PnL Log'!H1292<>"",'Daily PnL Log'!H1292,"") -> 0 | I61: =IF('Daily PnL Log'!I1292<>"",'Daily PnL Log'!I1292,"") -> 0 | J61: =IF('Daily PnL Log'!J1292<>"",'Daily PnL Log'!J1292,"") -> -41156 | ... N61: =IF('Daily PnL Log'!N1292<>"",'Daily PnL Log'!N1292,"") -> -41499.1 | O61: =IF(C61<>"",O60+C61,"") -> 48726.7 | P61: =IF(D61<>"",P60+D61,"") -> 35272.7 | Q61: =IF(E61<>"",Q60+E61,"") -> 0 | R61: =IF(F61<>"",R60+F61,"") -> -149132 | S61: =IF(G61<>"",S60+G61,"") -> -15861.2 | T61: =IF(H61<>"",T60+H61,"") -> 0 | U61: =IF(I61<>"",U60+I61,"") -> 0 | V61: =IF(J61<>"",V60+J61,"") -> -80993.8 | W61: =IF('Daily PnL Log'!W1292<>"",'Daily PnL Log'!W1292,"") -> 686096 | X61: =IF('Daily PnL Log'!X1292<>"",'Daily PnL Log'!X1292,"") -> -0.06048585 | Y61: =IF('Daily PnL Log'!Y1292<>"",'Daily PnL Log'!Y1292,"") | Z61: =IF('Daily PnL Log'!Z1292<>"",'Daily PnL Log'!Z1292,"") | AA61: =IF('Daily PnL Log'!AC1292<>"",'Daily PnL Log'!AC1292,"") -> -52157.41
A62: =TEXT(B62,"mmm") -> Jan | B62: ='Daily PnL Log'!B1293 -> 46043 | C62: =IF('Daily PnL Log'!C1293<>"",'Daily PnL Log'!C1293,"") -> 28757.5 | D62: =IF('Daily PnL Log'!D1293<>"",'Daily PnL Log'!D1293,"") -> -22309.5 | E62: =IF('Daily PnL Log'!E1293<>"",'Daily PnL Log'!E1293,"") -> 0 | F62: =IF('Daily PnL Log'!F1293<>"",'Daily PnL Log'!F1293,"") -> -35551.5 | G62: =IF('Daily PnL Log'!G1293<>"",'Daily PnL Log'!G1293,"") -> -4108.5 | H62: =IF('Daily PnL Log'!H1293<>"",'Daily PnL Log'!H1293,"") -> 0 | I62: =IF('Daily PnL Log'!I1293<>"",'Daily PnL Log'!I1293,"") -> 0 | J62: =IF('Daily PnL Log'!J1293<>"",'Daily PnL Log'!J1293,"") -> -33212 | ... N62: =IF('Daily PnL Log'!N1293<>"",'Daily PnL Log'!N1293,"") -> -34293.1 | O62: =IF(C62<>"",O61+C62,"") -> 77484.2 | P62: =IF(D62<>"",P61+D62,"") -> 12963.2 | Q62: =IF(E62<>"",Q61+E62,"") -> 0 | R62: =IF(F62<>"",R61+F62,"") -> -184683.5 | S62: =IF(G62<>"",S61+G62,"") -> -19969.7 | T62: =IF(H62<>"",T61+H62,"") -> 0 | U62: =IF(I62<>"",U61+I62,"") -> 0 | V62: =IF(J62<>"",V61+J62,"") -> -114205.8 | W62: =IF('Daily PnL Log'!W1293<>"",'Daily PnL Log'!W1293,"") -> 728236 | X62: =IF('Daily PnL Log'!X1293<>"",'Daily PnL Log'!X1293,"") -> -0.047090641 | Y62: =IF('Daily PnL Log'!Y1293<>"",'Daily PnL Log'!Y1293,"") -> -4179.83 | Z62: =IF('Daily PnL Log'!Z1293<>"",'Daily PnL Log'!Z1293,"") | AA62: =IF('Daily PnL Log'!AC1293<>"",'Daily PnL Log'!AC1293,"") -> -81976.01
... A69: =TEXT(B69,"mmm") -> Jan | B69: ='Daily PnL Log'!B1300 -> 46052 | C69: =IF('Daily PnL Log'!C1300<>"",'Daily PnL Log'!C1300,"") -> -2679.8 | D69: =IF('Daily PnL Log'!D1300<>"",'Daily PnL Log'!D1300,"") -> 6673.4 | E69: =IF('Daily PnL Log'!E1300<>"",'Daily PnL Log'!E1300,"") -> 0 | F69: =IF('Daily PnL Log'!F1300<>"",'Daily PnL Log'!F1300,"") -> 14676.9 | G69: =IF('Daily PnL Log'!G1300<>"",'Daily PnL Log'!G1300,"") -> 7510.6 | H69: =IF('Daily PnL Log'!H1300<>"",'Daily PnL Log'!H1300,"") -> 0 | I69: =IF('Daily PnL Log'!I1300<>"",'Daily PnL Log'!I1300,"") -> 0 | J69: =IF('Daily PnL Log'!J1300<>"",'Daily PnL Log'!J1300,"") -> 26181.1 | ... N69: =IF('Daily PnL Log'!N1300<>"",'Daily PnL Log'!N1300,"") -> 25532.23 | O69: =IF(C69<>"",O68+C69,"") -> 61881.2 | P69: =IF(D69<>"",P68+D69,"") -> 24673.2 | Q69: =IF(E69<>"",Q68+E69,"") -> 0 | R69: =IF(F69<>"",R68+F69,"") -> -125236.4 | S69: =IF(G69<>"",S68+G69,"") -> -10764.8 | T69: =IF(H69<>"",T68+H69,"") -> 0 | U69: =IF(I69<>"",U68+I69,"") -> 0 | V69: =IF(J69<>"",V68+J69,"") -> -49446.8 | W69: =IF('Daily PnL Log'!W1300<>"",'Daily PnL Log'!W1300,"") -> 807719 | X69: =IF('Daily PnL Log'!X1300<>"",'Daily PnL Log'!X1300,"") -> 0.031610288 | Y69: =IF('Daily PnL Log'!Y1300<>"",'Daily PnL Log'!Y1300,"") | Z69: =IF('Daily PnL Log'!Z1300<>"",'Daily PnL Log'!Z1300,"") | AA69: =IF('Daily PnL Log'!AC1300<>"",'Daily PnL Log'!AC1300,"") -> -58636.57

Sheet Yr 2025
A2: YTD PnL
A7: Trading PnL | B7: =J48 -> 590598.8
A8: Commissions | B8: =K48 -> -25351.82
A9: Exchange Fees | B9: =L48 -> -204474.88
A10: Expenses | B10: =Y48 -> -247991.37
A11: Interest | B11: =Z48 -> 73731.18
A12: NET PNL | B12: =B7+(B8+B9+B10+B11) -> 186511.91
A14: Average Margin | B14: =W48 -> 493254.24
A15: RoM | B15: =B12/B14 -> 0.3781253
A16: Std Dev | B16: =X48 -> 0.088891813
A17: Sharpe | B17: =(B15-0.045)/B16 -> 3.7475364
B48: TOTALS | C48: =SUM(C50:C297) -> 312252.8 | D48: =SUM(D50:D297) -> 45974.8 | E48: =SUM(E50:E297) -> 0 | F48: =SUM(F50:F297) -> 228309.1 | G48: =SUM(G50:G297) -> 4062.1 | H48: =SUM(H50:H297) -> 0 | I48: =SUM(I50:I297) -> 0 | J48: =SUM(J50:J297) -> 590598.8 | ... N48: =SUM(N50:N297) -> 360772.1 | W48: =AVERAGE(W50:W295) -> 493254.24 | X48: =_xlfn.STDEV.P(X50:X295) -> 0.088891813 | Y48: =SUM(Y50:Y295) -> -247991.37 | Z48: =SUM(Z50:Z295) -> 73731.18 | AA48: =SUM(AA50:AA295) -> -724838.7 | AB48: =SUM(AB50:AB295) -> 0
A49: Month | B49: Date | C49: Beans | D49: Meal | E49: Oil | F49: Corn | G49: Wheat | H49: KC Wheat | I49: Brent | J49: Total PnL | K49: Commissions | L49: Clr/brk fees | M49: Total Fees | N49: Net PnL | O49: Cum Beans | P49: Cum Meal | Q49: Cum Oil | R49: Cum Corn | S49: Cum Wheat | T49: Cum KC | U49: Cum Brent | V49: Cum PnL | W49: Margin | X49: RoM | Y49: Expenses | Z49: Int | AA49: Distributions | AB49: Bonuses | AC49: Net Liq
A50: =TEXT(B50,"mmm") -> Jan | B50: ='Daily PnL Log'!B1030 -> 45659 | C50: ='Daily PnL Log'!C1030 -> 3331 | D50: ='Daily PnL Log'!D1030 -> 7649.5 | E50: ='Daily PnL Log'!E1030 -> 0 | F50: ='Daily PnL Log'!F1030 -> -2447.3 | G50: ='Daily PnL Log'!G1030 -> 456.8 | H50: ='Daily PnL Log'!H1030 -> 0 | I50: ='Daily PnL Log'!I1030 -> 0 | ... N50: ='Daily PnL Log'!N1030 -> 8751.91 | O50: =C50 -> 3331 | P50: =D50 -> 7649.5 | Q50: =E50 -> 0 | R50: =F50 -> -2447.3 | S50: =G50 -> 456.8 | T50: =H50 -> 0 | U50: =I50 -> 0 | V50: =SUM(O50:T50) -> 8990 | W50: =IF('Daily PnL Log'!W1030<>"",'Daily PnL Log'!W1030,"") -> 609826 | X50: =IF('Daily PnL Log'!X1030<>"",'Daily PnL Log'!X1030,"") -> 0.014351487 | Y50: =IF('Daily PnL Log'!Y1030<>"",'Daily PnL Log'!Y1030,"") -> -6165.26 | Z50: =IF('Daily PnL Log'!Z1030<>"",'Daily PnL Log'!Z1030,"") | AA50: =IF('Daily PnL Log'!AA1030<>"",'Daily PnL Log'!AA1030,"") | AB50: =IF('Daily PnL Log'!AB1030<>"",'Daily PnL Log'!AB1030,"") | AC50: =IF('Daily PnL Log'!AC1030<>"",'Daily PnL Log'!AC1030,"") -> 742485.61
A51: =TEXT(B51,"mmm") -> Jan | B51: ='Daily PnL Log'!B1031 -> 45660 | C51: ='Daily PnL Log'!C1031 -> 26317.2 | D51: ='Daily PnL Log'!D1031 -> 5461.6 | E51: ='Daily PnL Log'!E1031 -> 0 | F51: ='Daily PnL Log'!F1031 -> 8454.8 | G51: ='Daily PnL Log'!G1031 -> 71791.9 | H51: ='Daily PnL Log'!H1031 -> 0 | I51: ='Daily PnL Log'!I1031 -> 0 | ... N51: ='Daily PnL Log'!N1031 -> 111165.66 | O51: =IF(C51<>"",O50+C51,"") -> 29648.2 | P51: =IF(D51<>"",P50+D51,"") -> 13111.1 | Q51: =IF(E51<>"",Q50+E51,"") -> 0 | R51: =IF(F51<>"",R50+F51,"") -> 6007.5 | S51: =IF(G51<>"",S50+G51,"") -> 72248.7 | T51: =IF(H51<>"",T50+H51,"") -> 0 | U51: =IF(I51<>"",U50+I51,"") -> 0 | V51: =IF(J51<>"",V50+J51,"") -> 121015.5 | W51: =IF('Daily PnL Log'!W1031<>"",'Daily PnL Log'!W1031,"") -> 511648 | X51: =IF('Daily PnL Log'!X1031<>"",'Daily PnL Log'!X1031,"") -> 0.2172698 | Y51: =IF('Daily PnL Log'!Y1031<>"",'Daily PnL Log'!Y1031,"") | Z51: =IF('Daily PnL Log'!Z1031<>"",'Daily PnL Log'!Z1031,"") | AA51: =IF('Daily PnL Log'!AA1031<>"",'Daily PnL Log'!AA1031,"") -> -724838.7 | AB51: =IF('Daily PnL Log'!AB1031<>"",'Daily PnL Log'!AB1031,"") | AC51: =IF('Daily PnL Log'!AC1031<>"",'Daily PnL Log'!AC1031,"") -> 122923.32
A52: =TEXT(B52,"mmm") -> Jan | B52: ='Daily PnL Log'!B1032 -> 45663 | C52: ='Daily PnL Log'!C1032 -> 3190.5 | D52: ='Daily PnL Log'!D1032 -> 2188.6 | E52: ='Daily PnL Log'!E1032 -> 0 | F52: ='Daily PnL Log'!F1032 -> 4137.8 | G52: ='Daily PnL Log'!G1032 -> -1459.3 | H52: ='Daily PnL Log'!H1032 -> 0 | I52: ='Daily PnL Log'!I1032 -> 0 | ... N52: ='Daily PnL Log'!N1032 -> 6962.75 | O52: =IF(C52<>"",O51+C52,"") -> 32838.7 | P52: =IF(D52<>"",P51+D52,"") -> 15299.7 | Q52: =IF(E52<>"",Q51+E52,"") -> 0 | R52: =IF(F52<>"",R51+F52,"") -> 10145.3 | S52: =IF(G52<>"",S51+G52,"") -> 70789.4 | T52: =IF(H52<>"",T51+H52,"") -> 0 | U52: =IF(I52<>"",U51+I52,"") -> 0 | V52: =IF(J52<>"",V51+J52,"") -> 129073.1 | W52: =IF('Daily PnL Log'!W1032<>"",'Daily PnL Log'!W1032,"") -> 513854 | X52: =IF('Daily PnL Log'!X1032<>"",'Daily PnL Log'!X1032,"") -> 0.013550055 | Y52: =IF('Daily PnL Log'!Y1032<>"",'Daily PnL Log'!Y1032,"") | Z52: =IF('Daily PnL Log'!Z1032<>"",'Daily PnL Log'!Z1032,"") | AA52: =IF('Daily PnL Log'!AA1032<>"",'Daily PnL Log'!AA1032,"") | AB52: =IF('Daily PnL Log'!AB1032<>"",'Daily PnL Log'!AB1032,"") | AC52: =IF('Daily PnL Log'!AC1032<>"",'Daily PnL Log'!AC1032,"") -> 92605.97
A53: =TEXT(B53,"mmm") -> Jan | B53: ='Daily PnL Log'!B1033 -> 45664 | C53: ='Daily PnL Log'!C1033 -> -15065.7 | D53: ='Daily PnL Log'!D1033 -> -1916.3 | E53: ='Daily PnL Log'!E1033 -> 0 | F53: ='Daily PnL Log'!F1033 -> 5447 | G53: ='Daily PnL Log'!G1033 -> 13752.6 | H53: ='Daily PnL Log'!H1033 -> 0 | I53: ='Daily PnL Log'!I1033 -> 0 | ... N53: ='Daily PnL Log'!N1033 -> 1206.06 | O53: =IF(C53<>"",O52+C53,"") -> 17773 | P53: =IF(D53<>"",P52+D53,"") -> 13383.4 | Q53: =IF(E53<>"",Q52+E53,"") -> 0 | R53: =IF(F53<>"",R52+F53,"") -> 15592.3 | S53: =IF(G53<>"",S52+G53,"") -> 84542 | T53: =IF(H53<>"",T52+H53,"") -> 0 | U53: =IF(I53<>"",U52+I53,"") -> 0 | V53: =IF(J53<>"",V52+J53,"") -> 131290.7 | W53: =IF('Daily PnL Log'!W1033<>"",'Daily PnL Log'!W1033,"") -> 486965 | X53: =IF('Daily PnL Log'!X1033<>"",'Daily PnL Log'!X1033,"") -> 0.0024766872 | Y53: =IF('Daily PnL Log'!Y1033<>"",'Daily PnL Log'!Y1033,"") | Z53: =IF('Daily PnL Log'!Z1033<>"",'Daily PnL Log'!Z1033,"") | AA53: =IF('Daily PnL Log'!AA1033<>"",'Daily PnL Log'!AA1033,"") | AB53: =IF('Daily PnL Log'!AB1033<>"",'Daily PnL Log'!AB1033,"") | AC53: =IF('Daily PnL Log'!AC1033<>"",'Daily PnL Log'!AC1033,"") -> 118295.68
A54: =TEXT(B54,"mmm") -> Jan | B54: ='Daily PnL Log'!B1034 -> 45665 | C54: ='Daily PnL Log'!C1034 -> 347.9 | D54: ='Daily PnL Log'!D1034 -> 1252.5 | E54: ='Daily PnL Log'!E1034 -> 0 | F54: ='Daily PnL Log'!F1034 -> 19068 | G54: ='Daily PnL Log'!G1034 -> 32396 | H54: ='Daily PnL Log'!H1034 -> 0 | I54: ='Daily PnL Log'!I1034 -> 0 | ... N54: ='Daily PnL Log'!N1034 -> 51235.22 | O54: =IF(C54<>"",O53+C54,"") -> 18120.9 | P54: =IF(D54<>"",P53+D54,"") -> 14635.9 | Q54: =IF(E54<>"",Q53+E54,"") -> 0 | R54: =IF(F54<>"",R53+F54,"") -> 34660.3 | S54: =IF(G54<>"",S53+G54,"") -> 116938 | T54: =IF(H54<>"",T53+H54,"") -> 0 | U54: =IF(I54<>"",U53+I54,"") -> 0 | V54: =IF(J54<>"",V53+J54,"") -> 184355.1 | W54: =IF('Daily PnL Log'!W1034<>"",'Daily PnL Log'!W1034,"") -> 437490 | X54: =IF('Daily PnL Log'!X1034<>"",'Daily PnL Log'!X1034,"") -> 0.11711175 | Y54: =IF('Daily PnL Log'!Y1034<>"",'Daily PnL Log'!Y1034,"") -> -284 | Z54: =IF('Daily PnL Log'!Z1034<>"",'Daily PnL Log'!Z1034,"") | AA54: =IF('Daily PnL Log'!AA1034<>"",'Daily PnL Log'!AA1034,"") | AB54: =IF('Daily PnL Log'!AB1034<>"",'Daily PnL Log'!AB1034,"") | AC54: =IF('Daily PnL Log'!AC1034<>"",'Daily PnL Log'!AC1034,"") -> 168025.75
A55: =TEXT(B55,"mmm") -> Jan | B55: ='Daily PnL Log'!B1035 -> 45666 | C55: ='Daily PnL Log'!C1035 -> -10519.2 | D55: ='Daily PnL Log'!D1035 -> 478.2 | E55: ='Daily PnL Log'!E1035 -> 0 | F55: ='Daily PnL Log'!F1035 -> 6622.1 | G55: ='Daily PnL Log'!G1035 -> 12135.9 | H55: ='Daily PnL Log'!H1035 -> 0 | I55: ='Daily PnL Log'!I1035 -> 0 | ... N55: ='Daily PnL Log'!N1035 -> 7142.75 | O55: =IF(C55<>"",O54+C55,"") -> 7601.7 | P55: =IF(D55<>"",P54+D55,"") -> 15114.1 | Q55: =IF(E55<>"",Q54+E55,"") -> 0 | R55: =IF(F55<>"",R54+F55,"") -> 41282.4 | S55: =IF(G55<>"",S54+G55,"") -> 129073.9 | T55: =IF(H55<>"",T54+H55,"") -> 0 | U55: =IF(I55<>"",U54+I55,"") -> 0 | V55: =IF(J55<>"",V54+J55,"") -> 193072.1 | W55: =IF('Daily PnL Log'!W1035<>"",'Daily PnL Log'!W1035,"") -> 503460 | X55: =IF('Daily PnL Log'!X1035<>"",'Daily PnL Log'!X1035,"") -> 0.014187324 | Y55: =IF('Daily PnL Log'!Y1035<>"",'Daily PnL Log'!Y1035,"") | Z55: =IF('Daily PnL Log'!Z1035<>"",'Daily PnL Log'!Z1035,"") | AA55: =IF('Daily PnL Log'!AA1035<>"",'Daily PnL Log'!AA1035,"") | AB55: =IF('Daily PnL Log'!AB1035<>"",'Daily PnL Log'!AB1035,"") | AC55: =IF('Daily PnL Log'!AC1035<>"",'Daily PnL Log'!AC1035,"") -> 196831.5
A56: =TEXT(B56,"mmm") -> Jan | B56: ='Daily PnL Log'!B1036 -> 45667 | C56: ='Daily PnL Log'!C1036 -> 84627.6 | D56: ='Daily PnL Log'!D1036 -> 29598.9 | E56: ='Daily PnL Log'!E1036 -> 0 | F56: ='Daily PnL Log'!F1036 -> 28168.5 | G56: ='Daily PnL Log'!G1036 -> 20215.4 | H56: ='Daily PnL Log'!H1036 -> 0 | I56: ='Daily PnL Log'!I1036 -> 0 | ... N56: ='Daily PnL Log'!N1036 -> 158711.71 | O56: =IF(C56<>"",O55+C56,"") -> 92229.3 | P56: =IF(D56<>"",P55+D56,"") -> 44713 | Q56: =IF(E56<>"",Q55+E56,"") -> 0 | R56: =IF(F56<>"",R55+F56,"") -> 69450.9 | S56: =IF(G56<>"",S55+G56,"") -> 149289.3 | T56: =IF(H56<>"",T55+H56,"") -> 0 | U56: =IF(I56<>"",U55+I56,"") -> 0 | V56: =IF(J56<>"",V55+J56,"") -> 355682.5 | W56: =IF('Daily PnL Log'!W1036<>"",'Daily PnL Log'!W1036,"") -> 572855 | X56: =IF('Daily PnL Log'!X1036<>"",'Daily PnL Log'!X1036,"") -> 0.2770539 | Y56: =IF('Daily PnL Log'!Y1036<>"",'Daily PnL Log'!Y1036,"") | Z56: =IF('Daily PnL Log'!Z1036<>"",'Daily PnL Log'!Z1036,"") | AA56: =IF('Daily PnL Log'!AA1036<>"",'Daily PnL Log'!AA1036,"") | AB56: =IF('Daily PnL Log'!AB1036<>"",'Daily PnL Log'!AB1036,"") | AC56: =IF('Daily PnL Log'!AC1036<>"",'Daily PnL Log'!AC1036,"") -> 336042.41
A57: =TEXT(B57,"mmm") -> Jan | B57: ='Daily PnL Log'!B1037 -> 45670 | C57: ='Daily PnL Log'!C1037 -> 8706 | D57: ='Daily PnL Log'!D1037 -> -25087.2 | E57: ='Daily PnL Log'!E1037 -> 0 | F57: ='Daily PnL Log'!F1037 -> -3629.2 | G57: ='Daily PnL Log'!G1037 -> -21274.3 | H57: ='Daily PnL Log'!H1037 -> 0 | I57: ='Daily PnL Log'!I1037 -> 0 | ... N57: ='Daily PnL Log'!N1037 -> -43270.49 | O57: =IF(C57<>"",O56+C57,"") -> 100935.3 | P57: =IF(D57<>"",P56+D57,"") -> 19625.8 | Q57: =IF(E57<>"",Q56+E57,"") -> 0 | R57: =IF(F57<>"",R56+F57,"") -> 65821.7 | S57: =IF(G57<>"",S56+G57,"") -> 128015 | T57: =IF(H57<>"",T56+H57,"") -> 0 | U57: =IF(I57<>"",U56+I57,"") -> 0 | V57: =IF(J57<>"",V56+J57,"") -> 314397.8 | W57: =IF('Daily PnL Log'!W1037<>"",'Daily PnL Log'!W1037,"") -> 705664 | X57: =IF('Daily PnL Log'!X1037<>"",'Daily PnL Log'!X1037,"") -> -0.061318829 | Y57: =IF('Daily PnL Log'!Y1037<>"",'Daily PnL Log'!Y1037,"") | Z57: =IF('Daily PnL Log'!Z1037<>"",'Daily PnL Log'!Z1037,"") | AA57: =IF('Daily PnL Log'!AA1037<>"",'Daily PnL Log'!AA1037,"") | AB57: =IF('Daily PnL Log'!AB1037<>"",'Daily PnL Log'!AB1037,"") | AC57: =IF('Daily PnL Log'!AC1037<>"",'Daily PnL Log'!AC1037,"") -> 309121.62
A58: =TEXT(B58,"mmm") -> Jan | B58: ='Daily PnL Log'!B1038 -> 45671 | C58: ='Daily PnL Log'!C1038 -> -23718 | D58: ='Daily PnL Log'!D1038 -> 24515.1 | E58: ='Daily PnL Log'!E1038 -> 0 | F58: ='Daily PnL Log'!F1038 -> -4119.5 | G58: ='Daily PnL Log'!G1038 -> -22018.8 | H58: ='Daily PnL Log'!H1038 -> 0 | I58: ='Daily PnL Log'!I1038 -> 0 | ... N58: ='Daily PnL Log'!N1038 -> -26466.71 | O58: =IF(C58<>"",O57+C58,"") -> 77217.3 | P58: =IF(D58<>"",P57+D58,"") -> 44140.9 | Q58: =IF(E58<>"",Q57+E58,"") -> 0 | R58: =IF(F58<>"",R57+F58,"") -> 61702.2 | S58: =IF(G58<>"",S57+G58,"") -> 105996.2 | T58: =IF(H58<>"",T57+H58,"") -> 0 | U58: =IF(I58<>"",U57+I58,"") -> 0 | V58: =IF(J58<>"",V57+J58,"") -> 289056.6 | W58: =IF('Daily PnL Log'!W1038<>"",'Daily PnL Log'!W1038,"") -> 666657 | X58: =IF('Daily PnL Log'!X1038<>"",'Daily PnL Log'!X1038,"") -> -0.039700641 | Y58: =IF('Daily PnL Log'!Y1038<>"",'Daily PnL Log'!Y1038,"") | Z58: =IF('Daily PnL Log'!Z1038<>"",'Daily PnL Log'!Z1038,"") | AA58: =IF('Daily PnL Log'!AA1038<>"",'Daily PnL Log'!AA1038,"") | AB58: =IF('Daily PnL Log'!AB1038<>"",'Daily PnL Log'!AB1038,"") | AC58: =IF('Daily PnL Log'!AC1038<>"",'Daily PnL Log'!AC1038,"") -> 289703.61
A59: =TEXT(B59,"mmm") -> Jan | B59: ='Daily PnL Log'!B1039 -> 45672 | C59: ='Daily PnL Log'!C1039 -> -18887.8 | D59: ='Daily PnL Log'!D1039 -> 547.8 | E59: ='Daily PnL Log'!E1039 -> 0 | F59: ='Daily PnL Log'!F1039 -> 21737.7 | G59: ='Daily PnL Log'!G1039 -> -11791.8 | H59: ='Daily PnL Log'!H1039 -> 0 | I59: ='Daily PnL Log'!I1039 -> 0 | ... N59: ='Daily PnL Log'!N1039 -> -9189.35 | O59: =IF(C59<>"",O58+C59,"") -> 58329.5 | P59: =IF(D59<>"",P58+D59,"") -> 44688.7 | Q59: =IF(E59<>"",Q58+E59,"") -> 0 | R59: =IF(F59<>"",R58+F59,"") -> 83439.9 | S59: =IF(G59<>"",S58+G59,"") -> 94204.4 | T59: =IF(H59<>"",T58+H59,"") -> 0 | U59: =IF(I59<>"",U58+I59,"") -> 0 | V59: =IF(J59<>"",V58+J59,"") -> 280662.5 | W59: =IF('Daily PnL Log'!W1039<>"",'Daily PnL Log'!W1039,"") -> 692862 | X59: =IF('Daily PnL Log'!X1039<>"",'Daily PnL Log'!X1039,"") -> -0.013262886 | Y59: =IF('Daily PnL Log'!Y1039<>"",'Daily PnL Log'!Y1039,"") -> -5646.84 | Z59: =IF('Daily PnL Log'!Z1039<>"",'Daily PnL Log'!Z1039,"") -> 19877.41 | AA59: =IF('Daily PnL Log'!AA1039<>"",'Daily PnL Log'!AA1039,"") | AB59: =IF('Daily PnL Log'!AB1039<>"",'Daily PnL Log'!AB1039,"") | AC59: =IF('Daily PnL Log'!AC1039<>"",'Daily PnL Log'!AC1039,"") -> 260978.36
A60: =TEXT(B60,"mmm") -> Jan | B60: ='Daily PnL Log'!B1040 -> 45673 | C60: ='Daily PnL Log'!C1040 -> -21597.6 | D60: ='Daily PnL Log'!D1040 -> -9550.8 | E60: ='Daily PnL Log'!E1040 -> 0 | F60: ='Daily PnL Log'!F1040 -> 6118 | G60: ='Daily PnL Log'!G1040 -> 14941 | H60: ='Daily PnL Log'!H1040 -> 0 | I60: ='Daily PnL Log'!I1040 -> 0 | ... N60: ='Daily PnL Log'!N1040 -> -11468.89 | O60: =IF(C60<>"",O59+C60,"") -> 36731.9 | P60: =IF(D60<>"",P59+D60,"") -> 35137.9 | Q60: =IF(E60<>"",Q59+E60,"") -> 0 | R60: =IF(F60<>"",R59+F60,"") -> 89557.9 | S60: =IF(G60<>"",S59+G60,"") -> 109145.4 | T60: =IF(H60<>"",T59+H60,"") -> 0 | U60: =IF(I60<>"",U59+I60,"") -> 0 | V60: =IF(J60<>"",V59+J60,"") -> 270573.1 | W60: =IF('Daily PnL Log'!W1040<>"",'Daily PnL Log'!W1040,"") -> 521152 | X60: =IF('Daily PnL Log'!X1040<>"",'Daily PnL Log'!X1040,"") -> -0.022006804 | Y60: =IF('Daily PnL Log'!Y1040<>"",'Daily PnL Log'!Y1040,"") | Z60: =IF('Daily PnL Log'!Z1040<>"",'Daily PnL Log'!Z1040,"") | AA60: =IF('Daily PnL Log'!AA1040<>"",'Daily PnL Log'!AA1040,"") | AB60: =IF('Daily PnL Log'!AB1040<>"",'Daily PnL Log'!AB1040,"") | AC60: =IF('Daily PnL Log'!AC1040<>"",'Daily PnL Log'!AC1040,"") -> 261442.62
A61: =TEXT(B61,"mmm") -> Jan | B61: ='Daily PnL Log'!B1041 -> 45674 | C61: ='Daily PnL Log'!C1041 -> -3136.9 | D61: ='Daily PnL Log'!D1041 -> 628.9 | E61: ='Daily PnL Log'!E1041 -> 0 | F61: ='Daily PnL Log'!F1041 -> -3028.7 | G61: ='Daily PnL Log'!G1041 -> -3748.3 | H61: ='Daily PnL Log'!H1041 -> 0 | I61: ='Daily PnL Log'!I1041 -> 0 | ... N61: ='Daily PnL Log'!N1041 -> -10481.19 | O61: =IF(C61<>"",O60+C61,"") -> 33595 | P61: =IF(D61<>"",P60+D61,"") -> 35766.8 | Q61: =IF(E61<>"",Q60+E61,"") -> 0 | R61: =IF(F61<>"",R60+F61,"") -> 86529.2 | S61: =IF(G61<>"",S60+G61,"") -> 105397.1 | T61: =IF(H61<>"",T60+H61,"") -> 0 | U61: =IF(I61<>"",U60+I61,"") -> 0 | V61: =IF(J61<>"",V60+J61,"") -> 261288.1 | W61: =IF('Daily PnL Log'!W1041<>"",'Daily PnL Log'!W1041,"") -> 563500 | X61: =IF('Daily PnL Log'!X1041<>"",'Daily PnL Log'!X1041,"") -> -0.01860016 | Y61: =IF('Daily PnL Log'!Y1041<>"",'Daily PnL Log'!Y1041,"") | Z61: =IF('Daily PnL Log'!Z1041<>"",'Daily PnL Log'!Z1041,"") | AA61: =IF('Daily PnL Log'!AA1041<>"",'Daily PnL Log'!AA1041,"") | AB61: =IF('Daily PnL Log'!AB1041<>"",'Daily PnL Log'!AB1041,"") | AC61: =IF('Daily PnL Log'!AC1041<>"",'Daily PnL Log'!AC1041,"") -> 235597.68
A62: =TEXT(B62,"mmm") -> Jan | B62: ='Daily PnL Log'!B1042 -> 45678 | C62: ='Daily PnL Log'!C1042 -> 19064.2 | D62: ='Daily PnL Log'!D1042 -> 4303.1 | E62: ='Daily PnL Log'!E1042 -> 0 | F62: ='Daily PnL Log'!F1042 -> 12221.4 | G62: ='Daily PnL Log'!G1042 -> 14441.9 | H62: ='Daily PnL Log'!H1042 -> 0 | I62: ='Daily PnL Log'!I1042 -> 0 | ... N62: ='Daily PnL Log'!N1042 -> 48825.79 | O62: =IF(C62<>"",O61+C62,"") -> 52659.2 | P62: =IF(D62<>"",P61+D62,"") -> 40069.9 | Q62: =IF(E62<>"",Q61+E62,"") -> 0 | R62: =IF(F62<>"",R61+F62,"") -> 98750.6 | S62: =IF(G62<>"",S61+G62,"") -> 119839 | T62: =IF(H62<>"",T61+H62,"") -> 0 | U62: =IF(I62<>"",U61+I62,"") -> 0 | V62: =IF(J62<>"",V61+J62,"") -> 311318.7 | W62: =IF('Daily PnL Log'!W1042<>"",'Daily PnL Log'!W1042,"") -> 608342 | X62: =IF('Daily PnL Log'!X1042<>"",'Daily PnL Log'!X1042,"") -> 0.080260429 | Y62: =IF('Daily PnL Log'!Y1042<>"",'Daily PnL Log'!Y1042,"") | Z62: =IF('Daily PnL Log'!Z1042<>"",'Daily PnL Log'!Z1042,"") | AA62: =IF('Daily PnL Log'!AA1042<>"",'Daily PnL Log'!AA1042,"") | AB62: =IF('Daily PnL Log'!AB1042<>"",'Daily PnL Log'!AB1042,"") | AC62: =IF('Daily PnL Log'!AC1042<>"",'Daily PnL Log'!AC1042,"") -> 302229.12
... A286: =TEXT(B286,"mmm") -> Dec | B286: ='Daily PnL Log'!B1266 -> 46001 | C286: ='Daily PnL Log'!C1266 -> 7542.4 | D286: ='Daily PnL Log'!D1266 -> 16026.5 | E286: ='Daily PnL Log'!E1266 -> 0 | F286: ='Daily PnL Log'!F1266 -> -19720.3 | G286: ='Daily PnL Log'!G1266 -> 31957.2 | H286: ='Daily PnL Log'!H1266 -> 0 | I286: ='Daily PnL Log'!I1266 -> 0 | ... N286: ='Daily PnL Log'!N1266 -> 35112.07 | O286: =IF(C286<>"",O285+C286,"") -> 268793.7 | P286: =IF(D286<>"",P285+D286,"") -> 44465.2 | Q286: =IF(E286<>"",Q285+E286,"") -> 0 | R286: =IF(F286<>"",R285+F286,"") -> 245091 | S286: =IF(G286<>"",S285+G286,"") -> -69609.9 | T286: =IF(H286<>"",T285+H286,"") -> 0 | U286: =IF(I286<>"",U285+I286,"") -> 0 | V286: =IF(J286<>"",V285+J286,"") -> 488740 | W286: =IF('Daily PnL Log'!W1266<>"",'Daily PnL Log'!W1266,"") -> 422688 | X286: =IF('Daily PnL Log'!X1266<>"",'Daily PnL Log'!X1266,"") -> 0.083068528 | Y286: =IF('Daily PnL Log'!Y1266<>"",'Daily PnL Log'!Y1266,"") | Z286: =IF('Daily PnL Log'!Z1266<>"",'Daily PnL Log'!Z1266,"") | AA286: =IF('Daily PnL Log'!AA1266<>"",'Daily PnL Log'!AA1266,"") | AB286: =IF('Daily PnL Log'!AB1266<>"",'Daily PnL Log'!AB1266,"") | AC286: =IF('Daily PnL Log'!AC1266<>"",'Daily PnL Log'!AC1266,"") -> 247929.42
A287: =TEXT(B287,"mmm") -> Dec | B287: ='Daily PnL Log'!B1267 -> 46002 | C287: ='Daily PnL Log'!C1267 -> 679 | D287: ='Daily PnL Log'!D1267 -> 23600.8 | E287: ='Daily PnL Log'!E1267 -> 0 | F287: ='Daily PnL Log'!F1267 -> -13498.6 | G287: ='Daily PnL Log'!G1267 -> 1224.8 | H287: ='Daily PnL Log'!H1267 -> 0 | I287: ='Daily PnL Log'!H1267 -> 0 | J287: ='Daily PnL Log'!J1267 -> 12006 | K287: ='Daily PnL Log'!K1267 -> -64.71 | L287: ='Daily PnL Log'!L1267 -> -571.94 | M287: ='Daily PnL Log'!M1267 -> -636.65 | N287: ='Daily PnL Log'!N1267 -> 11369.35 | O287: =IF(C287<>"",O286+C287,"") -> 269472.7 | P287: =IF(D287<>"",P286+D287,"") -> 68066 | Q287: =IF(E287<>"",Q286+E287,"") -> 0 | R287: =IF(F287<>"",R286+F287,"") -> 231592.4 | S287: =IF(G287<>"",S286+G287,"") -> -68385.1 | T287: =IF(H287<>"",T286+H287,"") -> 0 | U287: =IF(I287<>"",U286+I287,"") -> 0 | V287: =IF(J287<>"",V286+J287,"") -> 500746 | W287: =IF('Daily PnL Log'!W1267<>"",'Daily PnL Log'!W1267,"") -> 461918 | X287: =IF('Daily PnL Log'!X1267<>"",'Daily PnL Log'!X1267,"") -> 0.024613351 | Y287: =IF('Daily PnL Log'!Y1267<>"",'Daily PnL Log'!Y1267,"") | Z287: =IF('Daily PnL Log'!Z1267<>"",'Daily PnL Log'!Z1267,"") | AA287: =IF('Daily PnL Log'!AA1267<>"",'Daily PnL Log'!AA1267,"") | AB287: =IF('Daily PnL Log'!AB1267<>"",'Daily PnL Log'!AB1267,"") | AC287: =IF('Daily PnL Log'!AC1267<>"",'Daily PnL Log'!AC1267,"") -> 278427.77
A288: =TEXT(B288,"mmm") -> Dec | B288: ='Daily PnL Log'!B1268 -> 46003 | C288: ='Daily PnL Log'!C1268 -> -10519.4 | D288: ='Daily PnL Log'!D1268 -> 18351.8 | E288: ='Daily PnL Log'!E1268 -> 0 | F288: ='Daily PnL Log'!F1268 -> -11690.4 | G288: ='Daily PnL Log'!G1268 -> 13735.7 | H288: ='Daily PnL Log'!H1268 -> 0 | I288: ='Daily PnL Log'!I1268 -> 0 | ... N288: ='Daily PnL Log'!N1268 -> 9050.25 | O288: =IF(C288<>"",O287+C288,"") -> 258953.3 | P288: =IF(D288<>"",P287+D288,"") -> 86417.8 | Q288: =IF(E288<>"",Q287+E288,"") -> 0 | R288: =IF(F288<>"",R287+F288,"") -> 219902 | S288: =IF(G288<>"",S287+G288,"") -> -54649.4 | T288: =IF(H288<>"",T287+H288,"") -> 0 | U288: =IF(I288<>"",U287+I288,"") -> 0 | V288: =IF(J288<>"",V287+J288,"") -> 510623.7 | W288: =IF('Daily PnL Log'!W1268<>"",'Daily PnL Log'!W1268,"") -> 359262 | X288: =IF('Daily PnL Log'!X1268<>"",'Daily PnL Log'!X1268,"") -> 0.025191225 | Y288: =IF('Daily PnL Log'!Y1268<>"",'Daily PnL Log'!Y1268,"") | Z288: =IF('Daily PnL Log'!Z1268<>"",'Daily PnL Log'!Z1268,"") | AA288: =IF('Daily PnL Log'!AA1268<>"",'Daily PnL Log'!AA1268,"") | AB288: =IF('Daily PnL Log'!AB1268<>"",'Daily PnL Log'!AB1268,"") | AC288: =IF('Daily PnL Log'!AC1268<>"",'Daily PnL Log'!AC1268,"") -> 239024.07
A289: =TEXT(B289,"mmm") -> Dec | B289: ='Daily PnL Log'!B1269 -> 46006 | C289: ='Daily PnL Log'!C1269 -> -6096.2 | D289: ='Daily PnL Log'!D1269 -> -3702.9 | E289: ='Daily PnL Log'!E1269 -> 0 | F289: ='Daily PnL Log'!F1269 -> -5491.6 | G289: ='Daily PnL Log'!G1269 -> 26672.5 | H289: ='Daily PnL Log'!H1269 -> 0 | I289: ='Daily PnL Log'!I1269 -> 0 | ... N289: ='Daily PnL Log'!N1269 -> 10539.41 | O289: =IF(C289<>"",O288+C289,"") -> 252857.1 | P289: =IF(D289<>"",P288+D289,"") -> 82714.9 | Q289: =IF(E289<>"",Q288+E289,"") -> 0 | R289: =IF(F289<>"",R288+F289,"") -> 214410.4 | S289: =IF(G289<>"",S288+G289,"") -> -27976.9 | T289: =IF(H289<>"",T288+H289,"") -> 0 | U289: =IF(I289<>"",U288+I289,"") -> 0 | V289: =IF(J289<>"",V288+J289,"") -> 522005.5 | W289: =IF('Daily PnL Log'!W1269<>"",'Daily PnL Log'!W1269,"") -> 371398 | X289: =IF('Daily PnL Log'!X1269<>"",'Daily PnL Log'!X1269,"") -> 0.02837767 | Y289: =IF('Daily PnL Log'!Y1269<>"",'Daily PnL Log'!Y1269,"") -> -4025.71 | Z289: =IF('Daily PnL Log'!Z1269<>"",'Daily PnL Log'!Z1269,"") -> 1546.56 | AA289: =IF('Daily PnL Log'!AA1269<>"",'Daily PnL Log'!AA1269,"") | AB289: =IF('Daily PnL Log'!AB1269<>"",'Daily PnL Log'!AB1269,"") | AC289: =IF('Daily PnL Log'!AC1269<>"",'Daily PnL Log'!AC1269,"") -> 275791.68
A290: =TEXT(B290,"mmm") -> Dec | B290: ='Daily PnL Log'!B1270 -> 46007 | C290: ='Daily PnL Log'!C1270 -> 9321.4 | D290: ='Daily PnL Log'!D1270 -> -10567 | E290: ='Daily PnL Log'!E1270 -> 0 | F290: ='Daily PnL Log'!F1270 -> 16543.1 | G290: ='Daily PnL Log'!G1270 -> 43484.4 | H290: ='Daily PnL Log'!H1270 -> 0 | I290: ='Daily PnL Log'!I1270 -> 0 | ... N290: ='Daily PnL Log'!N1270 -> 57453.6 | O290: =IF(C290<>"",O289+C290,"") -> 262178.5 | P290: =IF(D290<>"",P289+D290,"") -> 72147.9 | Q290: =IF(E290<>"",Q289+E290,"") -> 0 | R290: =IF(F290<>"",R289+F290,"") -> 230953.5 | S290: =IF(G290<>"",S289+G290,"") -> 15507.5 | T290: =IF(H290<>"",T289+H290,"") -> 0 | U290: =IF(I290<>"",U289+I290,"") -> 0 | V290: =IF(J290<>"",V289+J290,"") -> 580787.4 | W290: =IF('Daily PnL Log'!W1270<>"",'Daily PnL Log'!W1270,"") -> 301626 | X290: =IF('Daily PnL Log'!X1270<>"",'Daily PnL Log'!X1270,"") -> 0.1904796 | Y290: =IF('Daily PnL Log'!Y1270<>"",'Daily PnL Log'!Y1270,"") -> -5220.58 | Z290: =IF('Daily PnL Log'!Z1270<>"",'Daily PnL Log'!Z1270,"") | AA290: =IF('Daily PnL Log'!AA1270<>"",'Daily PnL Log'!AA1270,"") | AB290: =IF('Daily PnL Log'!AB1270<>"",'Daily PnL Log'!AB1270,"") | AC290: =IF('Daily PnL Log'!AC1270<>"",'Daily PnL Log'!AC1270,"") -> 353757.13
A291: =TEXT(B291,"mmm") -> Dec | B291: ='Daily PnL Log'!B1271 -> 46008 | C291: ='Daily PnL Log'!C1271 -> -13063.9 | D291: ='Daily PnL Log'!D1271 -> 2844.7 | E291: ='Daily PnL Log'!E1271 -> 0 | F291: ='Daily PnL Log'!F1271 -> 18707.4 | G291: ='Daily PnL Log'!G1271 -> 12232.2 | H291: ='Daily PnL Log'!H1271 -> 0 | I291: ='Daily PnL Log'!I1271 -> 0 | ... N291: ='Daily PnL Log'!N1271 -> 19705.65 | O291: =IF(C291<>"",O290+C291,"") -> 249114.6 | P291: =IF(D291<>"",P290+D291,"") -> 74992.6 | Q291: =IF(E291<>"",Q290+E291,"") -> 0 | R291: =IF(F291<>"",R290+F291,"") -> 249660.9 | S291: =IF(G291<>"",S290+G291,"") -> 27739.7 | T291: =IF(H291<>"",T290+H291,"") -> 0 | U291: =IF(I291<>"",U290+I291,"") -> 0 | V291: =IF(J291<>"",V290+J291,"") -> 601507.8 | W291: =IF('Daily PnL Log'!W1271<>"",'Daily PnL Log'!W1271,"") -> 256740 | X291: =IF('Daily PnL Log'!X1271<>"",'Daily PnL Log'!X1271,"") -> 0.07675333 | Y291: =IF('Daily PnL Log'!Y1271<>"",'Daily PnL Log'!Y1271,"") | Z291: =IF('Daily PnL Log'!Z1271<>"",'Daily PnL Log'!Z1271,"") | AA291: =IF('Daily PnL Log'!AA1271<>"",'Daily PnL Log'!AA1271,"") | AB291: =IF('Daily PnL Log'!AB1271<>"",'Daily PnL Log'!AB1271,"") | AC291: =IF('Daily PnL Log'!AC1271<>"",'Daily PnL Log'!AC1271,"") -> 359096.13
A292: =TEXT(B292,"mmm") -> Dec | B292: ='Daily PnL Log'!B1272 -> 46009 | C292: ='Daily PnL Log'!C1272 -> 7778.7 | D292: ='Daily PnL Log'!D1272 -> -13636.8 | E292: ='Daily PnL Log'!E1272 -> 0 | F292: ='Daily PnL Log'!F1272 -> -9429.1 | G292: ='Daily PnL Log'!G1272 -> 591 | H292: ='Daily PnL Log'!H1272 -> 0 | I292: ='Daily PnL Log'!I1272 -> 0 | ... N292: ='Daily PnL Log'!N1272 -> -15287.75 | O292: =IF(C292<>"",O291+C292,"") -> 256893.3 | P292: =IF(D292<>"",P291+D292,"") -> 61355.8 | Q292: =IF(E292<>"",Q291+E292,"") -> 0 | R292: =IF(F292<>"",R291+F292,"") -> 240231.8 | S292: =IF(G292<>"",S291+G292,"") -> 28330.7 | T292: =IF(H292<>"",T291+H292,"") -> 0 | U292: =IF(I292<>"",U291+I292,"") -> 0 | V292: =IF(J292<>"",V291+J292,"") -> 586811.6 | W292: =IF('Daily PnL Log'!W1272<>"",'Daily PnL Log'!W1272,"") -> 293344 | X292: =IF('Daily PnL Log'!X1272<>"",'Daily PnL Log'!X1272,"") -> -0.052115434 | Y292: =IF('Daily PnL Log'!Y1272<>"",'Daily PnL Log'!Y1272,"") | Z292: =IF('Daily PnL Log'!Z1272<>"",'Daily PnL Log'!Z1272,"") | AA292: =IF('Daily PnL Log'!AA1272<>"",'Daily PnL Log'!AA1272,"") | AB292: =IF('Daily PnL Log'!AB1272<>"",'Daily PnL Log'!AB1272,"") | AC292: =IF('Daily PnL Log'!AC1272<>"",'Daily PnL Log'!AC1272,"") -> 350757.08
A293: =TEXT(B293,"mmm") -> Dec | B293: ='Daily PnL Log'!B1273 -> 46010 | C293: ='Daily PnL Log'!C1273 -> -9607 | D293: ='Daily PnL Log'!D1273 -> -763.8 | E293: ='Daily PnL Log'!E1273 -> 0 | F293: ='Daily PnL Log'!F1273 -> 1307.7 | G293: ='Daily PnL Log'!G1273 -> -10596.8 | H293: ='Daily PnL Log'!H1273 -> 0 | I293: ='Daily PnL Log'!I1273 -> 0 | ... N293: ='Daily PnL Log'!N1273 -> -20233.84 | O293: =IF(C293<>"",O292+C293,"") -> 247286.3 | P293: =IF(D293<>"",P292+D293,"") -> 60592 | Q293: =IF(E293<>"",Q292+E293,"") -> 0 | R293: =IF(F293<>"",R292+F293,"") -> 241539.5 | S293: =IF(G293<>"",S292+G293,"") -> 17733.9 | T293: =IF(H293<>"",T292+H293,"") -> 0 | U293: =IF(I293<>"",U292+I293,"") -> 0 | V293: =IF(J293<>"",V292+J293,"") -> 567151.7 | W293: =IF('Daily PnL Log'!W1273<>"",'Daily PnL Log'!W1273,"") -> 322116 | X293: =IF('Daily PnL Log'!X1273<>"",'Daily PnL Log'!X1273,"") -> -0.062815383 | Y293: =IF('Daily PnL Log'!Y1273<>"",'Daily PnL Log'!Y1273,"") | Z293: =IF('Daily PnL Log'!Z1273<>"",'Daily PnL Log'!Z1273,"") | AA293: =IF('Daily PnL Log'!AA1273<>"",'Daily PnL Log'!AA1273,"") | AB293: =IF('Daily PnL Log'!AB1273<>"",'Daily PnL Log'!AB1273,"") | AC293: =IF('Daily PnL Log'!AC1273<>"",'Daily PnL Log'!AC1273,"") -> 341036.89
